{
    "ultimo_valore_indice": 39039.86585862555,
    "variazione_24h_pct": -0.03460269350285117,
    "variazione_7g_pct": -0.13004556461661665,
    "variazione_ytd_pct": -0.28592635135487765,
    "ultima_allocazione_pesi": {
        "BTC": 0.7857953098304716,
        "ETH": 0.13425373127722703,
        "XRP": 0.04554489076048132,
        "SOL": 0.025722813728011197,
        "DOGE": 0.00868325440380884
    },
    "capitalizzazione_mercato": {
        "BTC": 1083881877337.6193,
        "ETH": 182629324655.21622,
        "XRP": 61623752530.011406,
        "SOL": 34152952674.940002,
        "DOGE": 11650325337.7502
    },
    "rendimenti_annuali": {
        "2021": 21.5,
        "2022": -64.9,
        "2023": 128.9,
        "2024": 117.4,
        "2025": -20.4,
        "2026": -28.6
    },
    "benchmark_annuali": {
        "2021": 25.6,
        "2022": -62.1,
        "2023": 149.0,
        "2024": 134.7,
        "2025": -17.4,
        "2026": -25.9
    }
}