{
    "ultimo_valore_indice": 55772.89845726712,
    "variazione_24h_pct": 0.00987994301444095,
    "variazione_7g_pct": 0.041133005038472836,
    "variazione_ytd_pct": -0.1685758278720807,
    "ultima_allocazione_pesi": {
        "BTC": 0.7745037402817124,
        "ETH": 0.1482594826229297,
        "XRP": 0.044622188571913184,
        "SOL": 0.02506941558942624,
        "DOGE": 0.007545172934018515
    },
    "capitalizzazione_mercato": {
        "BTC": 1265563904695.167,
        "ETH": 239140624095.296,
        "XRP": 73291880136.86,
        "SOL": 41505171311.604,
        "DOGE": 12541504470.88
    },
    "rendimenti_annuali": {
        "2021": -8.7,
        "2022": -65.7,
        "2023": 132.2,
        "2024": 117.9,
        "2025": -20.1,
        "2026": -16.9
    },
    "benchmark_annuali": {
        "2021": -23.2,
        "2022": -62.1,
        "2023": 149.0,
        "2024": 134.7,
        "2025": -17.4,
        "2026": -14.9
    }
}