[
    {
        "Date": "2024-09-24",
        "Price": 0.059871,
        "Circulating Supply": 0,
        "Market Cap": 0.0
    },
    {
        "Date": "2024-09-25",
        "Price": 0.059445,
        "Circulating Supply": 0,
        "Market Cap": 0.0
    },
    {
        "Date": "2024-09-27",
        "Price": 0.060879,
        "Circulating Supply": 0,
        "Market Cap": 0.0
    },
    {
        "Date": "2024-09-28",
        "Price": 0.06296,
        "Circulating Supply": 0,
        "Market Cap": 0.0
    },
    {
        "Date": "2024-09-29",
        "Price": 0.063244,
        "Circulating Supply": 0,
        "Market Cap": 0.0
    },
    {
        "Date": "2024-09-30",
        "Price": 0.060983,
        "Circulating Supply": 0,
        "Market Cap": 0.0
    },
    {
        "Date": "2024-10-01",
        "Price": 0.058701,
        "Circulating Supply": 0,
        "Market Cap": 0.0
    },
    {
        "Date": "2024-10-02",
        "Price": 0.056724,
        "Circulating Supply": 0,
        "Market Cap": 0.0
    },
    {
        "Date": "2024-10-03",
        "Price": 0.056562,
        "Circulating Supply": 0,
        "Market Cap": 0.0
    },
    {
        "Date": "2024-10-04",
        "Price": 0.056606,
        "Circulating Supply": 0,
        "Market Cap": 0.0
    },
    {
        "Date": "2024-10-05",
        "Price": 0.059105,
        "Circulating Supply": 0,
        "Market Cap": 0.0
    },
    {
        "Date": "2024-10-06",
        "Price": 0.059168,
        "Circulating Supply": 0,
        "Market Cap": 0.0
    },
    {
        "Date": "2024-10-07",
        "Price": 0.058978,
        "Circulating Supply": 0,
        "Market Cap": 0.0
    },
    {
        "Date": "2024-10-08",
        "Price": 0.058452,
        "Circulating Supply": 0,
        "Market Cap": 0.0
    },
    {
        "Date": "2024-10-09",
        "Price": 0.05839,
        "Circulating Supply": 0,
        "Market Cap": 0.0
    },
    {
        "Date": "2024-10-10",
        "Price": 0.057042,
        "Circulating Supply": 0,
        "Market Cap": 0.0
    },
    {
        "Date": "2024-10-11",
        "Price": 0.05149,
        "Circulating Supply": 0,
        "Market Cap": 0.0
    },
    {
        "Date": "2024-10-12",
        "Price": 0.052203,
        "Circulating Supply": 0,
        "Market Cap": 0.0
    },
    {
        "Date": "2024-10-13",
        "Price": 0.052193,
        "Circulating Supply": 0,
        "Market Cap": 0.0
    },
    {
        "Date": "2024-10-14",
        "Price": 0.050444,
        "Circulating Supply": 0,
        "Market Cap": 0.0
    },
    {
        "Date": "2024-10-15",
        "Price": 0.054187,
        "Circulating Supply": 0,
        "Market Cap": 0.0
    },
    {
        "Date": "2024-10-16",
        "Price": 0.050495,
        "Circulating Supply": 0,
        "Market Cap": 0.0
    },
    {
        "Date": "2024-10-17",
        "Price": 0.049456,
        "Circulating Supply": 0,
        "Market Cap": 0.0
    },
    {
        "Date": "2024-10-18",
        "Price": 0.046367,
        "Circulating Supply": 0,
        "Market Cap": 0.0
    },
    {
        "Date": "2024-10-19",
        "Price": 0.046281,
        "Circulating Supply": 0,
        "Market Cap": 0.0
    },
    {
        "Date": "2024-10-20",
        "Price": 0.046935,
        "Circulating Supply": 0,
        "Market Cap": 0.0
    },
    {
        "Date": "2024-10-21",
        "Price": 0.047389,
        "Circulating Supply": 0,
        "Market Cap": 0.0
    },
    {
        "Date": "2024-10-22",
        "Price": 0.045621,
        "Circulating Supply": 0,
        "Market Cap": 0.0
    },
    {
        "Date": "2024-10-23",
        "Price": 0.04684,
        "Circulating Supply": 0,
        "Market Cap": 0.0
    },
    {
        "Date": "2024-10-24",
        "Price": 0.044607,
        "Circulating Supply": 0,
        "Market Cap": 0.0
    },
    {
        "Date": "2024-10-25",
        "Price": 0.043905,
        "Circulating Supply": 0,
        "Market Cap": 0.0
    },
    {
        "Date": "2024-10-26",
        "Price": 0.040576,
        "Circulating Supply": 0,
        "Market Cap": 0.0
    },
    {
        "Date": "2024-10-27",
        "Price": 0.042351,
        "Circulating Supply": 0,
        "Market Cap": 0.0
    },
    {
        "Date": "2024-10-28",
        "Price": 0.042483,
        "Circulating Supply": 0,
        "Market Cap": 0.0
    },
    {
        "Date": "2024-10-29",
        "Price": 0.043579,
        "Circulating Supply": 0,
        "Market Cap": 0.0
    },
    {
        "Date": "2024-10-30",
        "Price": 0.043761,
        "Circulating Supply": 0,
        "Market Cap": 0.0
    },
    {
        "Date": "2024-10-31",
        "Price": 0.047735,
        "Circulating Supply": 0,
        "Market Cap": 0.0
    },
    {
        "Date": "2024-11-01",
        "Price": 0.048719,
        "Circulating Supply": 0,
        "Market Cap": 0.0
    },
    {
        "Date": "2024-11-02",
        "Price": 0.048744,
        "Circulating Supply": 0,
        "Market Cap": 0.0
    },
    {
        "Date": "2024-11-03",
        "Price": 0.046484,
        "Circulating Supply": 0,
        "Market Cap": 0.0
    },
    {
        "Date": "2024-11-04",
        "Price": 0.045102,
        "Circulating Supply": 0,
        "Market Cap": 0.0
    },
    {
        "Date": "2024-11-05",
        "Price": 0.043835,
        "Circulating Supply": 0,
        "Market Cap": 0.0
    },
    {
        "Date": "2024-11-06",
        "Price": 0.042677,
        "Circulating Supply": 0,
        "Market Cap": 0.0
    },
    {
        "Date": "2024-11-07",
        "Price": 0.053684,
        "Circulating Supply": 0,
        "Market Cap": 0.0
    },
    {
        "Date": "2024-11-08",
        "Price": 0.05807,
        "Circulating Supply": 0,
        "Market Cap": 0.0
    },
    {
        "Date": "2024-11-09",
        "Price": 0.056657,
        "Circulating Supply": 0,
        "Market Cap": 0.0
    },
    {
        "Date": "2024-11-10",
        "Price": 0.057482,
        "Circulating Supply": 0,
        "Market Cap": 0.0
    },
    {
        "Date": "2024-11-11",
        "Price": 0.057444,
        "Circulating Supply": 0,
        "Market Cap": 0.0
    },
    {
        "Date": "2024-11-12",
        "Price": 0.059786,
        "Circulating Supply": 0,
        "Market Cap": 0.0
    },
    {
        "Date": "2024-11-13",
        "Price": 0.060007,
        "Circulating Supply": 0,
        "Market Cap": 0.0
    },
    {
        "Date": "2024-11-14",
        "Price": 0.058761,
        "Circulating Supply": 0,
        "Market Cap": 0.0
    },
    {
        "Date": "2024-11-15",
        "Price": 0.055547,
        "Circulating Supply": 0,
        "Market Cap": 0.0
    },
    {
        "Date": "2024-11-16",
        "Price": 0.055105,
        "Circulating Supply": 0,
        "Market Cap": 0.0
    },
    {
        "Date": "2024-11-17",
        "Price": 0.057747,
        "Circulating Supply": 0,
        "Market Cap": 0.0
    },
    {
        "Date": "2024-11-18",
        "Price": 0.057909,
        "Circulating Supply": 0,
        "Market Cap": 0.0
    },
    {
        "Date": "2024-11-19",
        "Price": 0.060956,
        "Circulating Supply": 0,
        "Market Cap": 0.0
    },
    {
        "Date": "2024-11-20",
        "Price": 0.058698,
        "Circulating Supply": 0,
        "Market Cap": 0.0
    },
    {
        "Date": "2024-11-21",
        "Price": 0.059298,
        "Circulating Supply": 0,
        "Market Cap": 0.0
    },
    {
        "Date": "2024-11-22",
        "Price": 0.065343,
        "Circulating Supply": 0,
        "Market Cap": 0.0
    },
    {
        "Date": "2024-11-23",
        "Price": 0.062454,
        "Circulating Supply": 0,
        "Market Cap": 0.0
    },
    {
        "Date": "2024-11-24",
        "Price": 0.064029,
        "Circulating Supply": 0,
        "Market Cap": 0.0
    },
    {
        "Date": "2024-11-25",
        "Price": 0.069065,
        "Circulating Supply": 0,
        "Market Cap": 0.0
    },
    {
        "Date": "2024-11-26",
        "Price": 0.073521,
        "Circulating Supply": 0,
        "Market Cap": 0.0
    },
    {
        "Date": "2024-11-27",
        "Price": 0.068996,
        "Circulating Supply": 0,
        "Market Cap": 0.0
    },
    {
        "Date": "2024-11-28",
        "Price": 0.073199,
        "Circulating Supply": 0,
        "Market Cap": 0.0
    },
    {
        "Date": "2024-11-29",
        "Price": 0.072163,
        "Circulating Supply": 0,
        "Market Cap": 0.0
    },
    {
        "Date": "2024-11-30",
        "Price": 0.069768,
        "Circulating Supply": 0,
        "Market Cap": 0.0
    },
    {
        "Date": "2024-12-01",
        "Price": 0.072396,
        "Circulating Supply": 0,
        "Market Cap": 0.0
    },
    {
        "Date": "2024-12-02",
        "Price": 0.072556,
        "Circulating Supply": 0,
        "Market Cap": 0.0
    },
    {
        "Date": "2024-12-03",
        "Price": 0.077873,
        "Circulating Supply": 0,
        "Market Cap": 0.0
    },
    {
        "Date": "2024-12-04",
        "Price": 0.091094,
        "Circulating Supply": 0,
        "Market Cap": 0.0
    },
    {
        "Date": "2024-12-05",
        "Price": 0.089648,
        "Circulating Supply": 0,
        "Market Cap": 0.0
    },
    {
        "Date": "2024-12-06",
        "Price": 0.082992,
        "Circulating Supply": 0,
        "Market Cap": 0.0
    },
    {
        "Date": "2024-12-07",
        "Price": 0.085398,
        "Circulating Supply": 0,
        "Market Cap": 0.0
    },
    {
        "Date": "2024-12-08",
        "Price": 0.083792,
        "Circulating Supply": 0,
        "Market Cap": 0.0
    },
    {
        "Date": "2024-12-09",
        "Price": 0.087862,
        "Circulating Supply": 0,
        "Market Cap": 0.0
    },
    {
        "Date": "2024-12-10",
        "Price": 0.074488,
        "Circulating Supply": 0,
        "Market Cap": 0.0
    },
    {
        "Date": "2024-12-11",
        "Price": 0.069357,
        "Circulating Supply": 0,
        "Market Cap": 0.0
    },
    {
        "Date": "2024-12-12",
        "Price": 0.074283,
        "Circulating Supply": 0,
        "Market Cap": 0.0
    },
    {
        "Date": "2024-12-13",
        "Price": 0.080242,
        "Circulating Supply": 0,
        "Market Cap": 0.0
    },
    {
        "Date": "2024-12-14",
        "Price": 0.080826,
        "Circulating Supply": 0,
        "Market Cap": 0.0
    },
    {
        "Date": "2024-12-15",
        "Price": 0.074383,
        "Circulating Supply": 0,
        "Market Cap": 0.0
    },
    {
        "Date": "2024-12-16",
        "Price": 0.0809,
        "Circulating Supply": 0,
        "Market Cap": 0.0
    },
    {
        "Date": "2024-12-17",
        "Price": 0.0761,
        "Circulating Supply": 0,
        "Market Cap": 0.0
    },
    {
        "Date": "2024-12-18",
        "Price": 0.070494,
        "Circulating Supply": 0,
        "Market Cap": 0.0
    },
    {
        "Date": "2024-12-19",
        "Price": 0.06719,
        "Circulating Supply": 0,
        "Market Cap": 0.0
    },
    {
        "Date": "2024-12-20",
        "Price": 0.06632,
        "Circulating Supply": 0,
        "Market Cap": 0.0
    },
    {
        "Date": "2024-12-21",
        "Price": 0.065469,
        "Circulating Supply": 0,
        "Market Cap": 0.0
    },
    {
        "Date": "2024-12-22",
        "Price": 0.06186,
        "Circulating Supply": 0,
        "Market Cap": 0.0
    },
    {
        "Date": "2024-12-23",
        "Price": 0.062982,
        "Circulating Supply": 0,
        "Market Cap": 0.0
    },
    {
        "Date": "2024-12-24",
        "Price": 0.064639,
        "Circulating Supply": 0,
        "Market Cap": 0.0
    },
    {
        "Date": "2024-12-25",
        "Price": 0.066165,
        "Circulating Supply": 0,
        "Market Cap": 0.0
    },
    {
        "Date": "2024-12-26",
        "Price": 0.064585,
        "Circulating Supply": 0,
        "Market Cap": 0.0
    },
    {
        "Date": "2024-12-27",
        "Price": 0.060658,
        "Circulating Supply": 0,
        "Market Cap": 0.0
    },
    {
        "Date": "2024-12-28",
        "Price": 0.060717,
        "Circulating Supply": 0,
        "Market Cap": 0.0
    },
    {
        "Date": "2024-12-29",
        "Price": 0.05953,
        "Circulating Supply": 0,
        "Market Cap": 0.0
    },
    {
        "Date": "2024-12-30",
        "Price": 0.060257,
        "Circulating Supply": 0,
        "Market Cap": 0.0
    },
    {
        "Date": "2024-12-31",
        "Price": 0.059684,
        "Circulating Supply": 0,
        "Market Cap": 0.0
    },
    {
        "Date": "2025-01-01",
        "Price": 0.05777,
        "Circulating Supply": 0,
        "Market Cap": 0.0
    },
    {
        "Date": "2025-01-02",
        "Price": 0.061005,
        "Circulating Supply": 0,
        "Market Cap": 0.0
    },
    {
        "Date": "2025-01-03",
        "Price": 0.062527,
        "Circulating Supply": 0,
        "Market Cap": 0.0
    },
    {
        "Date": "2025-01-04",
        "Price": 0.061627,
        "Circulating Supply": 0,
        "Market Cap": 0.0
    },
    {
        "Date": "2025-01-05",
        "Price": 0.061482,
        "Circulating Supply": 0,
        "Market Cap": 0.0
    },
    {
        "Date": "2025-01-06",
        "Price": 0.0639,
        "Circulating Supply": 0,
        "Market Cap": 0.0
    },
    {
        "Date": "2025-01-07",
        "Price": 0.064928,
        "Circulating Supply": 0,
        "Market Cap": 0.0
    },
    {
        "Date": "2025-01-08",
        "Price": 0.060738,
        "Circulating Supply": 0,
        "Market Cap": 0.0
    },
    {
        "Date": "2025-01-09",
        "Price": 0.059888,
        "Circulating Supply": 0,
        "Market Cap": 0.0
    },
    {
        "Date": "2025-01-10",
        "Price": 0.058818,
        "Circulating Supply": 0,
        "Market Cap": 0.0
    },
    {
        "Date": "2025-01-11",
        "Price": 0.056409,
        "Circulating Supply": 0,
        "Market Cap": 0.0
    },
    {
        "Date": "2025-01-12",
        "Price": 0.055745,
        "Circulating Supply": 0,
        "Market Cap": 0.0
    },
    {
        "Date": "2025-01-13",
        "Price": 0.057907,
        "Circulating Supply": 0,
        "Market Cap": 0.0
    },
    {
        "Date": "2025-01-14",
        "Price": 0.054816,
        "Circulating Supply": 0,
        "Market Cap": 0.0
    },
    {
        "Date": "2025-01-15",
        "Price": 0.055718,
        "Circulating Supply": 0,
        "Market Cap": 0.0
    },
    {
        "Date": "2025-01-16",
        "Price": 0.057581,
        "Circulating Supply": 0,
        "Market Cap": 0.0
    },
    {
        "Date": "2025-01-17",
        "Price": 0.057617,
        "Circulating Supply": 0,
        "Market Cap": 0.0
    },
    {
        "Date": "2025-01-18",
        "Price": 0.056755,
        "Circulating Supply": 0,
        "Market Cap": 0.0
    },
    {
        "Date": "2025-01-19",
        "Price": 0.053463,
        "Circulating Supply": 0,
        "Market Cap": 0.0
    },
    {
        "Date": "2025-01-20",
        "Price": 0.051864,
        "Circulating Supply": 0,
        "Market Cap": 0.0
    },
    {
        "Date": "2025-01-21",
        "Price": 0.051728,
        "Circulating Supply": 0,
        "Market Cap": 0.0
    },
    {
        "Date": "2025-01-22",
        "Price": 0.052048,
        "Circulating Supply": 0,
        "Market Cap": 0.0
    },
    {
        "Date": "2025-01-23",
        "Price": 0.049678,
        "Circulating Supply": 0,
        "Market Cap": 0.0
    },
    {
        "Date": "2025-01-24",
        "Price": 0.05102,
        "Circulating Supply": 0,
        "Market Cap": 0.0
    },
    {
        "Date": "2025-01-25",
        "Price": 0.04835,
        "Circulating Supply": 0,
        "Market Cap": 0.0
    },
    {
        "Date": "2025-01-26",
        "Price": 0.047702,
        "Circulating Supply": 0,
        "Market Cap": 0.0
    },
    {
        "Date": "2025-01-27",
        "Price": 0.047727,
        "Circulating Supply": 0,
        "Market Cap": 0.0
    },
    {
        "Date": "2025-01-28",
        "Price": 0.048019,
        "Circulating Supply": 0,
        "Market Cap": 0.0
    },
    {
        "Date": "2025-01-29",
        "Price": 0.04519,
        "Circulating Supply": 0,
        "Market Cap": 0.0
    },
    {
        "Date": "2025-01-30",
        "Price": 0.044112,
        "Circulating Supply": 0,
        "Market Cap": 0.0
    },
    {
        "Date": "2025-01-31",
        "Price": 0.043231,
        "Circulating Supply": 0,
        "Market Cap": 0.0
    },
    {
        "Date": "2025-02-01",
        "Price": 0.044413,
        "Circulating Supply": 0,
        "Market Cap": 0.0
    },
    {
        "Date": "2025-02-02",
        "Price": 0.041839,
        "Circulating Supply": 0,
        "Market Cap": 0.0
    },
    {
        "Date": "2025-02-03",
        "Price": 0.041379,
        "Circulating Supply": 0,
        "Market Cap": 0.0
    },
    {
        "Date": "2025-02-04",
        "Price": 0.039656,
        "Circulating Supply": 0,
        "Market Cap": 0.0
    },
    {
        "Date": "2025-02-05",
        "Price": 0.036905,
        "Circulating Supply": 0,
        "Market Cap": 0.0
    },
    {
        "Date": "2025-02-06",
        "Price": 0.036741,
        "Circulating Supply": 0,
        "Market Cap": 0.0
    },
    {
        "Date": "2025-02-07",
        "Price": 0.036108,
        "Circulating Supply": 0,
        "Market Cap": 0.0
    },
    {
        "Date": "2025-02-08",
        "Price": 0.035648,
        "Circulating Supply": 0,
        "Market Cap": 0.0
    },
    {
        "Date": "2025-02-09",
        "Price": 0.036215,
        "Circulating Supply": 0,
        "Market Cap": 0.0
    },
    {
        "Date": "2025-02-10",
        "Price": 0.036685,
        "Circulating Supply": 0,
        "Market Cap": 0.0
    },
    {
        "Date": "2025-02-11",
        "Price": 0.03954,
        "Circulating Supply": 0,
        "Market Cap": 0.0
    },
    {
        "Date": "2025-02-12",
        "Price": 0.038372,
        "Circulating Supply": 0,
        "Market Cap": 0.0
    },
    {
        "Date": "2025-02-13",
        "Price": 0.040864,
        "Circulating Supply": 0,
        "Market Cap": 0.0
    },
    {
        "Date": "2025-02-14",
        "Price": 0.039428,
        "Circulating Supply": 0,
        "Market Cap": 0.0
    },
    {
        "Date": "2025-02-15",
        "Price": 0.03868,
        "Circulating Supply": 0,
        "Market Cap": 0.0
    },
    {
        "Date": "2025-02-16",
        "Price": 0.038646,
        "Circulating Supply": 0,
        "Market Cap": 0.0
    },
    {
        "Date": "2025-02-17",
        "Price": 0.039408,
        "Circulating Supply": 0,
        "Market Cap": 0.0
    },
    {
        "Date": "2025-02-18",
        "Price": 0.041643,
        "Circulating Supply": 0,
        "Market Cap": 0.0
    },
    {
        "Date": "2025-02-19",
        "Price": 0.044623,
        "Circulating Supply": 0,
        "Market Cap": 0.0
    },
    {
        "Date": "2025-02-20",
        "Price": 0.046991,
        "Circulating Supply": 0,
        "Market Cap": 0.0
    },
    {
        "Date": "2025-02-21",
        "Price": 0.056789,
        "Circulating Supply": 0,
        "Market Cap": 0.0
    },
    {
        "Date": "2025-02-22",
        "Price": 0.056359,
        "Circulating Supply": 0,
        "Market Cap": 0.0
    },
    {
        "Date": "2025-02-23",
        "Price": 0.058405,
        "Circulating Supply": 0,
        "Market Cap": 0.0
    },
    {
        "Date": "2025-02-24",
        "Price": 0.060572,
        "Circulating Supply": 0,
        "Market Cap": 0.0
    },
    {
        "Date": "2025-02-25",
        "Price": 0.056179,
        "Circulating Supply": 0,
        "Market Cap": 0.0
    },
    {
        "Date": "2025-02-26",
        "Price": 0.066165,
        "Circulating Supply": 0,
        "Market Cap": 0.0
    },
    {
        "Date": "2025-02-27",
        "Price": 0.064623,
        "Circulating Supply": 0,
        "Market Cap": 0.0
    },
    {
        "Date": "2025-02-28",
        "Price": 0.069405,
        "Circulating Supply": 0,
        "Market Cap": 0.0
    },
    {
        "Date": "2025-03-01",
        "Price": 0.060984,
        "Circulating Supply": 0,
        "Market Cap": 0.0
    },
    {
        "Date": "2025-03-02",
        "Price": 0.063709,
        "Circulating Supply": 0,
        "Market Cap": 0.0
    },
    {
        "Date": "2025-03-03",
        "Price": 0.062412,
        "Circulating Supply": 0,
        "Market Cap": 0.0
    },
    {
        "Date": "2025-03-04",
        "Price": 0.057214,
        "Circulating Supply": 0,
        "Market Cap": 0.0
    },
    {
        "Date": "2025-03-05",
        "Price": 0.05356,
        "Circulating Supply": 0,
        "Market Cap": 0.0
    },
    {
        "Date": "2025-03-06",
        "Price": 0.053047,
        "Circulating Supply": 0,
        "Market Cap": 0.0
    },
    {
        "Date": "2025-03-07",
        "Price": 0.049331,
        "Circulating Supply": 0,
        "Market Cap": 0.0
    },
    {
        "Date": "2025-03-08",
        "Price": 0.050436,
        "Circulating Supply": 0,
        "Market Cap": 0.0
    },
    {
        "Date": "2025-03-09",
        "Price": 0.052431,
        "Circulating Supply": 0,
        "Market Cap": 0.0
    },
    {
        "Date": "2025-03-10",
        "Price": 0.045563,
        "Circulating Supply": 0,
        "Market Cap": 0.0
    },
    {
        "Date": "2025-03-11",
        "Price": 0.042722,
        "Circulating Supply": 0,
        "Market Cap": 0.0
    },
    {
        "Date": "2025-03-12",
        "Price": 0.04331,
        "Circulating Supply": 0,
        "Market Cap": 0.0
    },
    {
        "Date": "2025-03-13",
        "Price": 0.043208,
        "Circulating Supply": 0,
        "Market Cap": 0.0
    },
    {
        "Date": "2025-03-14",
        "Price": 0.043487,
        "Circulating Supply": 0,
        "Market Cap": 0.0
    },
    {
        "Date": "2025-03-15",
        "Price": 0.04515,
        "Circulating Supply": 0,
        "Market Cap": 0.0
    },
    {
        "Date": "2025-03-16",
        "Price": 0.046834,
        "Circulating Supply": 0,
        "Market Cap": 0.0
    },
    {
        "Date": "2025-03-17",
        "Price": 0.045169,
        "Circulating Supply": 0,
        "Market Cap": 0.0
    },
    {
        "Date": "2025-03-18",
        "Price": 0.046076,
        "Circulating Supply": 0,
        "Market Cap": 0.0
    },
    {
        "Date": "2025-03-19",
        "Price": 0.048717,
        "Circulating Supply": 0,
        "Market Cap": 0.0
    },
    {
        "Date": "2025-03-20",
        "Price": 0.049506,
        "Circulating Supply": 0,
        "Market Cap": 0.0
    },
    {
        "Date": "2025-03-21",
        "Price": 0.048558,
        "Circulating Supply": 0,
        "Market Cap": 0.0
    },
    {
        "Date": "2025-03-22",
        "Price": 0.047192,
        "Circulating Supply": 0,
        "Market Cap": 0.0
    },
    {
        "Date": "2025-03-23",
        "Price": 0.047681,
        "Circulating Supply": 0,
        "Market Cap": 0.0
    },
    {
        "Date": "2025-03-24",
        "Price": 0.047237,
        "Circulating Supply": 0,
        "Market Cap": 0.0
    },
    {
        "Date": "2025-03-25",
        "Price": 0.049039,
        "Circulating Supply": 0,
        "Market Cap": 0.0
    },
    {
        "Date": "2025-03-26",
        "Price": 0.049809,
        "Circulating Supply": 0,
        "Market Cap": 0.0
    },
    {
        "Date": "2025-03-27",
        "Price": 0.053436,
        "Circulating Supply": 0,
        "Market Cap": 0.0
    },
    {
        "Date": "2025-03-28",
        "Price": 0.056,
        "Circulating Supply": 0,
        "Market Cap": 0.0
    },
    {
        "Date": "2025-03-29",
        "Price": 0.055678,
        "Circulating Supply": 0,
        "Market Cap": 0.0
    },
    {
        "Date": "2025-03-30",
        "Price": 0.050007,
        "Circulating Supply": 0,
        "Market Cap": 0.0
    },
    {
        "Date": "2025-03-31",
        "Price": 0.049535,
        "Circulating Supply": 0,
        "Market Cap": 0.0
    },
    {
        "Date": "2025-04-01",
        "Price": 0.050043,
        "Circulating Supply": 0,
        "Market Cap": 0.0
    },
    {
        "Date": "2025-04-02",
        "Price": 0.053524,
        "Circulating Supply": 0,
        "Market Cap": 0.0
    },
    {
        "Date": "2025-04-03",
        "Price": 0.049046,
        "Circulating Supply": 0,
        "Market Cap": 0.0
    },
    {
        "Date": "2025-04-04",
        "Price": 0.049383,
        "Circulating Supply": 0,
        "Market Cap": 0.0
    },
    {
        "Date": "2025-04-05",
        "Price": 0.051292,
        "Circulating Supply": 0,
        "Market Cap": 0.0
    },
    {
        "Date": "2025-04-06",
        "Price": 0.052146,
        "Circulating Supply": 0,
        "Market Cap": 0.0
    },
    {
        "Date": "2025-04-07",
        "Price": 0.043514,
        "Circulating Supply": 0,
        "Market Cap": 0.0
    },
    {
        "Date": "2025-04-08",
        "Price": 0.047216,
        "Circulating Supply": 0,
        "Market Cap": 0.0
    },
    {
        "Date": "2025-04-09",
        "Price": 0.046674,
        "Circulating Supply": 0,
        "Market Cap": 0.0
    },
    {
        "Date": "2025-04-10",
        "Price": 0.053108,
        "Circulating Supply": 0,
        "Market Cap": 0.0
    },
    {
        "Date": "2025-04-11",
        "Price": 0.04771,
        "Circulating Supply": 0,
        "Market Cap": 0.0
    },
    {
        "Date": "2025-04-12",
        "Price": 0.051351,
        "Circulating Supply": 0,
        "Market Cap": 0.0
    },
    {
        "Date": "2025-04-13",
        "Price": 0.054185,
        "Circulating Supply": 0,
        "Market Cap": 0.0
    },
    {
        "Date": "2025-04-14",
        "Price": 0.049705,
        "Circulating Supply": 0,
        "Market Cap": 0.0
    },
    {
        "Date": "2025-04-15",
        "Price": 0.050893,
        "Circulating Supply": 0,
        "Market Cap": 0.0
    },
    {
        "Date": "2025-04-16",
        "Price": 0.04993,
        "Circulating Supply": 0,
        "Market Cap": 0.0
    },
    {
        "Date": "2025-04-17",
        "Price": 0.04883,
        "Circulating Supply": 0,
        "Market Cap": 0.0
    },
    {
        "Date": "2025-04-18",
        "Price": 0.051986,
        "Circulating Supply": 0,
        "Market Cap": 0.0
    },
    {
        "Date": "2025-04-19",
        "Price": 0.052175,
        "Circulating Supply": 0,
        "Market Cap": 0.0
    },
    {
        "Date": "2025-04-20",
        "Price": 0.053371,
        "Circulating Supply": 0,
        "Market Cap": 0.0
    },
    {
        "Date": "2025-04-21",
        "Price": 0.052282,
        "Circulating Supply": 0,
        "Market Cap": 0.0
    },
    {
        "Date": "2025-04-22",
        "Price": 0.048746,
        "Circulating Supply": 0,
        "Market Cap": 0.0
    },
    {
        "Date": "2025-04-23",
        "Price": 0.053289,
        "Circulating Supply": 0,
        "Market Cap": 0.0
    },
    {
        "Date": "2025-04-24",
        "Price": 0.054591,
        "Circulating Supply": 0,
        "Market Cap": 0.0
    },
    {
        "Date": "2025-04-25",
        "Price": 0.055279,
        "Circulating Supply": 0,
        "Market Cap": 0.0
    },
    {
        "Date": "2025-04-26",
        "Price": 0.057564,
        "Circulating Supply": 0,
        "Market Cap": 0.0
    },
    {
        "Date": "2025-04-27",
        "Price": 0.059087,
        "Circulating Supply": 0,
        "Market Cap": 0.0
    },
    {
        "Date": "2025-04-28",
        "Price": 0.054423,
        "Circulating Supply": 0,
        "Market Cap": 0.0
    },
    {
        "Date": "2025-04-29",
        "Price": 0.055749,
        "Circulating Supply": 0,
        "Market Cap": 0.0
    },
    {
        "Date": "2025-04-30",
        "Price": 0.056044,
        "Circulating Supply": 0,
        "Market Cap": 0.0
    },
    {
        "Date": "2025-05-01",
        "Price": 0.054249,
        "Circulating Supply": 0,
        "Market Cap": 0.0
    },
    {
        "Date": "2025-05-02",
        "Price": 0.056254,
        "Circulating Supply": 0,
        "Market Cap": 0.0
    },
    {
        "Date": "2025-05-03",
        "Price": 0.060622,
        "Circulating Supply": 0,
        "Market Cap": 0.0
    },
    {
        "Date": "2025-05-04",
        "Price": 0.0581,
        "Circulating Supply": 0,
        "Market Cap": 0.0
    },
    {
        "Date": "2025-05-05",
        "Price": 0.056138,
        "Circulating Supply": 0,
        "Market Cap": 0.0
    },
    {
        "Date": "2025-05-06",
        "Price": 0.056926,
        "Circulating Supply": 0,
        "Market Cap": 0.0
    },
    {
        "Date": "2025-05-07",
        "Price": 0.054228,
        "Circulating Supply": 0,
        "Market Cap": 0.0
    },
    {
        "Date": "2025-05-08",
        "Price": 0.055666,
        "Circulating Supply": 0,
        "Market Cap": 0.0
    },
    {
        "Date": "2025-05-09",
        "Price": 0.06307,
        "Circulating Supply": 0,
        "Market Cap": 0.0
    },
    {
        "Date": "2025-05-10",
        "Price": 0.067133,
        "Circulating Supply": 0,
        "Market Cap": 0.0
    },
    {
        "Date": "2025-05-11",
        "Price": 0.072408,
        "Circulating Supply": 0,
        "Market Cap": 0.0
    },
    {
        "Date": "2025-05-12",
        "Price": 0.067721,
        "Circulating Supply": 0,
        "Market Cap": 0.0
    },
    {
        "Date": "2025-05-13",
        "Price": 0.067619,
        "Circulating Supply": 0,
        "Market Cap": 0.0
    },
    {
        "Date": "2025-05-14",
        "Price": 0.070344,
        "Circulating Supply": 0,
        "Market Cap": 0.0
    },
    {
        "Date": "2025-05-15",
        "Price": 0.069537,
        "Circulating Supply": 0,
        "Market Cap": 0.0
    },
    {
        "Date": "2025-05-16",
        "Price": 0.067447,
        "Circulating Supply": 0,
        "Market Cap": 0.0
    },
    {
        "Date": "2025-05-17",
        "Price": 0.070058,
        "Circulating Supply": 0,
        "Market Cap": 0.0
    },
    {
        "Date": "2025-05-18",
        "Price": 0.066843,
        "Circulating Supply": 0,
        "Market Cap": 0.0
    },
    {
        "Date": "2025-05-19",
        "Price": 0.064461,
        "Circulating Supply": 0,
        "Market Cap": 0.0
    },
    {
        "Date": "2025-05-20",
        "Price": 0.064426,
        "Circulating Supply": 0,
        "Market Cap": 0.0
    },
    {
        "Date": "2025-05-21",
        "Price": 0.063561,
        "Circulating Supply": 0,
        "Market Cap": 0.0
    },
    {
        "Date": "2025-05-22",
        "Price": 0.064731,
        "Circulating Supply": 0,
        "Market Cap": 0.0
    },
    {
        "Date": "2025-05-23",
        "Price": 0.064571,
        "Circulating Supply": 0,
        "Market Cap": 0.0
    },
    {
        "Date": "2025-05-24",
        "Price": 0.062955,
        "Circulating Supply": 0,
        "Market Cap": 0.0
    },
    {
        "Date": "2025-05-25",
        "Price": 0.063653,
        "Circulating Supply": 0,
        "Market Cap": 0.0
    },
    {
        "Date": "2025-05-26",
        "Price": 0.060162,
        "Circulating Supply": 0,
        "Market Cap": 0.0
    },
    {
        "Date": "2025-05-27",
        "Price": 0.059428,
        "Circulating Supply": 0,
        "Market Cap": 0.0
    },
    {
        "Date": "2025-05-28",
        "Price": 0.061787,
        "Circulating Supply": 0,
        "Market Cap": 0.0
    },
    {
        "Date": "2025-05-29",
        "Price": 0.063431,
        "Circulating Supply": 0,
        "Market Cap": 0.0
    },
    {
        "Date": "2025-05-30",
        "Price": 0.060408,
        "Circulating Supply": 0,
        "Market Cap": 0.0
    },
    {
        "Date": "2025-05-31",
        "Price": 0.059938,
        "Circulating Supply": 0,
        "Market Cap": 0.0
    },
    {
        "Date": "2025-06-01",
        "Price": 0.060696,
        "Circulating Supply": 0,
        "Market Cap": 0.0
    },
    {
        "Date": "2025-06-02",
        "Price": 0.058975,
        "Circulating Supply": 0,
        "Market Cap": 0.0
    },
    {
        "Date": "2025-06-03",
        "Price": 0.063333,
        "Circulating Supply": 0,
        "Market Cap": 0.0
    },
    {
        "Date": "2025-06-04",
        "Price": 0.068489,
        "Circulating Supply": 0,
        "Market Cap": 0.0
    },
    {
        "Date": "2025-06-05",
        "Price": 0.065089,
        "Circulating Supply": 0,
        "Market Cap": 0.0
    },
    {
        "Date": "2025-06-06",
        "Price": 0.06324,
        "Circulating Supply": 21344674140,
        "Market Cap": 1349832218.4577038
    },
    {
        "Date": "2025-06-07",
        "Price": 0.065732,
        "Circulating Supply": 21348577855,
        "Market Cap": 1403277354.7405689
    },
    {
        "Date": "2025-06-08",
        "Price": 0.068295,
        "Circulating Supply": 21333938476,
        "Market Cap": 1456994563.128271
    },
    {
        "Date": "2025-06-09",
        "Price": 0.064203,
        "Circulating Supply": 21319529078,
        "Market Cap": 1368771207.9598157
    },
    {
        "Date": "2025-06-10",
        "Price": 0.070805,
        "Circulating Supply": 21374565619,
        "Market Cap": 1513430170.0382874
    },
    {
        "Date": "2025-06-11",
        "Price": 0.078238,
        "Circulating Supply": 21316839740,
        "Market Cap": 1667779085.2586968
    },
    {
        "Date": "2025-06-12",
        "Price": 0.074619,
        "Circulating Supply": 21331486311,
        "Market Cap": 1591732370.3712244
    },
    {
        "Date": "2025-06-13",
        "Price": 0.071784,
        "Circulating Supply": 21405131051,
        "Market Cap": 1536550571.5398612
    },
    {
        "Date": "2025-06-14",
        "Price": 0.082888,
        "Circulating Supply": 21334867215,
        "Market Cap": 1768397157.9971712
    },
    {
        "Date": "2025-06-15",
        "Price": 0.080648,
        "Circulating Supply": 21317323043,
        "Market Cap": 1719193324.8937998
    },
    {
        "Date": "2025-06-16",
        "Price": 0.076739,
        "Circulating Supply": 21418659248,
        "Market Cap": 1643642006.3776457
    },
    {
        "Date": "2025-06-17",
        "Price": 0.078459,
        "Circulating Supply": 21324617840,
        "Market Cap": 1673102797.4431615
    },
    {
        "Date": "2025-06-18",
        "Price": 0.073778,
        "Circulating Supply": 21302832851,
        "Market Cap": 1571690396.0533721
    },
    {
        "Date": "2025-06-19",
        "Price": 0.07263,
        "Circulating Supply": 21317291961,
        "Market Cap": 1548280072.6370425
    },
    {
        "Date": "2025-06-20",
        "Price": 0.069569,
        "Circulating Supply": 21320894696,
        "Market Cap": 1483279537.3837068
    },
    {
        "Date": "2025-06-21",
        "Price": 0.071406,
        "Circulating Supply": 21321661844,
        "Market Cap": 1522495098.395756
    },
    {
        "Date": "2025-06-22",
        "Price": 0.06808,
        "Circulating Supply": 21110095699,
        "Market Cap": 1437171948.2444413
    },
    {
        "Date": "2025-06-23",
        "Price": 0.063092,
        "Circulating Supply": 21305315545,
        "Market Cap": 1344195136.0071585
    },
    {
        "Date": "2025-06-24",
        "Price": 0.072792,
        "Circulating Supply": 21307560106,
        "Market Cap": 1551027748.4797719
    },
    {
        "Date": "2025-06-25",
        "Price": 0.071682,
        "Circulating Supply": 21297483939,
        "Market Cap": 1526653284.9688244
    },
    {
        "Date": "2025-06-26",
        "Price": 0.06767,
        "Circulating Supply": 21302050948,
        "Market Cap": 1441512363.8453326
    },
    {
        "Date": "2025-06-27",
        "Price": 0.065244,
        "Circulating Supply": 21287502894,
        "Market Cap": 1388888550.5780857
    },
    {
        "Date": "2025-06-28",
        "Price": 0.073249,
        "Circulating Supply": 21320567797,
        "Market Cap": 1561700263.2608874
    },
    {
        "Date": "2025-06-29",
        "Price": 0.074246,
        "Circulating Supply": 21292604212,
        "Market Cap": 1580899189.5829337
    },
    {
        "Date": "2025-06-30",
        "Price": 0.072061,
        "Circulating Supply": 21288907263,
        "Market Cap": 1534101179.5188985
    },
    {
        "Date": "2025-07-01",
        "Price": 0.068766,
        "Circulating Supply": 21336991955,
        "Market Cap": 1467253185.2911048
    },
    {
        "Date": "2025-07-02",
        "Price": 0.06536,
        "Circulating Supply": 21262584901,
        "Market Cap": 1389722003.4748776
    },
    {
        "Date": "2025-07-03",
        "Price": 0.069966,
        "Circulating Supply": 21282256036,
        "Market Cap": 1489041970.1840098
    },
    {
        "Date": "2025-07-04",
        "Price": 0.068654,
        "Circulating Supply": 21264586979,
        "Market Cap": 1459894347.3437567
    },
    {
        "Date": "2025-07-05",
        "Price": 0.072042,
        "Circulating Supply": 21308965634,
        "Market Cap": 1535131785.1873813
    },
    {
        "Date": "2025-07-06",
        "Price": 0.070764,
        "Circulating Supply": 21321736403,
        "Market Cap": 1508821759.167314
    },
    {
        "Date": "2025-07-07",
        "Price": 0.067417,
        "Circulating Supply": 21305270549,
        "Market Cap": 1436328931.11971
    },
    {
        "Date": "2025-07-08",
        "Price": 0.067346,
        "Circulating Supply": 21287583496,
        "Market Cap": 1433624212.5763369
    },
    {
        "Date": "2025-07-09",
        "Price": 0.068375,
        "Circulating Supply": 21277896189,
        "Market Cap": 1454876576.5344381
    },
    {
        "Date": "2025-07-10",
        "Price": 0.069535,
        "Circulating Supply": 21306952126,
        "Market Cap": 1481575431.101525
    },
    {
        "Date": "2025-07-11",
        "Price": 0.072063,
        "Circulating Supply": 21273685262,
        "Market Cap": 1533054675.304976
    },
    {
        "Date": "2025-07-12",
        "Price": 0.073818,
        "Circulating Supply": 21121926411,
        "Market Cap": 1559186353.5949876
    },
    {
        "Date": "2025-07-13",
        "Price": 0.07268,
        "Circulating Supply": 21280286324,
        "Market Cap": 1546656196.917311
    },
    {
        "Date": "2025-07-14",
        "Price": 0.067162,
        "Circulating Supply": 21233324039,
        "Market Cap": 1426080895.2761533
    },
    {
        "Date": "2025-07-15",
        "Price": 0.066293,
        "Circulating Supply": 21278458227,
        "Market Cap": 1410606488.4352708
    },
    {
        "Date": "2025-07-16",
        "Price": 0.067512,
        "Circulating Supply": 21276801020,
        "Market Cap": 1436448126.7535079
    },
    {
        "Date": "2025-07-17",
        "Price": 0.068927,
        "Circulating Supply": 21278124490,
        "Market Cap": 1466642823.560257
    },
    {
        "Date": "2025-07-18",
        "Price": 0.067637,
        "Circulating Supply": 21295488158,
        "Market Cap": 1440356006.4242594
    },
    {
        "Date": "2025-07-19",
        "Price": 0.078473,
        "Circulating Supply": 21270717291,
        "Market Cap": 1669170735.9083748
    },
    {
        "Date": "2025-07-20",
        "Price": 0.077001,
        "Circulating Supply": 21259347204,
        "Market Cap": 1636992783.1739237
    },
    {
        "Date": "2025-07-21",
        "Price": 0.072152,
        "Circulating Supply": 21263317990,
        "Market Cap": 1534184023.9160042
    },
    {
        "Date": "2025-07-22",
        "Price": 0.074147,
        "Circulating Supply": 21266460096,
        "Market Cap": 1576847306.8503075
    },
    {
        "Date": "2025-07-23",
        "Price": 0.074239,
        "Circulating Supply": 21248721422,
        "Market Cap": 1577484104.662504
    },
    {
        "Date": "2025-07-24",
        "Price": 0.072325,
        "Circulating Supply": 21264355371,
        "Market Cap": 1537950831.9631555
    },
    {
        "Date": "2025-07-25",
        "Price": 0.072046,
        "Circulating Supply": 21307694028,
        "Market Cap": 1535124090.9287403
    },
    {
        "Date": "2025-07-26",
        "Price": 0.085454,
        "Circulating Supply": 21253199904,
        "Market Cap": 1816168534.580089
    },
    {
        "Date": "2025-07-27",
        "Price": 0.087505,
        "Circulating Supply": 21297606035,
        "Market Cap": 1863637191.936284
    },
    {
        "Date": "2025-07-28",
        "Price": 0.082178,
        "Circulating Supply": 21254423459,
        "Market Cap": 1746644777.9955554
    },
    {
        "Date": "2025-07-29",
        "Price": 0.078127,
        "Circulating Supply": 21284395623,
        "Market Cap": 1662883198.6502914
    },
    {
        "Date": "2025-07-30",
        "Price": 0.073945,
        "Circulating Supply": 21239465911,
        "Market Cap": 1570554535.5255406
    },
    {
        "Date": "2025-07-31",
        "Price": 0.074984,
        "Circulating Supply": 21257392569,
        "Market Cap": 1593966413.1158364
    },
    {
        "Date": "2025-08-01",
        "Price": 0.072116,
        "Circulating Supply": 21244786446,
        "Market Cap": 1532086491.1527908
    },
    {
        "Date": "2025-08-02",
        "Price": 0.072561,
        "Circulating Supply": 21240682752,
        "Market Cap": 1541242198.3612232
    },
    {
        "Date": "2025-08-03",
        "Price": 0.071037,
        "Circulating Supply": 21247682707,
        "Market Cap": 1509369541.9895139
    },
    {
        "Date": "2025-08-04",
        "Price": 0.068117,
        "Circulating Supply": 21242737019,
        "Market Cap": 1446988278.6453526
    },
    {
        "Date": "2025-08-05",
        "Price": 0.070905,
        "Circulating Supply": 21281068663,
        "Market Cap": 1508937579.5217772
    },
    {
        "Date": "2025-08-06",
        "Price": 0.065634,
        "Circulating Supply": 21249992645,
        "Market Cap": 1394731979.0859673
    },
    {
        "Date": "2025-08-07",
        "Price": 0.06884,
        "Circulating Supply": 21246239137,
        "Market Cap": 1462582203.3204105
    },
    {
        "Date": "2025-08-08",
        "Price": 0.071297,
        "Circulating Supply": 21251722085,
        "Market Cap": 1515189516.041793
    },
    {
        "Date": "2025-08-09",
        "Price": 0.07839,
        "Circulating Supply": 21230312218,
        "Market Cap": 1664245132.7632194
    },
    {
        "Date": "2025-08-10",
        "Price": 0.080825,
        "Circulating Supply": 21184454672,
        "Market Cap": 1712233166.458559
    },
    {
        "Date": "2025-08-11",
        "Price": 0.075112,
        "Circulating Supply": 21246267535,
        "Market Cap": 1595857307.6543143
    },
    {
        "Date": "2025-08-12",
        "Price": 0.07202,
        "Circulating Supply": 21234526010,
        "Market Cap": 1529315868.8981955
    },
    {
        "Date": "2025-08-13",
        "Price": 0.071467,
        "Circulating Supply": 21236348519,
        "Market Cap": 1517699758.2969182
    },
    {
        "Date": "2025-08-14",
        "Price": 0.07013,
        "Circulating Supply": 21236825745,
        "Market Cap": 1489334869.288315
    },
    {
        "Date": "2025-08-15",
        "Price": 0.066471,
        "Circulating Supply": 21230069489,
        "Market Cap": 1411173932.1796827
    },
    {
        "Date": "2025-08-16",
        "Price": 0.070658,
        "Circulating Supply": 21227471065,
        "Market Cap": 1499898368.5877864
    },
    {
        "Date": "2025-08-17",
        "Price": 0.069603,
        "Circulating Supply": 21227942286,
        "Market Cap": 1477525103.1181903
    },
    {
        "Date": "2025-08-18",
        "Price": 0.065782,
        "Circulating Supply": 21225286186,
        "Market Cap": 1396231586.5135553
    },
    {
        "Date": "2025-08-19",
        "Price": 0.061305,
        "Circulating Supply": 21223424400,
        "Market Cap": 1301107477.2569106
    },
    {
        "Date": "2025-08-20",
        "Price": 0.058791,
        "Circulating Supply": 21222989910,
        "Market Cap": 1247719419.226787
    },
    {
        "Date": "2025-08-21",
        "Price": 0.059972,
        "Circulating Supply": 21218337028,
        "Market Cap": 1272510938.9030387
    },
    {
        "Date": "2025-08-22",
        "Price": 0.058048,
        "Circulating Supply": 21201695816,
        "Market Cap": 1230713191.8343835
    },
    {
        "Date": "2025-08-23",
        "Price": 0.066683,
        "Circulating Supply": 21257473438,
        "Market Cap": 1417506425.5873773
    },
    {
        "Date": "2025-08-24",
        "Price": 0.06226,
        "Circulating Supply": 21206124726,
        "Market Cap": 1320298512.8393483
    },
    {
        "Date": "2025-08-25",
        "Price": 0.05406,
        "Circulating Supply": 21053064022,
        "Market Cap": 1138129684.9380252
    },
    {
        "Date": "2025-08-26",
        "Price": 0.053408,
        "Circulating Supply": 23291534355,
        "Market Cap": 1243943705.5971634
    },
    {
        "Date": "2025-08-27",
        "Price": 0.05723,
        "Circulating Supply": 23377500711,
        "Market Cap": 1337892615.3706205
    },
    {
        "Date": "2025-08-28",
        "Price": 0.056865,
        "Circulating Supply": 23385689952,
        "Market Cap": 1329833819.9593232
    },
    {
        "Date": "2025-08-29",
        "Price": 0.05501,
        "Circulating Supply": 23412453951,
        "Market Cap": 1287917708.179076
    },
    {
        "Date": "2025-08-30",
        "Price": 0.059182,
        "Circulating Supply": 23477075882,
        "Market Cap": 1389423800.7065532
    },
    {
        "Date": "2025-08-31",
        "Price": 0.059809,
        "Circulating Supply": 23359210808,
        "Market Cap": 1397082531.8372254
    },
    {
        "Date": "2025-09-01",
        "Price": 0.055037,
        "Circulating Supply": 23388527625,
        "Market Cap": 1287236199.84505
    },
    {
        "Date": "2025-09-02",
        "Price": 0.056085,
        "Circulating Supply": 23389207588,
        "Market Cap": 1311792568.9895298
    },
    {
        "Date": "2025-09-03",
        "Price": 0.063071,
        "Circulating Supply": 23373160593,
        "Market Cap": 1474180104.9549212
    },
    {
        "Date": "2025-09-04",
        "Price": 0.063679,
        "Circulating Supply": 23411954192,
        "Market Cap": 1490838411.7184656
    },
    {
        "Date": "2025-09-05",
        "Price": 0.062694,
        "Circulating Supply": 23360202472,
        "Market Cap": 1464540835.5492857
    },
    {
        "Date": "2025-09-06",
        "Price": 0.069327,
        "Circulating Supply": 23303951478,
        "Market Cap": 1615591601.8230855
    },
    {
        "Date": "2025-09-07",
        "Price": 0.066117,
        "Circulating Supply": 23400585601,
        "Market Cap": 1547177093.6242614
    },
    {
        "Date": "2025-09-08",
        "Price": 0.060643,
        "Circulating Supply": 23406075896,
        "Market Cap": 1419423112.269731
    },
    {
        "Date": "2025-09-09",
        "Price": 0.059824,
        "Circulating Supply": 23387706149,
        "Market Cap": 1399154247.3930235
    },
    {
        "Date": "2025-09-10",
        "Price": 0.059437,
        "Circulating Supply": 23479528452,
        "Market Cap": 1395549560.2113721
    },
    {
        "Date": "2025-09-11",
        "Price": 0.061803,
        "Circulating Supply": 23391545916,
        "Market Cap": 1445662687.8492067
    },
    {
        "Date": "2025-09-12",
        "Price": 0.061573,
        "Circulating Supply": 23400929879,
        "Market Cap": 1440853888.3926845
    },
    {
        "Date": "2025-09-13",
        "Price": 0.067985,
        "Circulating Supply": 23364030942,
        "Market Cap": 1588397254.0982547
    },
    {
        "Date": "2025-09-14",
        "Price": 0.071341,
        "Circulating Supply": 23328779120,
        "Market Cap": 1664303572.0346243
    },
    {
        "Date": "2025-09-15",
        "Price": 0.063945,
        "Circulating Supply": 23375386317,
        "Market Cap": 1494750166.5960631
    },
    {
        "Date": "2025-09-16",
        "Price": 0.062039,
        "Circulating Supply": 23397055087,
        "Market Cap": 1451526183.5758238
    },
    {
        "Date": "2025-09-17",
        "Price": 0.062289,
        "Circulating Supply": 23371068124,
        "Market Cap": 1455755513.8105083
    },
    {
        "Date": "2025-09-18",
        "Price": 0.065243,
        "Circulating Supply": 23324959145,
        "Market Cap": 1521785188.4779458
    },
    {
        "Date": "2025-09-19",
        "Price": 0.065797,
        "Circulating Supply": 23416883587,
        "Market Cap": 1540763212.0643919
    },
    {
        "Date": "2025-09-20",
        "Price": 0.066993,
        "Circulating Supply": 23373895892,
        "Market Cap": 1565887913.1390932
    },
    {
        "Date": "2025-09-21",
        "Price": 0.06435,
        "Circulating Supply": 23386911752,
        "Market Cap": 1504951264.5200517
    },
    {
        "Date": "2025-09-22",
        "Price": 0.059348,
        "Circulating Supply": 23391612065,
        "Market Cap": 1388235154.0340319
    },
    {
        "Date": "2025-09-23",
        "Price": 0.056509,
        "Circulating Supply": 23394074406,
        "Market Cap": 1321970371.0096762
    },
    {
        "Date": "2025-09-24",
        "Price": 0.057751,
        "Circulating Supply": 23410131748,
        "Market Cap": 1351968315.3416152
    },
    {
        "Date": "2025-09-25",
        "Price": 0.057025,
        "Circulating Supply": 23384741800,
        "Market Cap": 1333506848.4594855
    },
    {
        "Date": "2025-09-26",
        "Price": 0.055561,
        "Circulating Supply": 23406430218,
        "Market Cap": 1300492781.6471035
    },
    {
        "Date": "2025-09-27",
        "Price": 0.062235,
        "Circulating Supply": 23388625395,
        "Market Cap": 1455583318.220645
    },
    {
        "Date": "2025-09-28",
        "Price": 0.059935,
        "Circulating Supply": 23386805453,
        "Market Cap": 1401689785.3374932
    },
    {
        "Date": "2025-09-29",
        "Price": 0.058614,
        "Circulating Supply": 23389807173,
        "Market Cap": 1370970764.9634998
    },
    {
        "Date": "2025-09-30",
        "Price": 0.05588,
        "Circulating Supply": 23385304161,
        "Market Cap": 1306775266.2361803
    },
    {
        "Date": "2025-10-01",
        "Price": 0.057973,
        "Circulating Supply": 23366036521,
        "Market Cap": 1354601679.696326
    },
    {
        "Date": "2025-10-02",
        "Price": 0.060329,
        "Circulating Supply": 23373231198,
        "Market Cap": 1410095003.363253
    },
    {
        "Date": "2025-10-03",
        "Price": 0.059889,
        "Circulating Supply": 23372688419,
        "Market Cap": 1399757337.816585
    },
    {
        "Date": "2025-10-04",
        "Price": 0.06437,
        "Circulating Supply": 23405528110,
        "Market Cap": 1506621488.311574
    },
    {
        "Date": "2025-10-05",
        "Price": 0.062133,
        "Circulating Supply": 23382065387,
        "Market Cap": 1452792630.9585695
    },
    {
        "Date": "2025-10-06",
        "Price": 0.057408,
        "Circulating Supply": 23370345873,
        "Market Cap": 1341636874.8094609
    },
    {
        "Date": "2025-10-07",
        "Price": 0.059184,
        "Circulating Supply": 23369495466,
        "Market Cap": 1383098418.997994
    },
    {
        "Date": "2025-10-08",
        "Price": 0.057126,
        "Circulating Supply": 23338282026,
        "Market Cap": 1333224952.2897322
    },
    {
        "Date": "2025-10-09",
        "Price": 0.059267,
        "Circulating Supply": 23345827007,
        "Market Cap": 1383637810.596075
    },
    {
        "Date": "2025-10-10",
        "Price": 0.05788,
        "Circulating Supply": 23360309081,
        "Market Cap": 1352090401.4288738
    },
    {
        "Date": "2025-10-11",
        "Price": 0.05694,
        "Circulating Supply": 23333795471,
        "Market Cap": 1328631467.8553662
    },
    {
        "Date": "2025-10-12",
        "Price": 0.053701,
        "Circulating Supply": 23396831417,
        "Market Cap": 1256433094.9649181
    },
    {
        "Date": "2025-10-13",
        "Price": 0.054401,
        "Circulating Supply": 23349632254,
        "Market Cap": 1270238634.9502194
    },
    {
        "Date": "2025-10-14",
        "Price": 0.056515,
        "Circulating Supply": 23345771878,
        "Market Cap": 1319386881.494229
    },
    {
        "Date": "2025-10-15",
        "Price": 0.054594,
        "Circulating Supply": 23373252712,
        "Market Cap": 1276029113.041199
    },
    {
        "Date": "2025-10-16",
        "Price": 0.051424,
        "Circulating Supply": 23359386461,
        "Market Cap": 1201241756.8067906
    },
    {
        "Date": "2025-10-17",
        "Price": 0.051463,
        "Circulating Supply": 23328073079,
        "Market Cap": 1200528563.9642427
    },
    {
        "Date": "2025-10-18",
        "Price": 0.054499,
        "Circulating Supply": 23361746929,
        "Market Cap": 1273202107.3891652
    },
    {
        "Date": "2025-10-19",
        "Price": 0.054728,
        "Circulating Supply": 23360796768,
        "Market Cap": 1278497910.2112286
    },
    {
        "Date": "2025-10-20",
        "Price": 0.050364,
        "Circulating Supply": 23360033180,
        "Market Cap": 1176501459.02824
    },
    {
        "Date": "2025-10-21",
        "Price": 0.05006,
        "Circulating Supply": 23375503445,
        "Market Cap": 1170185068.556941
    },
    {
        "Date": "2025-10-22",
        "Price": 0.050182,
        "Circulating Supply": 23422802985,
        "Market Cap": 1175392545.722425
    },
    {
        "Date": "2025-10-23",
        "Price": 0.05005,
        "Circulating Supply": 23357582387,
        "Market Cap": 1169053253.374019
    },
    {
        "Date": "2025-10-24",
        "Price": 0.050379,
        "Circulating Supply": 23354865104,
        "Market Cap": 1176593402.3931048
    },
    {
        "Date": "2025-10-25",
        "Price": 0.053613,
        "Circulating Supply": 23352703474,
        "Market Cap": 1252016836.0547566
    },
    {
        "Date": "2025-10-26",
        "Price": 0.053282,
        "Circulating Supply": 23339231434,
        "Market Cap": 1243550527.7250562
    },
    {
        "Date": "2025-10-27",
        "Price": 0.050951,
        "Circulating Supply": 23361170029,
        "Market Cap": 1190279806.855445
    },
    {
        "Date": "2025-10-28",
        "Price": 0.050769,
        "Circulating Supply": 23340034900,
        "Market Cap": 1184943575.951889
    },
    {
        "Date": "2025-10-29",
        "Price": 0.050043,
        "Circulating Supply": 23337039764,
        "Market Cap": 1167856804.9633548
    },
    {
        "Date": "2025-10-30",
        "Price": 0.050715,
        "Circulating Supply": 23347822938,
        "Market Cap": 1184086832.432527
    },
    {
        "Date": "2025-10-31",
        "Price": 0.049689,
        "Circulating Supply": 23322187140,
        "Market Cap": 1158861044.3636081
    },
    {
        "Date": "2025-11-01",
        "Price": 0.051812,
        "Circulating Supply": 23348125955,
        "Market Cap": 1209721423.093436
    },
    {
        "Date": "2025-11-02",
        "Price": 0.051818,
        "Circulating Supply": 23342662543,
        "Market Cap": 1209561540.453643
    },
    {
        "Date": "2025-11-03",
        "Price": 0.048478,
        "Circulating Supply": 23314763724,
        "Market Cap": 1130262254.2472882
    },
    {
        "Date": "2025-11-04",
        "Price": 0.046779,
        "Circulating Supply": 22884474131,
        "Market Cap": 1070507017.2926393
    },
    {
        "Date": "2025-11-05",
        "Price": 0.046139,
        "Circulating Supply": 22844627685,
        "Market Cap": 1054033372.4858828
    },
    {
        "Date": "2025-11-06",
        "Price": 0.045066,
        "Circulating Supply": 22877372325,
        "Market Cap": 1030998018.8708531
    },
    {
        "Date": "2025-11-07",
        "Price": 0.043225,
        "Circulating Supply": 22860820960,
        "Market Cap": 988159989.7229773
    },
    {
        "Date": "2025-11-08",
        "Price": 0.051148,
        "Circulating Supply": 22874896536,
        "Market Cap": 1169997135.7498584
    },
    {
        "Date": "2025-11-09",
        "Price": 0.047572,
        "Circulating Supply": 22861491230,
        "Market Cap": 1087556457.7394753
    },
    {
        "Date": "2025-11-10",
        "Price": 0.047337,
        "Circulating Supply": 23449305198,
        "Market Cap": 1110014072.110678
    },
    {
        "Date": "2025-11-11",
        "Price": 0.049621,
        "Circulating Supply": 22916943832,
        "Market Cap": 1137168540.195683
    },
    {
        "Date": "2025-11-12",
        "Price": 0.0453,
        "Circulating Supply": 22946152382,
        "Market Cap": 1039470257.820909
    },
    {
        "Date": "2025-11-13",
        "Price": 0.050484,
        "Circulating Supply": 22924400681,
        "Market Cap": 1157315651.1772063
    },
    {
        "Date": "2025-11-14",
        "Price": 0.047374,
        "Circulating Supply": 22911454038,
        "Market Cap": 1085416772.2945385
    },
    {
        "Date": "2025-11-15",
        "Price": 0.047041,
        "Circulating Supply": 22917094980,
        "Market Cap": 1078037246.8084254
    },
    {
        "Date": "2025-11-16",
        "Price": 0.047692,
        "Circulating Supply": 22911967308,
        "Market Cap": 1092728018.8239198
    },
    {
        "Date": "2025-11-17",
        "Price": 0.04306,
        "Circulating Supply": 22889894769,
        "Market Cap": 985635085.1528438
    },
    {
        "Date": "2025-11-18",
        "Price": 0.041977,
        "Circulating Supply": 22870172515,
        "Market Cap": 960011999.1277112
    },
    {
        "Date": "2025-11-19",
        "Price": 0.044406,
        "Circulating Supply": 22924584161,
        "Market Cap": 1017988697.309264
    },
    {
        "Date": "2025-11-20",
        "Price": 0.042951,
        "Circulating Supply": 22913027348,
        "Market Cap": 984140869.8597171
    },
    {
        "Date": "2025-11-21",
        "Price": 0.041959,
        "Circulating Supply": 22929356555,
        "Market Cap": 962088558.0942576
    },
    {
        "Date": "2025-11-22",
        "Price": 0.040914,
        "Circulating Supply": 22926159274,
        "Market Cap": 937995497.7169514
    },
    {
        "Date": "2025-11-23",
        "Price": 0.038733,
        "Circulating Supply": 22902106532,
        "Market Cap": 887072845.0529194
    },
    {
        "Date": "2025-11-24",
        "Price": 0.037572,
        "Circulating Supply": 22907639563,
        "Market Cap": 860694567.846793
    },
    {
        "Date": "2025-11-25",
        "Price": 0.037767,
        "Circulating Supply": 22950044750,
        "Market Cap": 866757210.6083437
    },
    {
        "Date": "2025-11-26",
        "Price": 0.037023,
        "Circulating Supply": 22923960157,
        "Market Cap": 848704113.2035662
    },
    {
        "Date": "2025-11-27",
        "Price": 0.039885,
        "Circulating Supply": 22907351605,
        "Market Cap": 913659981.121901
    },
    {
        "Date": "2025-11-28",
        "Price": 0.042603,
        "Circulating Supply": 22946114634,
        "Market Cap": 977582039.9255434
    },
    {
        "Date": "2025-11-29",
        "Price": 0.046194,
        "Circulating Supply": 22959721564,
        "Market Cap": 1060609623.4618738
    },
    {
        "Date": "2025-11-30",
        "Price": 0.050581,
        "Circulating Supply": 22884473108,
        "Market Cap": 1157530481.9822686
    },
    {
        "Date": "2025-12-01",
        "Price": 0.047613,
        "Circulating Supply": 22880565190,
        "Market Cap": 1089409427.0251782
    },
    {
        "Date": "2025-12-02",
        "Price": 0.044564,
        "Circulating Supply": 22955333031,
        "Market Cap": 1022992824.4999491
    },
    {
        "Date": "2025-12-03",
        "Price": 0.047832,
        "Circulating Supply": 22920520921,
        "Market Cap": 1096331715.2556584
    },
    {
        "Date": "2025-12-04",
        "Price": 0.047939,
        "Circulating Supply": 22932840025,
        "Market Cap": 1099376428.8583603
    },
    {
        "Date": "2025-12-05",
        "Price": 0.048052,
        "Circulating Supply": 22939843521,
        "Market Cap": 1102298071.2180688
    },
    {
        "Date": "2025-12-06",
        "Price": 0.048434,
        "Circulating Supply": 22906685335,
        "Market Cap": 1109468715.4125972
    },
    {
        "Date": "2025-12-07",
        "Price": 0.048835,
        "Circulating Supply": 22907745827,
        "Market Cap": 1118694375.2722585
    },
    {
        "Date": "2025-12-08",
        "Price": 0.044909,
        "Circulating Supply": 22862770923,
        "Market Cap": 1026755225.5599531
    },
    {
        "Date": "2025-12-09",
        "Price": 0.046317,
        "Circulating Supply": 22918985921,
        "Market Cap": 1061542676.7491612
    },
    {
        "Date": "2025-12-10",
        "Price": 0.047013,
        "Circulating Supply": 22930279081,
        "Market Cap": 1078016608.5589993
    },
    {
        "Date": "2025-12-11",
        "Price": 0.047667,
        "Circulating Supply": 22928056048,
        "Market Cap": 1092922239.536795
    },
    {
        "Date": "2025-12-12",
        "Price": 0.0468,
        "Circulating Supply": 22915278220,
        "Market Cap": 1072437375.9752136
    },
    {
        "Date": "2025-12-13",
        "Price": 0.052972,
        "Circulating Supply": 22934815038,
        "Market Cap": 1214907038.821095
    },
    {
        "Date": "2025-12-14",
        "Price": 0.053962,
        "Circulating Supply": 22911992781,
        "Market Cap": 1236372458.055231
    },
    {
        "Date": "2025-12-15",
        "Price": 0.050684,
        "Circulating Supply": 22904077413,
        "Market Cap": 1160863841.0104356
    },
    {
        "Date": "2025-12-16",
        "Price": 0.0496,
        "Circulating Supply": 22943852250,
        "Market Cap": 1138009635.0595806
    },
    {
        "Date": "2025-12-17",
        "Price": 0.050771,
        "Circulating Supply": 22902178745,
        "Market Cap": 1162768031.046819
    },
    {
        "Date": "2025-12-18",
        "Price": 0.048391,
        "Circulating Supply": 22937769889,
        "Market Cap": 1109979055.7533848
    },
    {
        "Date": "2025-12-19",
        "Price": 0.048164,
        "Circulating Supply": 22934515440,
        "Market Cap": 1104624042.0341947
    },
    {
        "Date": "2025-12-20",
        "Price": 0.055475,
        "Circulating Supply": 22936681439,
        "Market Cap": 1272422135.0603933
    },
    {
        "Date": "2025-12-21",
        "Price": 0.058352,
        "Circulating Supply": 22892754882,
        "Market Cap": 1335828591.090046
    },
    {
        "Date": "2025-12-22",
        "Price": 0.056311,
        "Circulating Supply": 22908971521,
        "Market Cap": 1290037493.5340881
    },
    {
        "Date": "2025-12-23",
        "Price": 0.056664,
        "Circulating Supply": 22968335320,
        "Market Cap": 1301482543.4187355
    },
    {
        "Date": "2025-12-24",
        "Price": 0.054809,
        "Circulating Supply": 22948640770,
        "Market Cap": 1257788605.1789334
    },
    {
        "Date": "2025-12-25",
        "Price": 0.062749,
        "Circulating Supply": 22917617663,
        "Market Cap": 1438068082.6560693
    },
    {
        "Date": "2025-12-26",
        "Price": 0.057939,
        "Circulating Supply": 22963997790,
        "Market Cap": 1330509004.8746889
    },
    {
        "Date": "2025-12-27",
        "Price": 0.057166,
        "Circulating Supply": 22874848643,
        "Market Cap": 1307669562.8251135
    },
    {
        "Date": "2025-12-28",
        "Price": 0.057522,
        "Circulating Supply": 22941343955,
        "Market Cap": 1319641124.6612906
    },
    {
        "Date": "2025-12-29",
        "Price": 0.05439,
        "Circulating Supply": 22921980695,
        "Market Cap": 1246722522.9103682
    },
    {
        "Date": "2025-12-30",
        "Price": 0.052284,
        "Circulating Supply": 22943773504,
        "Market Cap": 1199600240.8129406
    },
    {
        "Date": "2025-12-31",
        "Price": 0.051542,
        "Circulating Supply": 22959729534,
        "Market Cap": 1183388984.5104194
    },
    {
        "Date": "2026-01-01",
        "Price": 0.0534,
        "Circulating Supply": 22960630041,
        "Market Cap": 1226091310.9289434
    },
    {
        "Date": "2026-01-02",
        "Price": 0.051553,
        "Circulating Supply": 22955108361,
        "Market Cap": 1183405318.2238119
    },
    {
        "Date": "2026-01-03",
        "Price": 0.058408,
        "Circulating Supply": 22950513382,
        "Market Cap": 1340491693.070399
    },
    {
        "Date": "2026-01-04",
        "Price": 0.057426,
        "Circulating Supply": 22969218055,
        "Market Cap": 1319038888.7057784
    },
    {
        "Date": "2026-01-05",
        "Price": 0.053162,
        "Circulating Supply": 22938867346,
        "Market Cap": 1219478809.913814
    },
    {
        "Date": "2026-01-06",
        "Price": 0.054809,
        "Circulating Supply": 22989406499,
        "Market Cap": 1260021497.5873415
    },
    {
        "Date": "2026-01-07",
        "Price": 0.054766,
        "Circulating Supply": 22971335776,
        "Market Cap": 1258039356.1358812
    },
    {
        "Date": "2026-01-08",
        "Price": 0.052652,
        "Circulating Supply": 22975046408,
        "Market Cap": 1209681983.2012448
    },
    {
        "Date": "2026-01-09",
        "Price": 0.049032,
        "Circulating Supply": 22963912932,
        "Market Cap": 1125958840.6890721
    },
    {
        "Date": "2026-01-10",
        "Price": 0.051514,
        "Circulating Supply": 22973009842,
        "Market Cap": 1183441899.310938
    },
    {
        "Date": "2026-01-11",
        "Price": 0.054376,
        "Circulating Supply": 22953553532,
        "Market Cap": 1248116571.5690682
    },
    {
        "Date": "2026-01-12",
        "Price": 0.050542,
        "Circulating Supply": 22953609376,
        "Market Cap": 1160122144.105916
    },
    {
        "Date": "2026-01-13",
        "Price": 0.047736,
        "Circulating Supply": 22982114070,
        "Market Cap": 1097068599.5738382
    },
    {
        "Date": "2026-01-14",
        "Price": 0.050767,
        "Circulating Supply": 22980876093,
        "Market Cap": 1166664542.0658047
    },
    {
        "Date": "2026-01-15",
        "Price": 0.051355,
        "Circulating Supply": 22963718297,
        "Market Cap": 1179307827.5394895
    },
    {
        "Date": "2026-01-16",
        "Price": 0.051589,
        "Circulating Supply": 22970341731,
        "Market Cap": 1185022440.9470313
    },
    {
        "Date": "2026-01-17",
        "Price": 0.059925,
        "Circulating Supply": 22988667053,
        "Market Cap": 1377595788.8540761
    },
    {
        "Date": "2026-01-18",
        "Price": 0.059365,
        "Circulating Supply": 22953418214,
        "Market Cap": 1362632585.084223
    },
    {
        "Date": "2026-01-19",
        "Price": 0.054983,
        "Circulating Supply": 22991417564,
        "Market Cap": 1264145839.2836652
    },
    {
        "Date": "2026-01-20",
        "Price": 0.05519,
        "Circulating Supply": 22994986543,
        "Market Cap": 1269099628.3247592
    },
    {
        "Date": "2026-01-21",
        "Price": 0.053828,
        "Circulating Supply": 22974637604,
        "Market Cap": 1236682623.832813
    },
    {
        "Date": "2026-01-22",
        "Price": 0.055101,
        "Circulating Supply": 22984870477,
        "Market Cap": 1266488874.7539325
    },
    {
        "Date": "2026-01-23",
        "Price": 0.057151,
        "Circulating Supply": 22975746491,
        "Market Cap": 1313086487.3823597
    },
    {
        "Date": "2026-01-24",
        "Price": 0.061607,
        "Circulating Supply": 22977643685,
        "Market Cap": 1415581197.6360626
    },
    {
        "Date": "2026-01-25",
        "Price": 0.061661,
        "Circulating Supply": 22970351197,
        "Market Cap": 1416370027.3631682
    },
    {
        "Date": "2026-01-26",
        "Price": 0.053944,
        "Circulating Supply": 22983710340,
        "Market Cap": 1239838137.2395835
    },
    {
        "Date": "2026-01-27",
        "Price": 0.05462,
        "Circulating Supply": 23008946803,
        "Market Cap": 1256739708.534675
    },
    {
        "Date": "2026-01-28",
        "Price": 0.052942,
        "Circulating Supply": 23016027846,
        "Market Cap": 1218523289.9599557
    },
    {
        "Date": "2026-01-29",
        "Price": 0.0562,
        "Circulating Supply": 22992267722,
        "Market Cap": 1292170645.2835402
    },
    {
        "Date": "2026-01-30",
        "Price": 0.054231,
        "Circulating Supply": 22972084468,
        "Market Cap": 1245808306.8059304
    },
    {
        "Date": "2026-01-31",
        "Price": 0.059632,
        "Circulating Supply": 22980964926,
        "Market Cap": 1370402467.6583781
    },
    {
        "Date": "2026-02-01",
        "Price": 0.056256,
        "Circulating Supply": 22980387565,
        "Market Cap": 1292793952.2137897
    },
    {
        "Date": "2026-02-02",
        "Price": 0.051684,
        "Circulating Supply": 22969046099,
        "Market Cap": 1187125251.2041843
    },
    {
        "Date": "2026-02-03",
        "Price": 0.053303,
        "Circulating Supply": 23008381850,
        "Market Cap": 1226426040.3295424
    },
    {
        "Date": "2026-02-04",
        "Price": 0.051869,
        "Circulating Supply": 23006166389,
        "Market Cap": 1193318286.5385368
    },
    {
        "Date": "2026-02-05",
        "Price": 0.051866,
        "Circulating Supply": 23015403599,
        "Market Cap": 1193708771.5476708
    },
    {
        "Date": "2026-02-06",
        "Price": 0.047609,
        "Circulating Supply": 23028729674,
        "Market Cap": 1096375167.9168448
    },
    {
        "Date": "2026-02-07",
        "Price": 0.058999,
        "Circulating Supply": 23036273782,
        "Market Cap": 1359117395.8436553
    },
    {
        "Date": "2026-02-08",
        "Price": 0.060038,
        "Circulating Supply": 22993666839,
        "Market Cap": 1380489018.8546753
    },
    {
        "Date": "2026-02-09",
        "Price": 0.057342,
        "Circulating Supply": 22989758937,
        "Market Cap": 1318280252.9562383
    },
    {
        "Date": "2026-02-10",
        "Price": 0.058365,
        "Circulating Supply": 23029656562,
        "Market Cap": 1344116310.4893744
    },
    {
        "Date": "2026-02-11",
        "Price": 0.057842,
        "Circulating Supply": 23004999278,
        "Market Cap": 1330645723.109485
    },
    {
        "Date": "2026-02-12",
        "Price": 0.055317,
        "Circulating Supply": 23010463164,
        "Market Cap": 1272867940.5984812
    },
    {
        "Date": "2026-02-13",
        "Price": 0.056185,
        "Circulating Supply": 23007224926,
        "Market Cap": 1292663713.4738722
    },
    {
        "Date": "2026-02-14",
        "Price": 0.063851,
        "Circulating Supply": 23006092888,
        "Market Cap": 1468952859.7476628
    },
    {
        "Date": "2026-02-15",
        "Price": 0.065228,
        "Circulating Supply": 23015570797,
        "Market Cap": 1501259186.0768692
    },
    {
        "Date": "2026-02-16",
        "Price": 0.056066,
        "Circulating Supply": 22995837575,
        "Market Cap": 1289295770.5060909
    },
    {
        "Date": "2026-02-17",
        "Price": 0.056504,
        "Circulating Supply": 23028599210,
        "Market Cap": 1301207687.7551656
    },
    {
        "Date": "2026-02-18",
        "Price": 0.053201,
        "Circulating Supply": 23030731848,
        "Market Cap": 1225256343.9881878
    },
    {
        "Date": "2026-02-19",
        "Price": 0.05632,
        "Circulating Supply": 23022797968,
        "Market Cap": 1296649626.6361601
    },
    {
        "Date": "2026-02-20",
        "Price": 0.054422,
        "Circulating Supply": 23020671775,
        "Market Cap": 1252824061.664166
    },
    {
        "Date": "2026-02-21",
        "Price": 0.059745,
        "Circulating Supply": 23009192529,
        "Market Cap": 1374679398.7868743
    },
    {
        "Date": "2026-02-22",
        "Price": 0.059518,
        "Circulating Supply": 23010880733,
        "Market Cap": 1369559571.1565423
    },
    {
        "Date": "2026-02-23",
        "Price": 0.054219,
        "Circulating Supply": 22995404881,
        "Market Cap": 1246780504.9526222
    },
    {
        "Date": "2026-02-24",
        "Price": 0.053345,
        "Circulating Supply": 23042348089,
        "Market Cap": 1229200124.2091963
    },
    {
        "Date": "2026-02-25",
        "Price": 0.056047,
        "Circulating Supply": 23039089876,
        "Market Cap": 1291262324.6116884
    },
    {
        "Date": "2026-02-26",
        "Price": 0.058183,
        "Circulating Supply": 23030317797,
        "Market Cap": 1339976038.9623713
    },
    {
        "Date": "2026-02-27",
        "Price": 0.058586,
        "Circulating Supply": 23022206720,
        "Market Cap": 1348770056.902388
    },
    {
        "Date": "2026-02-28",
        "Price": 0.062184,
        "Circulating Supply": 23008607903,
        "Market Cap": 1430768695.3313193
    },
    {
        "Date": "2026-03-01",
        "Price": 0.063016,
        "Circulating Supply": 23010906622,
        "Market Cap": 1450048451.808546
    },
    {
        "Date": "2026-03-02",
        "Price": 0.056847,
        "Circulating Supply": 23014748683,
        "Market Cap": 1308308794.019596
    },
    {
        "Date": "2026-03-03",
        "Price": 0.060579,
        "Circulating Supply": 23050200673,
        "Market Cap": 1396368390.4150872
    },
    {
        "Date": "2026-03-04",
        "Price": 0.061347,
        "Circulating Supply": 23048249075,
        "Market Cap": 1413933151.2843378
    },
    {
        "Date": "2026-03-05",
        "Price": 0.065551,
        "Circulating Supply": 23109425984,
        "Market Cap": 1514845992.8423324
    },
    {
        "Date": "2026-03-06",
        "Price": 0.065672,
        "Circulating Supply": 23054542392,
        "Market Cap": 1514041399.0358605
    },
    {
        "Date": "2026-03-07",
        "Price": 0.065651,
        "Circulating Supply": 23046815778,
        "Market Cap": 1513053807.6091583
    },
    {
        "Date": "2026-03-08",
        "Price": 0.066583,
        "Circulating Supply": 23044452340,
        "Market Cap": 1534374747.1579747
    },
    {
        "Date": "2026-03-09",
        "Price": 0.062675,
        "Circulating Supply": 23033049712,
        "Market Cap": 1443596009.0570319
    },
    {
        "Date": "2026-03-10",
        "Price": 0.064917,
        "Circulating Supply": 23037539866,
        "Market Cap": 1495529828.5714235
    },
    {
        "Date": "2026-03-11",
        "Price": 0.067199,
        "Circulating Supply": 23067340139,
        "Market Cap": 1550096982.4133167
    },
    {
        "Date": "2026-03-12",
        "Price": 0.068805,
        "Circulating Supply": 23054497706,
        "Market Cap": 1586267327.6736434
    },
    {
        "Date": "2026-03-13",
        "Price": 0.070478,
        "Circulating Supply": 23044569696,
        "Market Cap": 1624139996.331559
    },
    {
        "Date": "2026-03-14",
        "Price": 0.073059,
        "Circulating Supply": 23012099391,
        "Market Cap": 1681230465.984373
    },
    {
        "Date": "2026-03-15",
        "Price": 0.067359,
        "Circulating Supply": 23036778668,
        "Market Cap": 1551732699.1775212
    },
    {
        "Date": "2026-03-16",
        "Price": 0.064122,
        "Circulating Supply": 23043799560,
        "Market Cap": 1477603608.7286344
    },
    {
        "Date": "2026-03-17",
        "Price": 0.065588,
        "Circulating Supply": 23087660426,
        "Market Cap": 1514269475.4561336
    },
    {
        "Date": "2026-03-18",
        "Price": 0.063853,
        "Circulating Supply": 23095391047,
        "Market Cap": 1474703877.459666
    },
    {
        "Date": "2026-03-19",
        "Price": 0.062959,
        "Circulating Supply": 23044955519,
        "Market Cap": 1450882694.630709
    },
    {
        "Date": "2026-03-20",
        "Price": 0.061804,
        "Circulating Supply": 23071806970,
        "Market Cap": 1425928799.179808
    }
]