[
    {
        "Date": "2024-09-24",
        "Volume": 1168837.861954807
    },
    {
        "Date": "2024-09-25",
        "Volume": 1160538.583003513
    },
    {
        "Date": "2024-09-27",
        "Volume": 1188523.403377398
    },
    {
        "Date": "2024-09-28",
        "Volume": 1229155.9207916358
    },
    {
        "Date": "2024-09-29",
        "Volume": 1368015.7033036714
    },
    {
        "Date": "2024-09-30",
        "Volume": 1352728.400531604
    },
    {
        "Date": "2024-10-01",
        "Volume": 1249239.2917248178
    },
    {
        "Date": "2024-10-02",
        "Volume": 1248722.3710135745
    },
    {
        "Date": "2024-10-03",
        "Volume": 1214994.0565292106
    },
    {
        "Date": "2024-10-04",
        "Volume": 1252590.6587233276
    },
    {
        "Date": "2024-10-05",
        "Volume": 1306468.3334497944
    },
    {
        "Date": "2024-10-06",
        "Volume": 1255589.292118679
    },
    {
        "Date": "2024-10-07",
        "Volume": 1218822.0453891347
    },
    {
        "Date": "2024-10-08",
        "Volume": 1202972.0611076322
    },
    {
        "Date": "2024-10-09",
        "Volume": 1195364.2966887208
    },
    {
        "Date": "2024-10-10",
        "Volume": 1164144.9695973636
    },
    {
        "Date": "2024-10-11",
        "Volume": 2986336.3337474633
    },
    {
        "Date": "2024-10-12",
        "Volume": 1931855.0611244496
    },
    {
        "Date": "2024-10-13",
        "Volume": 1086306.4668088292
    },
    {
        "Date": "2024-10-14",
        "Volume": 1287490.0151480325
    },
    {
        "Date": "2024-10-15",
        "Volume": 2246342.3121381435
    },
    {
        "Date": "2024-10-16",
        "Volume": 7283424.35887817
    },
    {
        "Date": "2024-10-17",
        "Volume": 2755067.2750073182
    },
    {
        "Date": "2024-10-18",
        "Volume": 2952336.8853437477
    },
    {
        "Date": "2024-10-19",
        "Volume": 1496742.1951862958
    },
    {
        "Date": "2024-10-20",
        "Volume": 1234736.0506557208
    },
    {
        "Date": "2024-10-21",
        "Volume": 1672385.6261611958
    },
    {
        "Date": "2024-10-22",
        "Volume": 2151077.0727852895
    },
    {
        "Date": "2024-10-23",
        "Volume": 3899720.433993822
    },
    {
        "Date": "2024-10-24",
        "Volume": 3372899.1300316257
    },
    {
        "Date": "2024-10-25",
        "Volume": 1861073.3933320262
    },
    {
        "Date": "2024-10-26",
        "Volume": 4444550.684241976
    },
    {
        "Date": "2024-10-27",
        "Volume": 4056978.5019841967
    },
    {
        "Date": "2024-10-28",
        "Volume": 1079553.3005213405
    },
    {
        "Date": "2024-10-29",
        "Volume": 1866874.0304092623
    },
    {
        "Date": "2024-10-30",
        "Volume": 2943925.926377928
    },
    {
        "Date": "2024-10-31",
        "Volume": 10261944.42425845
    },
    {
        "Date": "2024-11-01",
        "Volume": 8542196.094805235
    },
    {
        "Date": "2024-11-02",
        "Volume": 8413661.837915696
    },
    {
        "Date": "2024-11-03",
        "Volume": 2692968.059368269
    },
    {
        "Date": "2024-11-04",
        "Volume": 3318584.3405492534
    },
    {
        "Date": "2024-11-05",
        "Volume": 3714654.304833102
    },
    {
        "Date": "2024-11-06",
        "Volume": 3415547.280133283
    },
    {
        "Date": "2024-11-07",
        "Volume": 19066615.32173349
    },
    {
        "Date": "2024-11-08",
        "Volume": 18982127.79622661
    },
    {
        "Date": "2024-11-09",
        "Volume": 7842566.093575826
    },
    {
        "Date": "2024-11-10",
        "Volume": 5666182.599337004
    },
    {
        "Date": "2024-11-11",
        "Volume": 11809968.597852256
    },
    {
        "Date": "2024-11-12",
        "Volume": 15414822.802053224
    },
    {
        "Date": "2024-11-13",
        "Volume": 17684777.101386905
    },
    {
        "Date": "2024-11-14",
        "Volume": 15243554.221461926
    },
    {
        "Date": "2024-11-15",
        "Volume": 7049119.1952932915
    },
    {
        "Date": "2024-11-16",
        "Volume": 5635440.358939523
    },
    {
        "Date": "2024-11-17",
        "Volume": 7133811.197979954
    },
    {
        "Date": "2024-11-18",
        "Volume": 9043313.877903605
    },
    {
        "Date": "2024-11-19",
        "Volume": 7665399.597757309
    },
    {
        "Date": "2024-11-20",
        "Volume": 6076281.376883754
    },
    {
        "Date": "2024-11-21",
        "Volume": 5506249.970281111
    },
    {
        "Date": "2024-11-22",
        "Volume": 15805112.492784882
    },
    {
        "Date": "2024-11-23",
        "Volume": 8187745.6758349575
    },
    {
        "Date": "2024-11-24",
        "Volume": 14136844.420628179
    },
    {
        "Date": "2024-11-25",
        "Volume": 13456878.060095653
    },
    {
        "Date": "2024-11-26",
        "Volume": 20928956.203228418
    },
    {
        "Date": "2024-11-27",
        "Volume": 689928.7988165976
    },
    {
        "Date": "2024-11-28",
        "Volume": 10003266.252819814
    },
    {
        "Date": "2024-11-29",
        "Volume": 6514448.098813467
    },
    {
        "Date": "2024-11-30",
        "Volume": 3648608.7764929757
    },
    {
        "Date": "2024-12-01",
        "Volume": 7164794.512123613
    },
    {
        "Date": "2024-12-02",
        "Volume": 5361639.659801271
    },
    {
        "Date": "2024-12-03",
        "Volume": 17441465.28906336
    },
    {
        "Date": "2024-12-04",
        "Volume": 40270156.05547656
    },
    {
        "Date": "2024-12-05",
        "Volume": 20710590.972923905
    },
    {
        "Date": "2024-12-06",
        "Volume": 15366101.95566909
    },
    {
        "Date": "2024-12-07",
        "Volume": 11276028.106326416
    },
    {
        "Date": "2024-12-08",
        "Volume": 4035980.39776522
    },
    {
        "Date": "2024-12-09",
        "Volume": 5381667.369147592
    },
    {
        "Date": "2024-12-10",
        "Volume": 19703260.171768297
    },
    {
        "Date": "2024-12-11",
        "Volume": 34824649.370319314
    },
    {
        "Date": "2024-12-12",
        "Volume": 10428813.609049497
    },
    {
        "Date": "2024-12-13",
        "Volume": 17298781.932356358
    },
    {
        "Date": "2024-12-14",
        "Volume": 12334564.501067521
    },
    {
        "Date": "2024-12-15",
        "Volume": 7364736.149051979
    },
    {
        "Date": "2024-12-16",
        "Volume": 9272310.564065784
    },
    {
        "Date": "2024-12-17",
        "Volume": 11685003.765682252
    },
    {
        "Date": "2024-12-18",
        "Volume": 6852588.706691967
    },
    {
        "Date": "2024-12-19",
        "Volume": 6379876.297295295
    },
    {
        "Date": "2024-12-20",
        "Volume": 13871920.791446831
    },
    {
        "Date": "2024-12-21",
        "Volume": 22981875.441384178
    },
    {
        "Date": "2024-12-22",
        "Volume": 9117202.994028473
    },
    {
        "Date": "2024-12-23",
        "Volume": 8689383.59253345
    },
    {
        "Date": "2024-12-24",
        "Volume": 11495513.729596566
    },
    {
        "Date": "2024-12-25",
        "Volume": 6050799.851029235
    },
    {
        "Date": "2024-12-26",
        "Volume": 3901801.980019875
    },
    {
        "Date": "2024-12-27",
        "Volume": 3059810.047813912
    },
    {
        "Date": "2024-12-28",
        "Volume": 17239380.33935492
    },
    {
        "Date": "2024-12-29",
        "Volume": 4421318.395683927
    },
    {
        "Date": "2024-12-30",
        "Volume": 3316019.595594302
    },
    {
        "Date": "2024-12-31",
        "Volume": 6888242.819297039
    },
    {
        "Date": "2025-01-01",
        "Volume": 3868163.7350978246
    },
    {
        "Date": "2025-01-02",
        "Volume": 2302697.207441678
    },
    {
        "Date": "2025-01-03",
        "Volume": 3614485.55115188
    },
    {
        "Date": "2025-01-04",
        "Volume": 2770598.3867644807
    },
    {
        "Date": "2025-01-05",
        "Volume": 4467345.762993703
    },
    {
        "Date": "2025-01-06",
        "Volume": 2719850.2297720998
    },
    {
        "Date": "2025-01-07",
        "Volume": 3074820.2726247576
    },
    {
        "Date": "2025-01-08",
        "Volume": 4303422.650565411
    },
    {
        "Date": "2025-01-09",
        "Volume": 7909942.5364916
    },
    {
        "Date": "2025-01-10",
        "Volume": 9700511.076232437
    },
    {
        "Date": "2025-01-11",
        "Volume": 5314730.795953299
    },
    {
        "Date": "2025-01-12",
        "Volume": 2208759.7642848906
    },
    {
        "Date": "2025-01-13",
        "Volume": 2783605.3459647717
    },
    {
        "Date": "2025-01-14",
        "Volume": 10873279.5403848
    },
    {
        "Date": "2025-01-15",
        "Volume": 3175415.156961894
    },
    {
        "Date": "2025-01-16",
        "Volume": 3538643.146636583
    },
    {
        "Date": "2025-01-17",
        "Volume": 3695616.085829332
    },
    {
        "Date": "2025-01-18",
        "Volume": 4476692.868890531
    },
    {
        "Date": "2025-01-19",
        "Volume": 6454951.787558842
    },
    {
        "Date": "2025-01-20",
        "Volume": 16654055.48236761
    },
    {
        "Date": "2025-01-21",
        "Volume": 19631231.788911935
    },
    {
        "Date": "2025-01-22",
        "Volume": 9220893.694026414
    },
    {
        "Date": "2025-01-23",
        "Volume": 3283543.9594985154
    },
    {
        "Date": "2025-01-24",
        "Volume": 8280957.34488572
    },
    {
        "Date": "2025-01-25",
        "Volume": 10715578.290645966
    },
    {
        "Date": "2025-01-26",
        "Volume": 5518289.65021057
    },
    {
        "Date": "2025-01-27",
        "Volume": 7001304.73701093
    },
    {
        "Date": "2025-01-28",
        "Volume": 13399398.994029865
    },
    {
        "Date": "2025-01-29",
        "Volume": 7988475.82412729
    },
    {
        "Date": "2025-01-30",
        "Volume": 10289476.846929157
    },
    {
        "Date": "2025-01-31",
        "Volume": 10065315.659068514
    },
    {
        "Date": "2025-02-01",
        "Volume": 12907081.600899719
    },
    {
        "Date": "2025-02-02",
        "Volume": 9458057.193558825
    },
    {
        "Date": "2025-02-03",
        "Volume": 18653746.180948406
    },
    {
        "Date": "2025-02-04",
        "Volume": 33820887.34139762
    },
    {
        "Date": "2025-02-05",
        "Volume": 18221232.424648672
    },
    {
        "Date": "2025-02-06",
        "Volume": 11522951.556406494
    },
    {
        "Date": "2025-02-07",
        "Volume": 9883781.857913986
    },
    {
        "Date": "2025-02-08",
        "Volume": 9199039.025980901
    },
    {
        "Date": "2025-02-09",
        "Volume": 9241360.075520203
    },
    {
        "Date": "2025-02-10",
        "Volume": 10779999.926388137
    },
    {
        "Date": "2025-02-11",
        "Volume": 12060409.034641724
    },
    {
        "Date": "2025-02-12",
        "Volume": 10084002.600740874
    },
    {
        "Date": "2025-02-13",
        "Volume": 13247870.080437828
    },
    {
        "Date": "2025-02-14",
        "Volume": 10920777.432634251
    },
    {
        "Date": "2025-02-15",
        "Volume": 8716084.523399232
    },
    {
        "Date": "2025-02-16",
        "Volume": 6038782.613483332
    },
    {
        "Date": "2025-02-17",
        "Volume": 7282509.680702216
    },
    {
        "Date": "2025-02-18",
        "Volume": 14129422.460106492
    },
    {
        "Date": "2025-02-19",
        "Volume": 18271418.693180803
    },
    {
        "Date": "2025-02-20",
        "Volume": 17763886.38068279
    },
    {
        "Date": "2025-02-21",
        "Volume": 31622937.325797796
    },
    {
        "Date": "2025-02-22",
        "Volume": 33512549.355755877
    },
    {
        "Date": "2025-02-23",
        "Volume": 19870545.693618465
    },
    {
        "Date": "2025-02-24",
        "Volume": 21136919.89379404
    },
    {
        "Date": "2025-02-25",
        "Volume": 20643117.850730453
    },
    {
        "Date": "2025-02-26",
        "Volume": 18266228.547862794
    },
    {
        "Date": "2025-02-27",
        "Volume": 15393025.188928036
    },
    {
        "Date": "2025-02-28",
        "Volume": 9897448.845563943
    },
    {
        "Date": "2025-03-01",
        "Volume": 15915381.844930343
    },
    {
        "Date": "2025-03-02",
        "Volume": 9540062.971848872
    },
    {
        "Date": "2025-03-03",
        "Volume": 10261094.869127207
    },
    {
        "Date": "2025-03-04",
        "Volume": 10550189.277626595
    },
    {
        "Date": "2025-03-05",
        "Volume": 11370934.965109833
    },
    {
        "Date": "2025-03-06",
        "Volume": 6538265.184417846
    },
    {
        "Date": "2025-03-07",
        "Volume": 7788447.324246652
    },
    {
        "Date": "2025-03-08",
        "Volume": 9297476.326438205
    },
    {
        "Date": "2025-03-09",
        "Volume": 9379997.06202702
    },
    {
        "Date": "2025-03-10",
        "Volume": 10247943.024764173
    },
    {
        "Date": "2025-03-11",
        "Volume": 8640190.511813642
    },
    {
        "Date": "2025-03-12",
        "Volume": 9199766.91416931
    },
    {
        "Date": "2025-03-13",
        "Volume": 8516750.597058097
    },
    {
        "Date": "2025-03-14",
        "Volume": 8042101.244356696
    },
    {
        "Date": "2025-03-15",
        "Volume": 8193483.810681689
    },
    {
        "Date": "2025-03-16",
        "Volume": 6889462.871631502
    },
    {
        "Date": "2025-03-17",
        "Volume": 9147564.804656984
    },
    {
        "Date": "2025-03-18",
        "Volume": 6650637.837398274
    },
    {
        "Date": "2025-03-19",
        "Volume": 8816038.94654688
    },
    {
        "Date": "2025-03-20",
        "Volume": 9341851.624371404
    },
    {
        "Date": "2025-03-21",
        "Volume": 7780066.776312536
    },
    {
        "Date": "2025-03-22",
        "Volume": 6401889.84555266
    },
    {
        "Date": "2025-03-23",
        "Volume": 7742304.387290348
    },
    {
        "Date": "2025-03-24",
        "Volume": 7419950.7673180355
    },
    {
        "Date": "2025-03-25",
        "Volume": 7146540.012629297
    },
    {
        "Date": "2025-03-26",
        "Volume": 7727857.738668927
    },
    {
        "Date": "2025-03-27",
        "Volume": 6771810.15157204
    },
    {
        "Date": "2025-03-28",
        "Volume": 8018675.719131661
    },
    {
        "Date": "2025-03-29",
        "Volume": 8579894.328583281
    },
    {
        "Date": "2025-03-30",
        "Volume": 8986101.068628795
    },
    {
        "Date": "2025-03-31",
        "Volume": 5954891.232101306
    },
    {
        "Date": "2025-04-01",
        "Volume": 6952948.637565894
    },
    {
        "Date": "2025-04-02",
        "Volume": 6605906.07852844
    },
    {
        "Date": "2025-04-03",
        "Volume": 6184334.522538068
    },
    {
        "Date": "2025-04-04",
        "Volume": 7863090.693801277
    },
    {
        "Date": "2025-04-05",
        "Volume": 10153212.89774536
    },
    {
        "Date": "2025-04-06",
        "Volume": 8291394.775204489
    },
    {
        "Date": "2025-04-07",
        "Volume": 7882807.468207119
    },
    {
        "Date": "2025-04-08",
        "Volume": 10434135.837287916
    },
    {
        "Date": "2025-04-09",
        "Volume": 7831850.598879677
    },
    {
        "Date": "2025-04-10",
        "Volume": 10635338.661841314
    },
    {
        "Date": "2025-04-11",
        "Volume": 6621605.140359722
    },
    {
        "Date": "2025-04-12",
        "Volume": 7927860.216045884
    },
    {
        "Date": "2025-04-13",
        "Volume": 8868550.00478994
    },
    {
        "Date": "2025-04-14",
        "Volume": 7894885.590493952
    },
    {
        "Date": "2025-04-15",
        "Volume": 7586250.848864528
    },
    {
        "Date": "2025-04-16",
        "Volume": 6572133.640044959
    },
    {
        "Date": "2025-04-17",
        "Volume": 5254288.60531409
    },
    {
        "Date": "2025-04-18",
        "Volume": 6476381.6655823365
    },
    {
        "Date": "2025-04-19",
        "Volume": 5794131.803507765
    },
    {
        "Date": "2025-04-20",
        "Volume": 5617106.541595236
    },
    {
        "Date": "2025-04-21",
        "Volume": 5928005.350651995
    },
    {
        "Date": "2025-04-22",
        "Volume": 5831729.563260266
    },
    {
        "Date": "2025-04-23",
        "Volume": 7003165.054876198
    },
    {
        "Date": "2025-04-24",
        "Volume": 6056436.111682055
    },
    {
        "Date": "2025-04-25",
        "Volume": 5123263.337371763
    },
    {
        "Date": "2025-04-26",
        "Volume": 5139085.117454724
    },
    {
        "Date": "2025-04-27",
        "Volume": 6121390.021373415
    },
    {
        "Date": "2025-04-28",
        "Volume": 7302106.015693338
    },
    {
        "Date": "2025-04-29",
        "Volume": 8050777.310097672
    },
    {
        "Date": "2025-04-30",
        "Volume": 6000469.552248338
    },
    {
        "Date": "2025-05-01",
        "Volume": 4999349.918073426
    },
    {
        "Date": "2025-05-02",
        "Volume": 7401631.133770708
    },
    {
        "Date": "2025-05-03",
        "Volume": 8680535.771148019
    },
    {
        "Date": "2025-05-04",
        "Volume": 7206765.895785488
    },
    {
        "Date": "2025-05-05",
        "Volume": 4940037.6905174265
    },
    {
        "Date": "2025-05-06",
        "Volume": 7016245.861512301
    },
    {
        "Date": "2025-05-07",
        "Volume": 6383202.231896381
    },
    {
        "Date": "2025-05-08",
        "Volume": 6134193.0060977945
    },
    {
        "Date": "2025-05-09",
        "Volume": 6122073.077682333
    },
    {
        "Date": "2025-05-10",
        "Volume": 7672200.590738288
    },
    {
        "Date": "2025-05-11",
        "Volume": 8087134.734198085
    },
    {
        "Date": "2025-05-12",
        "Volume": 7866726.296550456
    },
    {
        "Date": "2025-05-13",
        "Volume": 7936471.074875349
    },
    {
        "Date": "2025-05-14",
        "Volume": 8551685.871635895
    },
    {
        "Date": "2025-05-15",
        "Volume": 8751524.221768845
    },
    {
        "Date": "2025-05-16",
        "Volume": 5705974.266815318
    },
    {
        "Date": "2025-05-17",
        "Volume": 5516883.812382395
    },
    {
        "Date": "2025-05-18",
        "Volume": 6942369.777331139
    },
    {
        "Date": "2025-05-19",
        "Volume": 6701011.131290944
    },
    {
        "Date": "2025-05-20",
        "Volume": 6416834.061048529
    },
    {
        "Date": "2025-05-21",
        "Volume": 7256981.56165031
    },
    {
        "Date": "2025-05-22",
        "Volume": 6332337.1608553715
    },
    {
        "Date": "2025-05-23",
        "Volume": 5499827.888305098
    },
    {
        "Date": "2025-05-24",
        "Volume": 6186392.194237784
    },
    {
        "Date": "2025-05-25",
        "Volume": 6228598.31521901
    },
    {
        "Date": "2025-05-26",
        "Volume": 6097107.216572625
    },
    {
        "Date": "2025-05-27",
        "Volume": 6109287.691556863
    },
    {
        "Date": "2025-05-28",
        "Volume": 5202791.484718337
    },
    {
        "Date": "2025-05-29",
        "Volume": 5384076.96973511
    },
    {
        "Date": "2025-05-30",
        "Volume": 5940027.545769403
    },
    {
        "Date": "2025-05-31",
        "Volume": 8764708.764112482
    },
    {
        "Date": "2025-06-01",
        "Volume": 6806075.783960002
    },
    {
        "Date": "2025-06-02",
        "Volume": 7323297.629399532
    },
    {
        "Date": "2025-06-03",
        "Volume": 8661742.858266057
    },
    {
        "Date": "2025-06-04",
        "Volume": 7676268.541608277
    },
    {
        "Date": "2025-06-05",
        "Volume": 7027366.052770944
    },
    {
        "Date": "2025-06-06",
        "Volume": 8013784.074629267
    },
    {
        "Date": "2025-06-07",
        "Volume": 7079465.146647176
    },
    {
        "Date": "2025-06-08",
        "Volume": 6138676.33787667
    },
    {
        "Date": "2025-06-09",
        "Volume": 7126271.211352974
    },
    {
        "Date": "2025-06-10",
        "Volume": 10659596.877230847
    },
    {
        "Date": "2025-06-11",
        "Volume": 13449282.927504055
    },
    {
        "Date": "2025-06-12",
        "Volume": 8884960.559983684
    },
    {
        "Date": "2025-06-13",
        "Volume": 7447233.088253855
    },
    {
        "Date": "2025-06-14",
        "Volume": 12533470.391024083
    },
    {
        "Date": "2025-06-15",
        "Volume": 7937786.812208306
    },
    {
        "Date": "2025-06-16",
        "Volume": 7593139.467896213
    },
    {
        "Date": "2025-06-17",
        "Volume": 11101411.792034268
    },
    {
        "Date": "2025-06-18",
        "Volume": 8066882.657371176
    },
    {
        "Date": "2025-06-19",
        "Volume": 7565006.054691767
    },
    {
        "Date": "2025-06-20",
        "Volume": 8436444.12563259
    },
    {
        "Date": "2025-06-21",
        "Volume": 8323707.462732359
    },
    {
        "Date": "2025-06-22",
        "Volume": 5724759.025861726
    },
    {
        "Date": "2025-06-23",
        "Volume": 6199475.955999616
    },
    {
        "Date": "2025-06-24",
        "Volume": 10179758.293068055
    },
    {
        "Date": "2025-06-25",
        "Volume": 7018556.493736669
    },
    {
        "Date": "2025-06-26",
        "Volume": 5147644.528561184
    },
    {
        "Date": "2025-06-27",
        "Volume": 5035604.266577296
    },
    {
        "Date": "2025-06-28",
        "Volume": 5564564.354335637
    },
    {
        "Date": "2025-06-29",
        "Volume": 6401218.290888694
    },
    {
        "Date": "2025-06-30",
        "Volume": 7035969.255384924
    },
    {
        "Date": "2025-07-01",
        "Volume": 6635513.677230227
    },
    {
        "Date": "2025-07-02",
        "Volume": 5348049.255602402
    },
    {
        "Date": "2025-07-03",
        "Volume": 6777405.69853976
    },
    {
        "Date": "2025-07-04",
        "Volume": 6278924.51351767
    },
    {
        "Date": "2025-07-05",
        "Volume": 5509038.8216934325
    },
    {
        "Date": "2025-07-06",
        "Volume": 5619199.690836009
    },
    {
        "Date": "2025-07-07",
        "Volume": 6117782.623734045
    },
    {
        "Date": "2025-07-08",
        "Volume": 4912128.641163917
    },
    {
        "Date": "2025-07-09",
        "Volume": 5066339.01885333
    },
    {
        "Date": "2025-07-10",
        "Volume": 5332566.284027646
    },
    {
        "Date": "2025-07-11",
        "Volume": 8129925.467871833
    },
    {
        "Date": "2025-07-12",
        "Volume": 6168821.655532761
    },
    {
        "Date": "2025-07-13",
        "Volume": 2873038.080101554
    },
    {
        "Date": "2025-07-14",
        "Volume": 2103868.1405881257
    },
    {
        "Date": "2025-07-15",
        "Volume": 2785076.216658431
    },
    {
        "Date": "2025-07-16",
        "Volume": 3184898.959129965
    },
    {
        "Date": "2025-07-17",
        "Volume": 1981227.2877750383
    },
    {
        "Date": "2025-07-18",
        "Volume": 2513674.3569300366
    },
    {
        "Date": "2025-07-19",
        "Volume": 6858594.131206648
    },
    {
        "Date": "2025-07-20",
        "Volume": 1609372.633849582
    },
    {
        "Date": "2025-07-21",
        "Volume": 2778749.02285896
    },
    {
        "Date": "2025-07-22",
        "Volume": 2623812.0333735123
    },
    {
        "Date": "2025-07-23",
        "Volume": 4279929.39731867
    },
    {
        "Date": "2025-07-24",
        "Volume": 3920318.1571785444
    },
    {
        "Date": "2025-07-25",
        "Volume": 7406482.329748395
    },
    {
        "Date": "2025-07-26",
        "Volume": 5641239.79955325
    },
    {
        "Date": "2025-07-27",
        "Volume": 3964712.286862229
    },
    {
        "Date": "2025-07-28",
        "Volume": 2374674.0979485186
    },
    {
        "Date": "2025-07-29",
        "Volume": 4871116.229875908
    },
    {
        "Date": "2025-07-30",
        "Volume": 2848086.740705784
    },
    {
        "Date": "2025-07-31",
        "Volume": 2634654.6290892907
    },
    {
        "Date": "2025-08-01",
        "Volume": 2038357.9664012443
    },
    {
        "Date": "2025-08-02",
        "Volume": 2992628.6406171573
    },
    {
        "Date": "2025-08-03",
        "Volume": 1936368.704904749
    },
    {
        "Date": "2025-08-04",
        "Volume": 1506201.8475172666
    },
    {
        "Date": "2025-08-05",
        "Volume": 2218143.5766066383
    },
    {
        "Date": "2025-08-06",
        "Volume": 2706725.228513291
    },
    {
        "Date": "2025-08-07",
        "Volume": 2623048.2030801172
    },
    {
        "Date": "2025-08-08",
        "Volume": 1462017.0506987683
    },
    {
        "Date": "2025-08-09",
        "Volume": 3469624.651911279
    },
    {
        "Date": "2025-08-10",
        "Volume": 2429904.4992851214
    },
    {
        "Date": "2025-08-11",
        "Volume": 2006706.5163609625
    },
    {
        "Date": "2025-08-12",
        "Volume": 4548024.5822054
    },
    {
        "Date": "2025-08-13",
        "Volume": 3649931.6114205257
    },
    {
        "Date": "2025-08-14",
        "Volume": 5238272.683600921
    },
    {
        "Date": "2025-08-15",
        "Volume": 3662435.4789119707
    },
    {
        "Date": "2025-08-16",
        "Volume": 2289807.0729499515
    },
    {
        "Date": "2025-08-17",
        "Volume": 2137939.54175787
    },
    {
        "Date": "2025-08-18",
        "Volume": 5650575.546579243
    },
    {
        "Date": "2025-08-19",
        "Volume": 3218732.406928396
    },
    {
        "Date": "2025-08-20",
        "Volume": 3156728.417634337
    },
    {
        "Date": "2025-08-21",
        "Volume": 2737907.2096471777
    },
    {
        "Date": "2025-08-22",
        "Volume": 2395378.4314532685
    },
    {
        "Date": "2025-08-23",
        "Volume": 7898139.038875374
    },
    {
        "Date": "2025-08-24",
        "Volume": 4830367.221359956
    },
    {
        "Date": "2025-08-25",
        "Volume": 3334978.3347768676
    },
    {
        "Date": "2025-08-26",
        "Volume": 1237367.0171594224
    },
    {
        "Date": "2025-08-27",
        "Volume": 2287969.532306362
    },
    {
        "Date": "2025-08-28",
        "Volume": 1891391.5142210687
    },
    {
        "Date": "2025-08-29",
        "Volume": 1601534.0812959226
    },
    {
        "Date": "2025-08-30",
        "Volume": 2574791.550303142
    },
    {
        "Date": "2025-08-31",
        "Volume": 1925476.759153867
    },
    {
        "Date": "2025-09-01",
        "Volume": 1112428.4823170393
    },
    {
        "Date": "2025-09-02",
        "Volume": 1094586.9944442993
    },
    {
        "Date": "2025-09-03",
        "Volume": 7222348.231199754
    },
    {
        "Date": "2025-09-04",
        "Volume": 4116597.360720088
    },
    {
        "Date": "2025-09-05",
        "Volume": 4492624.218827394
    },
    {
        "Date": "2025-09-06",
        "Volume": 5272186.2889814405
    },
    {
        "Date": "2025-09-07",
        "Volume": 3896163.9546872242
    },
    {
        "Date": "2025-09-08",
        "Volume": 3176368.4991638497
    },
    {
        "Date": "2025-09-09",
        "Volume": 6817533.00170351
    },
    {
        "Date": "2025-09-10",
        "Volume": 27417639.816922456
    },
    {
        "Date": "2025-09-11",
        "Volume": 22117548.23157534
    },
    {
        "Date": "2025-09-12",
        "Volume": 35817884.63618688
    },
    {
        "Date": "2025-09-13",
        "Volume": 21280803.763618514
    },
    {
        "Date": "2025-09-14",
        "Volume": 18481025.138460927
    },
    {
        "Date": "2025-09-15",
        "Volume": 22813834.558189366
    },
    {
        "Date": "2025-09-16",
        "Volume": 13726626.850962948
    },
    {
        "Date": "2025-09-17",
        "Volume": 14862551.478657683
    },
    {
        "Date": "2025-09-18",
        "Volume": 77906365.373844
    },
    {
        "Date": "2025-09-19",
        "Volume": 33044895.13214773
    },
    {
        "Date": "2025-09-20",
        "Volume": 15978296.267252507
    },
    {
        "Date": "2025-09-21",
        "Volume": 26462771.859469075
    },
    {
        "Date": "2025-09-22",
        "Volume": 17304571.700462233
    },
    {
        "Date": "2025-09-23",
        "Volume": 25285150.871396855
    },
    {
        "Date": "2025-09-24",
        "Volume": 24361107.019139722
    },
    {
        "Date": "2025-09-25",
        "Volume": 31559861.266574837
    },
    {
        "Date": "2025-09-26",
        "Volume": 28340045.833769523
    },
    {
        "Date": "2025-09-27",
        "Volume": 20368280.172601946
    },
    {
        "Date": "2025-09-28",
        "Volume": 13418169.851688817
    },
    {
        "Date": "2025-09-29",
        "Volume": 17387368.200680524
    },
    {
        "Date": "2025-09-30",
        "Volume": 21915157.23638655
    },
    {
        "Date": "2025-10-01",
        "Volume": 24740896.453053426
    },
    {
        "Date": "2025-10-02",
        "Volume": 39056043.413944185
    },
    {
        "Date": "2025-10-03",
        "Volume": 23791099.412419252
    },
    {
        "Date": "2025-10-04",
        "Volume": 20193599.84440432
    },
    {
        "Date": "2025-10-05",
        "Volume": 14328514.457595106
    },
    {
        "Date": "2025-10-06",
        "Volume": 13729719.949978849
    },
    {
        "Date": "2025-10-07",
        "Volume": 14283932.64335073
    },
    {
        "Date": "2025-10-08",
        "Volume": 21317055.81834868
    },
    {
        "Date": "2025-10-09",
        "Volume": 13201045.108811075
    },
    {
        "Date": "2025-10-10",
        "Volume": 12844896.441150686
    },
    {
        "Date": "2025-10-11",
        "Volume": 47490057.37255334
    },
    {
        "Date": "2025-10-12",
        "Volume": 31645840.84606814
    },
    {
        "Date": "2025-10-13",
        "Volume": 12909794.78554418
    },
    {
        "Date": "2025-10-14",
        "Volume": 20971946.621502876
    },
    {
        "Date": "2025-10-15",
        "Volume": 24941485.195428807
    },
    {
        "Date": "2025-10-16",
        "Volume": 16990540.95156787
    },
    {
        "Date": "2025-10-17",
        "Volume": 15199350.732048247
    },
    {
        "Date": "2025-10-18",
        "Volume": 22747052.444776878
    },
    {
        "Date": "2025-10-19",
        "Volume": 6253296.062180726
    },
    {
        "Date": "2025-10-20",
        "Volume": 10556919.714213312
    },
    {
        "Date": "2025-10-21",
        "Volume": 9532027.859033654
    },
    {
        "Date": "2025-10-22",
        "Volume": 20605128.78675158
    },
    {
        "Date": "2025-10-23",
        "Volume": 14143939.858443452
    },
    {
        "Date": "2025-10-24",
        "Volume": 7519531.972011689
    },
    {
        "Date": "2025-10-25",
        "Volume": 8339851.277674018
    },
    {
        "Date": "2025-10-26",
        "Volume": 5386677.025658382
    },
    {
        "Date": "2025-10-27",
        "Volume": 6560937.752444935
    },
    {
        "Date": "2025-10-28",
        "Volume": 7619543.541406704
    },
    {
        "Date": "2025-10-29",
        "Volume": 8354321.781017441
    },
    {
        "Date": "2025-10-30",
        "Volume": 5849198.1512927795
    },
    {
        "Date": "2025-10-31",
        "Volume": 11899797.112374261
    },
    {
        "Date": "2025-11-01",
        "Volume": 10739510.893004274
    },
    {
        "Date": "2025-11-02",
        "Volume": 4488156.003373419
    },
    {
        "Date": "2025-11-03",
        "Volume": 5158410.643139819
    },
    {
        "Date": "2025-11-04",
        "Volume": 15173954.341553729
    },
    {
        "Date": "2025-11-05",
        "Volume": 19647589.636768915
    },
    {
        "Date": "2025-11-06",
        "Volume": 14665645.421064591
    },
    {
        "Date": "2025-11-07",
        "Volume": 9259703.910360632
    },
    {
        "Date": "2025-11-08",
        "Volume": 15817090.154466415
    },
    {
        "Date": "2025-11-09",
        "Volume": 9742910.761541795
    },
    {
        "Date": "2025-11-10",
        "Volume": 7098273.0732958205
    },
    {
        "Date": "2025-11-11",
        "Volume": 9661679.23883338
    },
    {
        "Date": "2025-11-12",
        "Volume": 12264528.810786387
    },
    {
        "Date": "2025-11-13",
        "Volume": 44215024.76410336
    },
    {
        "Date": "2025-11-14",
        "Volume": 20041060.819734327
    },
    {
        "Date": "2025-11-15",
        "Volume": 19231937.634512484
    },
    {
        "Date": "2025-11-16",
        "Volume": 11881483.93678978
    },
    {
        "Date": "2025-11-17",
        "Volume": 10226408.460571416
    },
    {
        "Date": "2025-11-18",
        "Volume": 10479279.926527774
    },
    {
        "Date": "2025-11-19",
        "Volume": 11140466.055591602
    },
    {
        "Date": "2025-11-20",
        "Volume": 9689190.04211365
    },
    {
        "Date": "2025-11-21",
        "Volume": 10475371.184819175
    },
    {
        "Date": "2025-11-22",
        "Volume": 21639851.679829974
    },
    {
        "Date": "2025-11-23",
        "Volume": 18389753.68848671
    },
    {
        "Date": "2025-11-24",
        "Volume": 7701317.191756641
    },
    {
        "Date": "2025-11-25",
        "Volume": 11973131.881413903
    },
    {
        "Date": "2025-11-26",
        "Volume": 11622012.2685106
    },
    {
        "Date": "2025-11-27",
        "Volume": 15041627.190385476
    },
    {
        "Date": "2025-11-28",
        "Volume": 22468600.384978227
    },
    {
        "Date": "2025-11-29",
        "Volume": 32654973.5736346
    },
    {
        "Date": "2025-11-30",
        "Volume": 34182129.21385226
    },
    {
        "Date": "2025-12-01",
        "Volume": 26897663.113658212
    },
    {
        "Date": "2025-12-02",
        "Volume": 20598751.066691775
    },
    {
        "Date": "2025-12-03",
        "Volume": 25211218.556960467
    },
    {
        "Date": "2025-12-04",
        "Volume": 22605363.596465066
    },
    {
        "Date": "2025-12-05",
        "Volume": 16173903.046997719
    },
    {
        "Date": "2025-12-06",
        "Volume": 13231668.184539527
    },
    {
        "Date": "2025-12-07",
        "Volume": 7848752.762803835
    },
    {
        "Date": "2025-12-08",
        "Volume": 8843256.757324774
    },
    {
        "Date": "2025-12-09",
        "Volume": 7886567.417804455
    },
    {
        "Date": "2025-12-10",
        "Volume": 12372158.386966925
    },
    {
        "Date": "2025-12-11",
        "Volume": 9868052.271946825
    },
    {
        "Date": "2025-12-12",
        "Volume": 7953186.245433142
    },
    {
        "Date": "2025-12-13",
        "Volume": 13943547.835097851
    },
    {
        "Date": "2025-12-14",
        "Volume": 6902821.960593785
    },
    {
        "Date": "2025-12-15",
        "Volume": 13772344.623144843
    },
    {
        "Date": "2025-12-16",
        "Volume": 16936943.921804935
    },
    {
        "Date": "2025-12-17",
        "Volume": 11865710.151302699
    },
    {
        "Date": "2025-12-18",
        "Volume": 13633847.13877398
    },
    {
        "Date": "2025-12-19",
        "Volume": 12071175.009535655
    },
    {
        "Date": "2025-12-20",
        "Volume": 14491968.687326655
    },
    {
        "Date": "2025-12-21",
        "Volume": 12535675.201417714
    },
    {
        "Date": "2025-12-22",
        "Volume": 14198264.743702747
    },
    {
        "Date": "2025-12-23",
        "Volume": 20167464.049118567
    },
    {
        "Date": "2025-12-24",
        "Volume": 13451197.310732547
    },
    {
        "Date": "2025-12-25",
        "Volume": 15282180.715118518
    },
    {
        "Date": "2025-12-26",
        "Volume": 11762886.076000242
    },
    {
        "Date": "2025-12-27",
        "Volume": 20000361.606279094
    },
    {
        "Date": "2025-12-28",
        "Volume": 17422514.085392077
    },
    {
        "Date": "2025-12-29",
        "Volume": 9684076.667552577
    },
    {
        "Date": "2025-12-30",
        "Volume": 11031657.553055715
    },
    {
        "Date": "2025-12-31",
        "Volume": 6730265.079624618
    },
    {
        "Date": "2026-01-01",
        "Volume": 10527650.897914046
    },
    {
        "Date": "2026-01-02",
        "Volume": 5496477.348232905
    },
    {
        "Date": "2026-01-03",
        "Volume": 9913090.112015994
    },
    {
        "Date": "2026-01-04",
        "Volume": 12615696.472243555
    },
    {
        "Date": "2026-01-05",
        "Volume": 10120260.044530427
    },
    {
        "Date": "2026-01-06",
        "Volume": 10360861.833627954
    },
    {
        "Date": "2026-01-07",
        "Volume": 11500142.734087344
    },
    {
        "Date": "2026-01-08",
        "Volume": 7482523.252064068
    },
    {
        "Date": "2026-01-09",
        "Volume": 10799763.727918688
    },
    {
        "Date": "2026-01-10",
        "Volume": 12248349.487876916
    },
    {
        "Date": "2026-01-11",
        "Volume": 9945127.8043339
    },
    {
        "Date": "2026-01-12",
        "Volume": 9316035.97953762
    },
    {
        "Date": "2026-01-13",
        "Volume": 13948540.957162185
    },
    {
        "Date": "2026-01-14",
        "Volume": 11193243.545541495
    },
    {
        "Date": "2026-01-15",
        "Volume": 8245965.807010596
    },
    {
        "Date": "2026-01-16",
        "Volume": 7894799.280178844
    },
    {
        "Date": "2026-01-17",
        "Volume": 18103655.342159532
    },
    {
        "Date": "2026-01-18",
        "Volume": 9693290.153113546
    },
    {
        "Date": "2026-01-19",
        "Volume": 7829606.024456993
    },
    {
        "Date": "2026-01-20",
        "Volume": 19944591.237167504
    },
    {
        "Date": "2026-01-21",
        "Volume": 11351232.717597065
    },
    {
        "Date": "2026-01-22",
        "Volume": 14354842.202393979
    },
    {
        "Date": "2026-01-23",
        "Volume": 23607145.78817586
    },
    {
        "Date": "2026-01-24",
        "Volume": 13214583.497710684
    },
    {
        "Date": "2026-01-25",
        "Volume": 6343053.630841547
    },
    {
        "Date": "2026-01-26",
        "Volume": 10110498.3845474
    },
    {
        "Date": "2026-01-27",
        "Volume": 12204404.477593657
    },
    {
        "Date": "2026-01-28",
        "Volume": 8648180.547675062
    },
    {
        "Date": "2026-01-29",
        "Volume": 12028165.387741646
    },
    {
        "Date": "2026-01-30",
        "Volume": 16990907.800873756
    },
    {
        "Date": "2026-01-31",
        "Volume": 16169702.936295813
    },
    {
        "Date": "2026-02-01",
        "Volume": 36093476.830027014
    },
    {
        "Date": "2026-02-02",
        "Volume": 17015209.01043589
    },
    {
        "Date": "2026-02-03",
        "Volume": 21669709.99866917
    },
    {
        "Date": "2026-02-04",
        "Volume": 26556177.052494798
    },
    {
        "Date": "2026-02-05",
        "Volume": 22709785.804916967
    },
    {
        "Date": "2026-02-06",
        "Volume": 38904130.5003608
    },
    {
        "Date": "2026-02-07",
        "Volume": 44457641.51978007
    },
    {
        "Date": "2026-02-08",
        "Volume": 24898956.15133515
    },
    {
        "Date": "2026-02-09",
        "Volume": 32644515.927326247
    },
    {
        "Date": "2026-02-10",
        "Volume": 30487832.893890154
    },
    {
        "Date": "2026-02-11",
        "Volume": 14945634.72261209
    },
    {
        "Date": "2026-02-12",
        "Volume": 15976495.943414044
    },
    {
        "Date": "2026-02-13",
        "Volume": 7640645.553353955
    },
    {
        "Date": "2026-02-14",
        "Volume": 12655358.116140611
    },
    {
        "Date": "2026-02-15",
        "Volume": 8693915.285430128
    },
    {
        "Date": "2026-02-16",
        "Volume": 8410270.058578901
    },
    {
        "Date": "2026-02-17",
        "Volume": 6028442.195657612
    },
    {
        "Date": "2026-02-18",
        "Volume": 10785195.503503272
    },
    {
        "Date": "2026-02-19",
        "Volume": 16307141.74972199
    },
    {
        "Date": "2026-02-20",
        "Volume": 10205621.38811983
    },
    {
        "Date": "2026-02-21",
        "Volume": 8563036.663639456
    },
    {
        "Date": "2026-02-22",
        "Volume": 6320981.724265118
    },
    {
        "Date": "2026-02-23",
        "Volume": 4680676.0318252565
    },
    {
        "Date": "2026-02-24",
        "Volume": 11125729.739784583
    },
    {
        "Date": "2026-02-25",
        "Volume": 8998117.364868354
    },
    {
        "Date": "2026-02-26",
        "Volume": 15863241.299775954
    },
    {
        "Date": "2026-02-27",
        "Volume": 8969139.143263625
    },
    {
        "Date": "2026-02-28",
        "Volume": 8694180.972262086
    },
    {
        "Date": "2026-03-01",
        "Volume": 9968695.24451301
    },
    {
        "Date": "2026-03-02",
        "Volume": 10486417.343089668
    },
    {
        "Date": "2026-03-03",
        "Volume": 12310108.31387502
    },
    {
        "Date": "2026-03-04",
        "Volume": 15124380.947909664
    },
    {
        "Date": "2026-03-05",
        "Volume": 18992987.93848814
    },
    {
        "Date": "2026-03-06",
        "Volume": 19926607.316361185
    },
    {
        "Date": "2026-03-07",
        "Volume": 9494684.472137097
    },
    {
        "Date": "2026-03-08",
        "Volume": 10415596.072739415
    },
    {
        "Date": "2026-03-09",
        "Volume": 8084898.37305956
    },
    {
        "Date": "2026-03-10",
        "Volume": 10032961.957951365
    },
    {
        "Date": "2026-03-11",
        "Volume": 20174222.86997088
    },
    {
        "Date": "2026-03-12",
        "Volume": 15401762.958675677
    },
    {
        "Date": "2026-03-13",
        "Volume": 16129689.259349912
    },
    {
        "Date": "2026-03-14",
        "Volume": 17257478.58760181
    },
    {
        "Date": "2026-03-15",
        "Volume": 11544150.078467675
    },
    {
        "Date": "2026-03-16",
        "Volume": 10636606.361360205
    },
    {
        "Date": "2026-03-17",
        "Volume": 25505780.583414648
    },
    {
        "Date": "2026-03-18",
        "Volume": 20018532.574389145
    },
    {
        "Date": "2026-03-19",
        "Volume": 16273464.231057497
    },
    {
        "Date": "2026-03-20",
        "Volume": 10143869.152827816
    }
]