{
    "ultimo_valore_indice": 19775.377211433744,
    "variazione_24h_pct": -0.011735364121527314,
    "variazione_7g_pct": -0.01244188528809742,
    "variazione_ytd_pct": -0.28462619632132213,
    "ultima_allocazione_pesi": {
        "ETH": 0.7918286633564661,
        "SOL": 0.15182928403411228,
        "ADA": 0.027886566268518896,
        "AVAX": 0.012354780157262435,
        "DOT": 0.006488677909473475,
        "NEAR": 0.009612028274167031
    },
    "capitalizzazione_mercato": {
        "ETH": 219098269328.492,
        "SOL": 42681928371.293,
        "ADA": 7805926877.158999,
        "AVAX": 3487054925.277,
        "DOT": 1834861143.16,
        "NEAR": 2730935244.7139997
    },
    "rendimenti_annuali": {
        "2021": 38.8,
        "2022": -71.4,
        "2023": 108.3,
        "2024": 54.3,
        "2025": -31.9,
        "2026": -28.5
    },
    "benchmark_annuali": {
        "2021": 27.5,
        "2022": -62.1,
        "2023": 149.0,
        "2024": 134.7,
        "2025": -17.4,
        "2026": -11.2
    }
}