[
  {
    "data": "2021-09-30",
    "prezzo": 57.48
  },
  {
    "data": "2021-10-01",
    "prezzo": 58.41
  },
  {
    "data": "2021-10-02",
    "prezzo": 60.15
  },
  {
    "data": "2021-10-03",
    "prezzo": 59.56
  },
  {
    "data": "2021-10-04",
    "prezzo": 56.17
  },
  {
    "data": "2021-10-05",
    "prezzo": 55.82
  },
  {
    "data": "2021-10-06",
    "prezzo": 51.42
  },
  {
    "data": "2021-10-07",
    "prezzo": 53.23
  },
  {
    "data": "2021-10-08",
    "prezzo": 52.2
  },
  {
    "data": "2021-10-09",
    "prezzo": 52.29
  },
  {
    "data": "2021-10-10",
    "prezzo": 49.05
  },
  {
    "data": "2021-10-11",
    "prezzo": 47.81
  },
  {
    "data": "2021-10-12",
    "prezzo": 46.98
  },
  {
    "data": "2021-10-13",
    "prezzo": 47.43
  },
  {
    "data": "2021-10-14",
    "prezzo": 48.38
  },
  {
    "data": "2021-10-15",
    "prezzo": 48.47
  },
  {
    "data": "2021-10-16",
    "prezzo": 49.35
  },
  {
    "data": "2021-10-17",
    "prezzo": 48.29
  },
  {
    "data": "2021-10-18",
    "prezzo": 47.81
  },
  {
    "data": "2021-10-19",
    "prezzo": 48.9
  },
  {
    "data": "2021-10-20",
    "prezzo": 51.12
  },
  {
    "data": "2021-10-21",
    "prezzo": 52.81
  },
  {
    "data": "2021-10-22",
    "prezzo": 56.25
  },
  {
    "data": "2021-10-23",
    "prezzo": 56.26
  },
  {
    "data": "2021-10-24",
    "prezzo": 55.95
  },
  {
    "data": "2021-10-25",
    "prezzo": 60.2
  },
  {
    "data": "2021-10-26",
    "prezzo": 59.56
  },
  {
    "data": "2021-10-27",
    "prezzo": 53.45
  },
  {
    "data": "2021-10-28",
    "prezzo": 55.15
  },
  {
    "data": "2021-10-29",
    "prezzo": 55.98
  },
  {
    "data": "2021-10-30",
    "prezzo": 54.02
  },
  {
    "data": "2021-10-31",
    "prezzo": 55.7
  },
  {
    "data": "2021-11-01",
    "prezzo": 56.07
  },
  {
    "data": "2021-11-02",
    "prezzo": 58.71
  },
  {
    "data": "2021-11-03",
    "prezzo": 65.99
  },
  {
    "data": "2021-11-04",
    "prezzo": 68.82
  },
  {
    "data": "2021-11-05",
    "prezzo": 64.34
  },
  {
    "data": "2021-11-06",
    "prezzo": 67.79
  },
  {
    "data": "2021-11-07",
    "prezzo": 75.9
  },
  {
    "data": "2021-11-08",
    "prezzo": 78.86
  },
  {
    "data": "2021-11-09",
    "prezzo": 76.55
  },
  {
    "data": "2021-11-10",
    "prezzo": 75.07
  },
  {
    "data": "2021-11-11",
    "prezzo": 77.45
  },
  {
    "data": "2021-11-12",
    "prezzo": 74.38
  },
  {
    "data": "2021-11-13",
    "prezzo": 85.76
  },
  {
    "data": "2021-11-14",
    "prezzo": 83.82
  },
  {
    "data": "2021-11-15",
    "prezzo": 82.78
  },
  {
    "data": "2021-11-16",
    "prezzo": 86.42
  },
  {
    "data": "2021-11-17",
    "prezzo": 95.15
  },
  {
    "data": "2021-11-18",
    "prezzo": 89.41
  },
  {
    "data": "2021-11-19",
    "prezzo": 99.74
  },
  {
    "data": "2021-11-20",
    "prezzo": 111.88
  },
  {
    "data": "2021-11-21",
    "prezzo": 114.25
  },
  {
    "data": "2021-11-22",
    "prezzo": 120.45
  },
  {
    "data": "2021-11-23",
    "prezzo": 110.22
  },
  {
    "data": "2021-11-24",
    "prezzo": 102.85
  },
  {
    "data": "2021-11-25",
    "prezzo": 106.53
  },
  {
    "data": "2021-11-26",
    "prezzo": 92.46
  },
  {
    "data": "2021-11-27",
    "prezzo": 100.13
  },
  {
    "data": "2021-11-28",
    "prezzo": 98.06
  },
  {
    "data": "2021-11-29",
    "prezzo": 107.11
  },
  {
    "data": "2021-11-30",
    "prezzo": 106.83
  },
  {
    "data": "2021-12-01",
    "prezzo": 105.87
  },
  {
    "data": "2021-12-02",
    "prezzo": 95.39
  },
  {
    "data": "2021-12-03",
    "prezzo": 96.08
  },
  {
    "data": "2021-12-04",
    "prezzo": 82.51
  },
  {
    "data": "2021-12-05",
    "prezzo": 76.4
  },
  {
    "data": "2021-12-06",
    "prezzo": 82.64
  },
  {
    "data": "2021-12-07",
    "prezzo": 79.48
  },
  {
    "data": "2021-12-08",
    "prezzo": 82.29
  },
  {
    "data": "2021-12-09",
    "prezzo": 75.64
  },
  {
    "data": "2021-12-10",
    "prezzo": 71.3
  },
  {
    "data": "2021-12-11",
    "prezzo": 76.59
  },
  {
    "data": "2021-12-12",
    "prezzo": 78.14
  },
  {
    "data": "2021-12-13",
    "prezzo": 70.03
  },
  {
    "data": "2021-12-14",
    "prezzo": 77.51
  },
  {
    "data": "2021-12-15",
    "prezzo": 89.84
  },
  {
    "data": "2021-12-16",
    "prezzo": 86.72
  },
  {
    "data": "2021-12-17",
    "prezzo": 98.66
  },
  {
    "data": "2021-12-18",
    "prezzo": 102.94
  },
  {
    "data": "2021-12-19",
    "prezzo": 95.59
  },
  {
    "data": "2021-12-20",
    "prezzo": 100.78
  },
  {
    "data": "2021-12-21",
    "prezzo": 109.3
  },
  {
    "data": "2021-12-22",
    "prezzo": 103.02
  },
  {
    "data": "2021-12-23",
    "prezzo": 107.23
  },
  {
    "data": "2021-12-24",
    "prezzo": 101.57
  },
  {
    "data": "2021-12-25",
    "prezzo": 101.49
  },
  {
    "data": "2021-12-26",
    "prezzo": 101.74
  },
  {
    "data": "2021-12-27",
    "prezzo": 100.58
  },
  {
    "data": "2021-12-28",
    "prezzo": 94.83
  },
  {
    "data": "2021-12-29",
    "prezzo": 90.94
  },
  {
    "data": "2021-12-30",
    "prezzo": 89.93
  },
  {
    "data": "2021-12-31",
    "prezzo": 96.27
  },
  {
    "data": "2022-01-01",
    "prezzo": 100.63
  },
  {
    "data": "2022-01-02",
    "prezzo": 99.63
  },
  {
    "data": "2022-01-03",
    "prezzo": 95.81
  },
  {
    "data": "2022-01-04",
    "prezzo": 91.65
  },
  {
    "data": "2022-01-05",
    "prezzo": 86.0
  },
  {
    "data": "2022-01-06",
    "prezzo": 84.4
  },
  {
    "data": "2022-01-07",
    "prezzo": 76.43
  },
  {
    "data": "2022-01-08",
    "prezzo": 74.02
  },
  {
    "data": "2022-01-09",
    "prezzo": 78.68
  },
  {
    "data": "2022-01-10",
    "prezzo": 74.64
  },
  {
    "data": "2022-01-11",
    "prezzo": 78.87
  },
  {
    "data": "2022-01-12",
    "prezzo": 84.02
  },
  {
    "data": "2022-01-13",
    "prezzo": 78.48
  },
  {
    "data": "2022-01-14",
    "prezzo": 79.23
  },
  {
    "data": "2022-01-15",
    "prezzo": 81.6
  },
  {
    "data": "2022-01-16",
    "prezzo": 80.95
  },
  {
    "data": "2022-01-17",
    "prezzo": 76.02
  },
  {
    "data": "2022-01-18",
    "prezzo": 76.13
  },
  {
    "data": "2022-01-19",
    "prezzo": 72.87
  },
  {
    "data": "2022-01-20",
    "prezzo": 70.06
  },
  {
    "data": "2022-01-21",
    "prezzo": 58.3
  },
  {
    "data": "2022-01-22",
    "prezzo": 52.79
  },
  {
    "data": "2022-01-23",
    "prezzo": 57.28
  },
  {
    "data": "2022-01-24",
    "prezzo": 55.6
  },
  {
    "data": "2022-01-25",
    "prezzo": 60.29
  },
  {
    "data": "2022-01-26",
    "prezzo": 58.65
  },
  {
    "data": "2022-01-27",
    "prezzo": 58.11
  },
  {
    "data": "2022-01-28",
    "prezzo": 60.17
  },
  {
    "data": "2022-01-29",
    "prezzo": 64.65
  },
  {
    "data": "2022-01-30",
    "prezzo": 60.97
  },
  {
    "data": "2022-01-31",
    "prezzo": 62.26
  },
  {
    "data": "2022-02-01",
    "prezzo": 65.11
  },
  {
    "data": "2022-02-02",
    "prezzo": 59.9
  },
  {
    "data": "2022-02-03",
    "prezzo": 59.9
  },
  {
    "data": "2022-02-04",
    "prezzo": 67.89
  },
  {
    "data": "2022-02-05",
    "prezzo": 67.43
  },
  {
    "data": "2022-02-06",
    "prezzo": 69.26
  },
  {
    "data": "2022-02-07",
    "prezzo": 72.9
  },
  {
    "data": "2022-02-08",
    "prezzo": 75.79
  },
  {
    "data": "2022-02-09",
    "prezzo": 78.88
  },
  {
    "data": "2022-02-10",
    "prezzo": 80.05
  },
  {
    "data": "2022-02-11",
    "prezzo": 72.11
  },
  {
    "data": "2022-02-12",
    "prezzo": 71.69
  },
  {
    "data": "2022-02-13",
    "prezzo": 68.9
  },
  {
    "data": "2022-02-14",
    "prezzo": 72.42
  },
  {
    "data": "2022-02-15",
    "prezzo": 82.0
  },
  {
    "data": "2022-02-16",
    "prezzo": 83.82
  },
  {
    "data": "2022-02-17",
    "prezzo": 77.7
  },
  {
    "data": "2022-02-18",
    "prezzo": 73.84
  },
  {
    "data": "2022-02-19",
    "prezzo": 75.08
  },
  {
    "data": "2022-02-20",
    "prezzo": 68.34
  },
  {
    "data": "2022-02-21",
    "prezzo": 61.93
  },
  {
    "data": "2022-02-22",
    "prezzo": 65.73
  },
  {
    "data": "2022-02-23",
    "prezzo": 65.02
  },
  {
    "data": "2022-02-24",
    "prezzo": 68.27
  },
  {
    "data": "2022-02-25",
    "prezzo": 71.77
  },
  {
    "data": "2022-02-26",
    "prezzo": 72.61
  },
  {
    "data": "2022-02-27",
    "prezzo": 67.1
  },
  {
    "data": "2022-02-28",
    "prezzo": 75.4
  },
  {
    "data": "2022-03-01",
    "prezzo": 78.08
  },
  {
    "data": "2022-03-02",
    "prezzo": 75.08
  },
  {
    "data": "2022-03-03",
    "prezzo": 70.68
  },
  {
    "data": "2022-03-04",
    "prezzo": 69.36
  },
  {
    "data": "2022-03-05",
    "prezzo": 70.1
  },
  {
    "data": "2022-03-06",
    "prezzo": 66.7
  },
  {
    "data": "2022-03-07",
    "prezzo": 66.09
  },
  {
    "data": "2022-03-08",
    "prezzo": 66.99
  },
  {
    "data": "2022-03-09",
    "prezzo": 70.34
  },
  {
    "data": "2022-03-10",
    "prezzo": 67.2
  },
  {
    "data": "2022-03-11",
    "prezzo": 65.31
  },
  {
    "data": "2022-03-12",
    "prezzo": 65.08
  },
  {
    "data": "2022-03-13",
    "prezzo": 62.16
  },
  {
    "data": "2022-03-14",
    "prezzo": 63.07
  },
  {
    "data": "2022-03-15",
    "prezzo": 63.73
  },
  {
    "data": "2022-03-16",
    "prezzo": 67.25
  },
  {
    "data": "2022-03-17",
    "prezzo": 71.58
  },
  {
    "data": "2022-03-18",
    "prezzo": 77.69
  },
  {
    "data": "2022-03-19",
    "prezzo": 80.95
  },
  {
    "data": "2022-03-20",
    "prezzo": 76.78
  },
  {
    "data": "2022-03-21",
    "prezzo": 78.2
  },
  {
    "data": "2022-03-22",
    "prezzo": 76.1
  },
  {
    "data": "2022-03-23",
    "prezzo": 78.14
  },
  {
    "data": "2022-03-24",
    "prezzo": 79.62
  },
  {
    "data": "2022-03-25",
    "prezzo": 76.09
  },
  {
    "data": "2022-03-26",
    "prezzo": 78.28
  },
  {
    "data": "2022-03-27",
    "prezzo": 81.83
  },
  {
    "data": "2022-03-28",
    "prezzo": 81.49
  },
  {
    "data": "2022-03-29",
    "prezzo": 83.5
  },
  {
    "data": "2022-03-30",
    "prezzo": 85.3
  },
  {
    "data": "2022-03-31",
    "prezzo": 88.0
  },
  {
    "data": "2022-04-01",
    "prezzo": 87.7
  },
  {
    "data": "2022-04-02",
    "prezzo": 87.2
  },
  {
    "data": "2022-04-03",
    "prezzo": 88.79
  },
  {
    "data": "2022-04-04",
    "prezzo": 87.61
  },
  {
    "data": "2022-04-05",
    "prezzo": 83.48
  },
  {
    "data": "2022-04-06",
    "prezzo": 76.17
  },
  {
    "data": "2022-04-07",
    "prezzo": 80.6
  },
  {
    "data": "2022-04-08",
    "prezzo": 77.07
  },
  {
    "data": "2022-04-09",
    "prezzo": 78.0
  },
  {
    "data": "2022-04-10",
    "prezzo": 74.42
  },
  {
    "data": "2022-04-11",
    "prezzo": 68.53
  },
  {
    "data": "2022-04-12",
    "prezzo": 70.57
  },
  {
    "data": "2022-04-13",
    "prezzo": 73.49
  },
  {
    "data": "2022-04-14",
    "prezzo": 71.03
  },
  {
    "data": "2022-04-15",
    "prezzo": 71.67
  },
  {
    "data": "2022-04-16",
    "prezzo": 71.98
  },
  {
    "data": "2022-04-17",
    "prezzo": 69.76
  },
  {
    "data": "2022-04-18",
    "prezzo": 72.18
  },
  {
    "data": "2022-04-19",
    "prezzo": 74.24
  },
  {
    "data": "2022-04-20",
    "prezzo": 72.3
  },
  {
    "data": "2022-04-21",
    "prezzo": 69.24
  },
  {
    "data": "2022-04-22",
    "prezzo": 68.53
  },
  {
    "data": "2022-04-23",
    "prezzo": 67.53
  },
  {
    "data": "2022-04-24",
    "prezzo": 66.33
  },
  {
    "data": "2022-04-25",
    "prezzo": 68.06
  },
  {
    "data": "2022-04-26",
    "prezzo": 64.55
  },
  {
    "data": "2022-04-27",
    "prezzo": 66.15
  },
  {
    "data": "2022-04-28",
    "prezzo": 64.05
  },
  {
    "data": "2022-04-29",
    "prezzo": 60.13
  },
  {
    "data": "2022-04-30",
    "prezzo": 54.1
  },
  {
    "data": "2022-05-01",
    "prezzo": 55.74
  },
  {
    "data": "2022-05-02",
    "prezzo": 57.4
  },
  {
    "data": "2022-05-03",
    "prezzo": 56.61
  },
  {
    "data": "2022-05-04",
    "prezzo": 63.37
  },
  {
    "data": "2022-05-05",
    "prezzo": 56.0
  },
  {
    "data": "2022-05-06",
    "prezzo": 54.2
  },
  {
    "data": "2022-05-07",
    "prezzo": 52.18
  },
  {
    "data": "2022-05-08",
    "prezzo": 48.98
  },
  {
    "data": "2022-05-09",
    "prezzo": 38.92
  },
  {
    "data": "2022-05-10",
    "prezzo": 42.31
  },
  {
    "data": "2022-05-11",
    "prezzo": 29.61
  },
  {
    "data": "2022-05-12",
    "prezzo": 29.09
  },
  {
    "data": "2022-05-13",
    "prezzo": 30.92
  },
  {
    "data": "2022-05-14",
    "prezzo": 32.58
  },
  {
    "data": "2022-05-15",
    "prezzo": 35.13
  },
  {
    "data": "2022-05-16",
    "prezzo": 31.17
  },
  {
    "data": "2022-05-17",
    "prezzo": 32.58
  },
  {
    "data": "2022-05-18",
    "prezzo": 28.18
  },
  {
    "data": "2022-05-19",
    "prezzo": 28.7
  },
  {
    "data": "2022-05-20",
    "prezzo": 27.24
  },
  {
    "data": "2022-05-21",
    "prezzo": 28.26
  },
  {
    "data": "2022-05-22",
    "prezzo": 29.94
  },
  {
    "data": "2022-05-23",
    "prezzo": 27.17
  },
  {
    "data": "2022-05-24",
    "prezzo": 27.06
  },
  {
    "data": "2022-05-25",
    "prezzo": 25.48
  },
  {
    "data": "2022-05-26",
    "prezzo": 21.83
  },
  {
    "data": "2022-05-27",
    "prezzo": 21.01
  },
  {
    "data": "2022-05-28",
    "prezzo": 23.03
  },
  {
    "data": "2022-05-29",
    "prezzo": 24.35
  },
  {
    "data": "2022-05-30",
    "prezzo": 25.69
  },
  {
    "data": "2022-05-31",
    "prezzo": 24.6
  },
  {
    "data": "2022-06-01",
    "prezzo": 22.22
  },
  {
    "data": "2022-06-02",
    "prezzo": 22.9
  },
  {
    "data": "2022-06-03",
    "prezzo": 21.44
  },
  {
    "data": "2022-06-04",
    "prezzo": 22.92
  },
  {
    "data": "2022-06-05",
    "prezzo": 22.52
  },
  {
    "data": "2022-06-06",
    "prezzo": 24.27
  },
  {
    "data": "2022-06-07",
    "prezzo": 23.06
  },
  {
    "data": "2022-06-08",
    "prezzo": 22.81
  },
  {
    "data": "2022-06-09",
    "prezzo": 22.91
  },
  {
    "data": "2022-06-10",
    "prezzo": 20.98
  },
  {
    "data": "2022-06-11",
    "prezzo": 18.91
  },
  {
    "data": "2022-06-12",
    "prezzo": 16.47
  },
  {
    "data": "2022-06-13",
    "prezzo": 15.47
  },
  {
    "data": "2022-06-14",
    "prezzo": 15.84
  },
  {
    "data": "2022-06-15",
    "prezzo": 17.51
  },
  {
    "data": "2022-06-16",
    "prezzo": 14.92
  },
  {
    "data": "2022-06-17",
    "prezzo": 15.27
  },
  {
    "data": "2022-06-18",
    "prezzo": 14.16
  },
  {
    "data": "2022-06-19",
    "prezzo": 15.35
  },
  {
    "data": "2022-06-20",
    "prezzo": 16.2
  },
  {
    "data": "2022-06-21",
    "prezzo": 16.02
  },
  {
    "data": "2022-06-22",
    "prezzo": 15.2
  },
  {
    "data": "2022-06-23",
    "prezzo": 17.35
  },
  {
    "data": "2022-06-24",
    "prezzo": 19.42
  },
  {
    "data": "2022-06-25",
    "prezzo": 20.22
  },
  {
    "data": "2022-06-26",
    "prezzo": 18.66
  },
  {
    "data": "2022-06-27",
    "prezzo": 18.26
  },
  {
    "data": "2022-06-28",
    "prezzo": 17.2
  },
  {
    "data": "2022-06-29",
    "prezzo": 17.01
  },
  {
    "data": "2022-06-30",
    "prezzo": 16.17
  },
  {
    "data": "2022-07-01",
    "prezzo": 15.45
  },
  {
    "data": "2022-07-02",
    "prezzo": 15.66
  },
  {
    "data": "2022-07-03",
    "prezzo": 15.93
  },
  {
    "data": "2022-07-04",
    "prezzo": 17.1
  },
  {
    "data": "2022-07-05",
    "prezzo": 17.61
  },
  {
    "data": "2022-07-06",
    "prezzo": 18.8
  },
  {
    "data": "2022-07-07",
    "prezzo": 19.91
  },
  {
    "data": "2022-07-08",
    "prezzo": 19.35
  },
  {
    "data": "2022-07-09",
    "prezzo": 19.57
  },
  {
    "data": "2022-07-10",
    "prezzo": 18.81
  },
  {
    "data": "2022-07-11",
    "prezzo": 17.18
  },
  {
    "data": "2022-07-12",
    "prezzo": 16.7
  },
  {
    "data": "2022-07-13",
    "prezzo": 18.74
  },
  {
    "data": "2022-07-14",
    "prezzo": 19.77
  },
  {
    "data": "2022-07-15",
    "prezzo": 19.24
  },
  {
    "data": "2022-07-16",
    "prezzo": 21.17
  },
  {
    "data": "2022-07-17",
    "prezzo": 20.41
  },
  {
    "data": "2022-07-18",
    "prezzo": 23.62
  },
  {
    "data": "2022-07-19",
    "prezzo": 24.2
  },
  {
    "data": "2022-07-20",
    "prezzo": 23.28
  },
  {
    "data": "2022-07-21",
    "prezzo": 24.48
  },
  {
    "data": "2022-07-22",
    "prezzo": 23.17
  },
  {
    "data": "2022-07-23",
    "prezzo": 23.18
  },
  {
    "data": "2022-07-24",
    "prezzo": 23.34
  },
  {
    "data": "2022-07-25",
    "prezzo": 20.44
  },
  {
    "data": "2022-07-26",
    "prezzo": 20.49
  },
  {
    "data": "2022-07-27",
    "prezzo": 22.94
  },
  {
    "data": "2022-07-28",
    "prezzo": 23.75
  },
  {
    "data": "2022-07-29",
    "prezzo": 24.01
  },
  {
    "data": "2022-07-30",
    "prezzo": 23.73
  },
  {
    "data": "2022-07-31",
    "prezzo": 23.24
  },
  {
    "data": "2022-08-01",
    "prezzo": 22.98
  },
  {
    "data": "2022-08-02",
    "prezzo": 22.520231
  },
  {
    "data": "2022-08-03",
    "prezzo": 22.73
  },
  {
    "data": "2022-08-04",
    "prezzo": 22.74
  },
  {
    "data": "2022-08-05",
    "prezzo": 24.53
  },
  {
    "data": "2022-08-06",
    "prezzo": 26.23
  },
  {
    "data": "2022-08-07",
    "prezzo": 85.88
  },
  {
    "data": "2022-08-08",
    "prezzo": 27.43
  },
  {
    "data": "2022-08-09",
    "prezzo": 26.84
  },
  {
    "data": "2022-08-10",
    "prezzo": 28.25
  },
  {
    "data": "2022-08-11",
    "prezzo": 27.73654
  },
  {
    "data": "2022-08-12",
    "prezzo": 28.62
  },
  {
    "data": "2022-08-13",
    "prezzo": 28.44
  },
  {
    "data": "2022-08-14",
    "prezzo": 27.5
  },
  {
    "data": "2022-08-15",
    "prezzo": 27.49
  },
  {
    "data": "2022-08-16",
    "prezzo": 26.68
  },
  {
    "data": "2022-08-17",
    "prezzo": 25.08
  },
  {
    "data": "2022-08-18",
    "prezzo": 23.973961
  },
  {
    "data": "2022-08-19",
    "prezzo": 21.99
  },
  {
    "data": "2022-08-20",
    "prezzo": 22.22
  },
  {
    "data": "2022-08-21",
    "prezzo": 22.9
  },
  {
    "data": "2022-08-22",
    "prezzo": 22.69
  },
  {
    "data": "2022-08-23",
    "prezzo": 23.59
  },
  {
    "data": "2022-08-24",
    "prezzo": 23.10585
  },
  {
    "data": "2022-08-25",
    "prezzo": 23.08
  },
  {
    "data": "2022-08-26",
    "prezzo": 20.65
  },
  {
    "data": "2022-08-27",
    "prezzo": 20.12
  },
  {
    "data": "2022-08-28",
    "prezzo": 18.579987
  },
  {
    "data": "2022-08-29",
    "prezzo": 19.32
  },
  {
    "data": "2022-08-30",
    "prezzo": 19.28663
  },
  {
    "data": "2022-08-31",
    "prezzo": 19.08
  },
  {
    "data": "2022-09-01",
    "prezzo": 19.39
  },
  {
    "data": "2022-09-02",
    "prezzo": 18.96
  },
  {
    "data": "2022-09-03",
    "prezzo": 18.95
  },
  {
    "data": "2022-09-04",
    "prezzo": 19.12
  },
  {
    "data": "2022-09-05",
    "prezzo": 19.51
  },
  {
    "data": "2022-09-06",
    "prezzo": 18.36
  },
  {
    "data": "2022-09-07",
    "prezzo": 18.95
  },
  {
    "data": "2022-09-08",
    "prezzo": 19.12
  },
  {
    "data": "2022-09-09",
    "prezzo": 20.19
  },
  {
    "data": "2022-09-10",
    "prezzo": 20.63
  },
  {
    "data": "2022-09-11",
    "prezzo": 20.53
  },
  {
    "data": "2022-09-12",
    "prezzo": 21.12
  },
  {
    "data": "2022-09-13",
    "prezzo": 18.97
  },
  {
    "data": "2022-09-14",
    "prezzo": 19.14
  },
  {
    "data": "2022-09-15",
    "prezzo": 18.2
  },
  {
    "data": "2022-09-16",
    "prezzo": 17.57
  },
  {
    "data": "2022-09-17",
    "prezzo": 18.47
  },
  {
    "data": "2022-09-18",
    "prezzo": 16.67326
  },
  {
    "data": "2022-09-19",
    "prezzo": 17.27
  },
  {
    "data": "2022-09-20",
    "prezzo": 16.71
  },
  {
    "data": "2022-09-21",
    "prezzo": 16.88
  },
  {
    "data": "2022-09-22",
    "prezzo": 17.99
  },
  {
    "data": "2022-09-23",
    "prezzo": 18.48
  },
  {
    "data": "2022-09-24",
    "prezzo": 18.14
  },
  {
    "data": "2022-09-25",
    "prezzo": 17.94
  },
  {
    "data": "2022-09-26",
    "prezzo": 17.37
  },
  {
    "data": "2022-09-27",
    "prezzo": 19.18
  },
  {
    "data": "2022-09-28",
    "prezzo": 17.72
  },
  {
    "data": "2022-09-29",
    "prezzo": 17.510006
  },
  {
    "data": "2022-09-30",
    "prezzo": 17.58
  },
  {
    "data": "2022-10-01",
    "prezzo": 17.31
  },
  {
    "data": "2022-10-02",
    "prezzo": 16.89
  },
  {
    "data": "2022-10-03",
    "prezzo": 17.43
  },
  {
    "data": "2022-10-04",
    "prezzo": 17.440015
  },
  {
    "data": "2022-10-05",
    "prezzo": 17.540005
  },
  {
    "data": "2022-10-06",
    "prezzo": 17.38
  },
  {
    "data": "2022-10-07",
    "prezzo": 17.379997
  },
  {
    "data": "2022-10-08",
    "prezzo": 17.190002
  },
  {
    "data": "2022-10-09",
    "prezzo": 17.34
  },
  {
    "data": "2022-10-10",
    "prezzo": 16.68
  },
  {
    "data": "2022-10-11",
    "prezzo": 16.42
  },
  {
    "data": "2022-10-12",
    "prezzo": 16.72
  },
  {
    "data": "2022-10-13",
    "prezzo": 16.05
  },
  {
    "data": "2022-10-14",
    "prezzo": 16.14
  },
  {
    "data": "2022-10-15",
    "prezzo": 15.89
  },
  {
    "data": "2022-10-16",
    "prezzo": 16.19
  },
  {
    "data": "2022-10-17",
    "prezzo": 16.410001
  },
  {
    "data": "2022-10-18",
    "prezzo": 16.11
  },
  {
    "data": "2022-10-19",
    "prezzo": 15.44
  },
  {
    "data": "2022-10-20",
    "prezzo": 15.51
  },
  {
    "data": "2022-10-21",
    "prezzo": 15.89
  },
  {
    "data": "2022-10-22",
    "prezzo": 15.91
  },
  {
    "data": "2022-10-23",
    "prezzo": 16.49
  },
  {
    "data": "2022-10-24",
    "prezzo": 15.96
  },
  {
    "data": "2022-10-25",
    "prezzo": 16.71
  },
  {
    "data": "2022-10-26",
    "prezzo": 16.83004
  },
  {
    "data": "2022-10-27",
    "prezzo": 16.96
  },
  {
    "data": "2022-10-28",
    "prezzo": 18.42
  },
  {
    "data": "2022-10-29",
    "prezzo": 18.32
  },
  {
    "data": "2022-10-30",
    "prezzo": 18.38
  },
  {
    "data": "2022-10-31",
    "prezzo": 19.52
  },
  {
    "data": "2022-11-01",
    "prezzo": 18.86
  },
  {
    "data": "2022-11-02",
    "prezzo": 18.23
  },
  {
    "data": "2022-11-03",
    "prezzo": 18.5
  },
  {
    "data": "2022-11-04",
    "prezzo": 19.43
  },
  {
    "data": "2022-11-05",
    "prezzo": 19.610002
  },
  {
    "data": "2022-11-06",
    "prezzo": 18.320023
  },
  {
    "data": "2022-11-07",
    "prezzo": 18.010001
  },
  {
    "data": "2022-11-08",
    "prezzo": 15.880041
  },
  {
    "data": "2022-11-09",
    "prezzo": 12.83
  },
  {
    "data": "2022-11-10",
    "prezzo": 15.149993
  },
  {
    "data": "2022-11-11",
    "prezzo": 13.609997
  },
  {
    "data": "2022-11-12",
    "prezzo": 12.609999
  },
  {
    "data": "2022-11-13",
    "prezzo": 12.53004
  },
  {
    "data": "2022-11-14",
    "prezzo": 12.699998
  },
  {
    "data": "2022-11-15",
    "prezzo": 13.01
  },
  {
    "data": "2022-11-16",
    "prezzo": 12.619995
  },
  {
    "data": "2022-11-17",
    "prezzo": 12.45
  },
  {
    "data": "2022-11-18",
    "prezzo": 12.59
  },
  {
    "data": "2022-11-19",
    "prezzo": 12.489997
  },
  {
    "data": "2022-11-20",
    "prezzo": 11.79
  },
  {
    "data": "2022-11-21",
    "prezzo": 11.52
  },
  {
    "data": "2022-11-22",
    "prezzo": 11.910016
  },
  {
    "data": "2022-11-23",
    "prezzo": 12.49
  },
  {
    "data": "2022-11-24",
    "prezzo": 12.41
  },
  {
    "data": "2022-11-25",
    "prezzo": 12.329994
  },
  {
    "data": "2022-11-26",
    "prezzo": 12.289997
  },
  {
    "data": "2022-11-27",
    "prezzo": 12.43
  },
  {
    "data": "2022-11-28",
    "prezzo": 12.02
  },
  {
    "data": "2022-11-29",
    "prezzo": 12.09
  },
  {
    "data": "2022-11-30",
    "prezzo": 12.62
  },
  {
    "data": "2022-12-01",
    "prezzo": 12.250006
  },
  {
    "data": "2022-12-02",
    "prezzo": 12.92
  },
  {
    "data": "2022-12-03",
    "prezzo": 12.76
  },
  {
    "data": "2022-12-04",
    "prezzo": 13.14
  },
  {
    "data": "2022-12-05",
    "prezzo": 12.94
  },
  {
    "data": "2022-12-06",
    "prezzo": 13.06
  },
  {
    "data": "2022-12-07",
    "prezzo": 12.57
  },
  {
    "data": "2022-12-08",
    "prezzo": 12.7
  },
  {
    "data": "2022-12-09",
    "prezzo": 12.73
  },
  {
    "data": "2022-12-10",
    "prezzo": 12.75
  },
  {
    "data": "2022-12-11",
    "prezzo": 12.339999
  },
  {
    "data": "2022-12-12",
    "prezzo": 12.3
  },
  {
    "data": "2022-12-13",
    "prezzo": 12.87
  },
  {
    "data": "2022-12-14",
    "prezzo": 12.82
  },
  {
    "data": "2022-12-15",
    "prezzo": 12.41
  },
  {
    "data": "2022-12-16",
    "prezzo": 11.170003
  },
  {
    "data": "2022-12-17",
    "prezzo": 11.26
  },
  {
    "data": "2022-12-18",
    "prezzo": 11.26
  },
  {
    "data": "2022-12-19",
    "prezzo": 10.72
  },
  {
    "data": "2022-12-20",
    "prezzo": 11.27
  },
  {
    "data": "2022-12-21",
    "prezzo": 11.0
  },
  {
    "data": "2022-12-22",
    "prezzo": 11.19
  },
  {
    "data": "2022-12-23",
    "prezzo": 11.1
  },
  {
    "data": "2022-12-24",
    "prezzo": 11.01
  },
  {
    "data": "2022-12-25",
    "prezzo": 10.950001
  },
  {
    "data": "2022-12-26",
    "prezzo": 11.01
  },
  {
    "data": "2022-12-27",
    "prezzo": 10.92
  },
  {
    "data": "2022-12-28",
    "prezzo": 10.49
  },
  {
    "data": "2022-12-29",
    "prezzo": 10.31
  },
  {
    "data": "2022-12-30",
    "prezzo": 10.16
  },
  {
    "data": "2022-12-31",
    "prezzo": 10.19
  },
  {
    "data": "2023-01-01",
    "prezzo": 10.11
  },
  {
    "data": "2023-01-02",
    "prezzo": 10.43
  },
  {
    "data": "2023-01-03",
    "prezzo": 10.78
  },
  {
    "data": "2023-01-04",
    "prezzo": 11.4
  },
  {
    "data": "2023-01-05",
    "prezzo": 11.14
  },
  {
    "data": "2023-01-06",
    "prezzo": 10.84
  },
  {
    "data": "2023-01-07",
    "prezzo": 11.129924
  },
  {
    "data": "2023-01-08",
    "prezzo": 11.3
  },
  {
    "data": "2023-01-09",
    "prezzo": 11.35
  },
  {
    "data": "2023-01-10",
    "prezzo": 11.84
  },
  {
    "data": "2023-01-11",
    "prezzo": 14.829983
  },
  {
    "data": "2023-01-12",
    "prezzo": 14.269998
  },
  {
    "data": "2023-01-13",
    "prezzo": 15.319889
  },
  {
    "data": "2023-01-14",
    "prezzo": 15.65
  },
  {
    "data": "2023-01-15",
    "prezzo": 15.500013
  },
  {
    "data": "2023-01-16",
    "prezzo": 15.42
  },
  {
    "data": "2023-01-17",
    "prezzo": 15.87
  },
  {
    "data": "2023-01-18",
    "prezzo": 14.609997
  },
  {
    "data": "2023-01-19",
    "prezzo": 14.96
  },
  {
    "data": "2023-01-20",
    "prezzo": 16.149993
  },
  {
    "data": "2023-01-21",
    "prezzo": 15.57
  },
  {
    "data": "2023-01-22",
    "prezzo": 15.99
  },
  {
    "data": "2023-01-23",
    "prezzo": 16.6
  },
  {
    "data": "2023-01-24",
    "prezzo": 15.63
  },
  {
    "data": "2023-01-25",
    "prezzo": 16.25
  },
  {
    "data": "2023-01-26",
    "prezzo": 16.62
  },
  {
    "data": "2023-01-27",
    "prezzo": 19.420023
  },
  {
    "data": "2023-01-28",
    "prezzo": 18.97
  },
  {
    "data": "2023-01-29",
    "prezzo": 19.359999
  },
  {
    "data": "2023-01-30",
    "prezzo": 18.22
  },
  {
    "data": "2023-01-31",
    "prezzo": 18.24
  },
  {
    "data": "2023-02-01",
    "prezzo": 19.12
  },
  {
    "data": "2023-02-02",
    "prezzo": 19.44
  },
  {
    "data": "2023-02-03",
    "prezzo": 19.76
  },
  {
    "data": "2023-02-04",
    "prezzo": 19.190013
  },
  {
    "data": "2023-02-05",
    "prezzo": 18.63
  },
  {
    "data": "2023-02-06",
    "prezzo": 18.26
  },
  {
    "data": "2023-02-07",
    "prezzo": 19.42
  },
  {
    "data": "2023-02-08",
    "prezzo": 18.82
  },
  {
    "data": "2023-02-09",
    "prezzo": 16.65
  },
  {
    "data": "2023-02-10",
    "prezzo": 16.67
  },
  {
    "data": "2023-02-11",
    "prezzo": 16.91
  },
  {
    "data": "2023-02-12",
    "prezzo": 16.64
  },
  {
    "data": "2023-02-13",
    "prezzo": 16.44
  },
  {
    "data": "2023-02-14",
    "prezzo": 16.93
  },
  {
    "data": "2023-02-15",
    "prezzo": 18.68
  },
  {
    "data": "2023-02-16",
    "prezzo": 17.45
  },
  {
    "data": "2023-02-17",
    "prezzo": 18.23
  },
  {
    "data": "2023-02-18",
    "prezzo": 18.29
  },
  {
    "data": "2023-02-19",
    "prezzo": 18.49
  },
  {
    "data": "2023-02-20",
    "prezzo": 19.42
  },
  {
    "data": "2023-02-21",
    "prezzo": 19.67
  },
  {
    "data": "2023-02-22",
    "prezzo": 19.1
  },
  {
    "data": "2023-02-23",
    "prezzo": 18.61428
  },
  {
    "data": "2023-02-24",
    "prezzo": 17.43
  },
  {
    "data": "2023-02-25",
    "prezzo": 17.040116
  },
  {
    "data": "2023-02-26",
    "prezzo": 17.45
  },
  {
    "data": "2023-02-27",
    "prezzo": 16.89
  },
  {
    "data": "2023-02-28",
    "prezzo": 16.15
  },
  {
    "data": "2023-03-01",
    "prezzo": 16.66
  },
  {
    "data": "2023-03-02",
    "prezzo": 16.45
  },
  {
    "data": "2023-03-03",
    "prezzo": 15.67
  },
  {
    "data": "2023-03-04",
    "prezzo": 15.17
  },
  {
    "data": "2023-03-05",
    "prezzo": 15.22
  },
  {
    "data": "2023-03-06",
    "prezzo": 15.54
  },
  {
    "data": "2023-03-07",
    "prezzo": 15.33
  },
  {
    "data": "2023-03-08",
    "prezzo": 14.35
  },
  {
    "data": "2023-03-09",
    "prezzo": 13.58
  },
  {
    "data": "2023-03-10",
    "prezzo": 13.93
  },
  {
    "data": "2023-03-11",
    "prezzo": 13.44
  },
  {
    "data": "2023-03-12",
    "prezzo": 14.992833
  },
  {
    "data": "2023-03-13",
    "prezzo": 15.15
  },
  {
    "data": "2023-03-14",
    "prezzo": 15.91
  },
  {
    "data": "2023-03-15",
    "prezzo": 14.65
  },
  {
    "data": "2023-03-16",
    "prezzo": 14.95
  },
  {
    "data": "2023-03-17",
    "prezzo": 16.4988
  },
  {
    "data": "2023-03-18",
    "prezzo": 15.92
  },
  {
    "data": "2023-03-19",
    "prezzo": 16.43364
  },
  {
    "data": "2023-03-20",
    "prezzo": 15.5
  },
  {
    "data": "2023-03-21",
    "prezzo": 16.23911
  },
  {
    "data": "2023-03-22",
    "prezzo": 15.43
  },
  {
    "data": "2023-03-23",
    "prezzo": 16.23
  },
  {
    "data": "2023-03-24",
    "prezzo": 15.82
  },
  {
    "data": "2023-03-25",
    "prezzo": 15.71
  },
  {
    "data": "2023-03-26",
    "prezzo": 15.87
  },
  {
    "data": "2023-03-27",
    "prezzo": 15.28
  },
  {
    "data": "2023-03-28",
    "prezzo": 15.42936
  },
  {
    "data": "2023-03-29",
    "prezzo": 15.93
  },
  {
    "data": "2023-03-30",
    "prezzo": 15.82
  },
  {
    "data": "2023-03-31",
    "prezzo": 16.34
  },
  {
    "data": "2023-04-01",
    "prezzo": 16.42
  },
  {
    "data": "2023-04-02",
    "prezzo": 15.96
  },
  {
    "data": "2023-04-03",
    "prezzo": 15.7
  },
  {
    "data": "2023-04-04",
    "prezzo": 16.11
  },
  {
    "data": "2023-04-05",
    "prezzo": 16.5
  },
  {
    "data": "2023-04-06",
    "prezzo": 16.52
  },
  {
    "data": "2023-04-07",
    "prezzo": 16.15
  },
  {
    "data": "2023-04-08",
    "prezzo": 16.04
  },
  {
    "data": "2023-04-09",
    "prezzo": 16.11
  },
  {
    "data": "2023-04-10",
    "prezzo": 16.48
  },
  {
    "data": "2023-04-11",
    "prezzo": 16.63
  },
  {
    "data": "2023-04-12",
    "prezzo": 16.61
  },
  {
    "data": "2023-04-13",
    "prezzo": 17.06
  },
  {
    "data": "2023-04-14",
    "prezzo": 17.51
  },
  {
    "data": "2023-04-15",
    "prezzo": 17.4
  },
  {
    "data": "2023-04-16",
    "prezzo": 18.39
  },
  {
    "data": "2023-04-17",
    "prezzo": 18.8
  },
  {
    "data": "2023-04-18",
    "prezzo": 19.34
  },
  {
    "data": "2023-04-19",
    "prezzo": 17.32
  },
  {
    "data": "2023-04-20",
    "prezzo": 16.79
  },
  {
    "data": "2023-04-21",
    "prezzo": 15.43
  },
  {
    "data": "2023-04-22",
    "prezzo": 15.73
  },
  {
    "data": "2023-04-23",
    "prezzo": 15.32354
  },
  {
    "data": "2023-04-24",
    "prezzo": 15.31
  },
  {
    "data": "2023-04-25",
    "prezzo": 16.1
  },
  {
    "data": "2023-04-26",
    "prezzo": 15.58
  },
  {
    "data": "2023-04-27",
    "prezzo": 16.08
  },
  {
    "data": "2023-04-28",
    "prezzo": 15.93
  },
  {
    "data": "2023-04-29",
    "prezzo": 15.85
  },
  {
    "data": "2023-04-30",
    "prezzo": 15.55
  },
  {
    "data": "2023-05-01",
    "prezzo": 15.19
  },
  {
    "data": "2023-05-02",
    "prezzo": 15.30782
  },
  {
    "data": "2023-05-03",
    "prezzo": 15.51947
  },
  {
    "data": "2023-05-04",
    "prezzo": 15.34652
  },
  {
    "data": "2023-05-05",
    "prezzo": 15.77821
  },
  {
    "data": "2023-05-06",
    "prezzo": 15.1
  },
  {
    "data": "2023-05-07",
    "prezzo": 14.85
  },
  {
    "data": "2023-05-08",
    "prezzo": 14.02
  },
  {
    "data": "2023-05-09",
    "prezzo": 14.0
  },
  {
    "data": "2023-05-10",
    "prezzo": 14.18
  },
  {
    "data": "2023-05-11",
    "prezzo": 13.73
  },
  {
    "data": "2023-05-12",
    "prezzo": 13.99
  },
  {
    "data": "2023-05-13",
    "prezzo": 13.78
  },
  {
    "data": "2023-05-14",
    "prezzo": 13.87
  },
  {
    "data": "2023-05-15",
    "prezzo": 13.86328
  },
  {
    "data": "2023-05-16",
    "prezzo": 13.72
  },
  {
    "data": "2023-05-17",
    "prezzo": 14.01
  },
  {
    "data": "2023-05-18",
    "prezzo": 13.66
  },
  {
    "data": "2023-05-19",
    "prezzo": 13.61
  },
  {
    "data": "2023-05-20",
    "prezzo": 13.53
  },
  {
    "data": "2023-05-21",
    "prezzo": 13.23
  },
  {
    "data": "2023-05-22",
    "prezzo": 13.57
  },
  {
    "data": "2023-05-23",
    "prezzo": 13.63
  },
  {
    "data": "2023-05-24",
    "prezzo": 13.1285
  },
  {
    "data": "2023-05-25",
    "prezzo": 13.15
  },
  {
    "data": "2023-05-26",
    "prezzo": 13.36541
  },
  {
    "data": "2023-05-27",
    "prezzo": 13.55
  },
  {
    "data": "2023-05-28",
    "prezzo": 13.91792
  },
  {
    "data": "2023-05-29",
    "prezzo": 13.52
  },
  {
    "data": "2023-05-30",
    "prezzo": 13.46129
  },
  {
    "data": "2023-05-31",
    "prezzo": 13.18817
  },
  {
    "data": "2023-06-01",
    "prezzo": 13.11
  },
  {
    "data": "2023-06-02",
    "prezzo": 13.51
  },
  {
    "data": "2023-06-03",
    "prezzo": 13.6
  },
  {
    "data": "2023-06-04",
    "prezzo": 13.81
  },
  {
    "data": "2023-06-05",
    "prezzo": 12.965
  },
  {
    "data": "2023-06-06",
    "prezzo": 13.67
  },
  {
    "data": "2023-06-07",
    "prezzo": 13.1
  },
  {
    "data": "2023-06-08",
    "prezzo": 12.91
  },
  {
    "data": "2023-06-09",
    "prezzo": 12.79
  },
  {
    "data": "2023-06-10",
    "prezzo": 10.9
  },
  {
    "data": "2023-06-11",
    "prezzo": 10.78
  },
  {
    "data": "2023-06-12",
    "prezzo": 10.7
  },
  {
    "data": "2023-06-13",
    "prezzo": 10.83
  },
  {
    "data": "2023-06-14",
    "prezzo": 10.47
  },
  {
    "data": "2023-06-15",
    "prezzo": 10.41
  },
  {
    "data": "2023-06-16",
    "prezzo": 10.55
  },
  {
    "data": "2023-06-17",
    "prezzo": 10.62
  },
  {
    "data": "2023-06-18",
    "prezzo": 10.35
  },
  {
    "data": "2023-06-19",
    "prezzo": 10.5
  },
  {
    "data": "2023-06-20",
    "prezzo": 11.08
  },
  {
    "data": "2023-06-21",
    "prezzo": 11.73
  },
  {
    "data": "2023-06-22",
    "prezzo": 11.54
  },
  {
    "data": "2023-06-23",
    "prezzo": 12.19
  },
  {
    "data": "2023-06-24",
    "prezzo": 11.88
  },
  {
    "data": "2023-06-25",
    "prezzo": 12.29
  },
  {
    "data": "2023-06-26",
    "prezzo": 12.03
  },
  {
    "data": "2023-06-27",
    "prezzo": 12.07
  },
  {
    "data": "2023-06-28",
    "prezzo": 11.31
  },
  {
    "data": "2023-06-29",
    "prezzo": 11.66
  },
  {
    "data": "2023-06-30",
    "prezzo": 11.9034
  },
  {
    "data": "2023-07-01",
    "prezzo": 11.9
  },
  {
    "data": "2023-07-02",
    "prezzo": 12.0
  },
  {
    "data": "2023-07-03",
    "prezzo": 12.06
  },
  {
    "data": "2023-07-04",
    "prezzo": 11.95
  },
  {
    "data": "2023-07-05",
    "prezzo": 11.69
  },
  {
    "data": "2023-07-06",
    "prezzo": 11.45
  },
  {
    "data": "2023-07-07",
    "prezzo": 11.63183
  },
  {
    "data": "2023-07-08",
    "prezzo": 12.44595
  },
  {
    "data": "2023-07-09",
    "prezzo": 12.42
  },
  {
    "data": "2023-07-10",
    "prezzo": 12.16
  },
  {
    "data": "2023-07-11",
    "prezzo": 12.01
  },
  {
    "data": "2023-07-12",
    "prezzo": 11.71
  },
  {
    "data": "2023-07-13",
    "prezzo": 12.56762
  },
  {
    "data": "2023-07-14",
    "prezzo": 12.98
  },
  {
    "data": "2023-07-15",
    "prezzo": 13.24
  },
  {
    "data": "2023-07-16",
    "prezzo": 12.73
  },
  {
    "data": "2023-07-17",
    "prezzo": 12.83
  },
  {
    "data": "2023-07-18",
    "prezzo": 12.25
  },
  {
    "data": "2023-07-19",
    "prezzo": 12.48
  },
  {
    "data": "2023-07-20",
    "prezzo": 12.45
  },
  {
    "data": "2023-07-21",
    "prezzo": 12.57
  },
  {
    "data": "2023-07-22",
    "prezzo": 12.14
  },
  {
    "data": "2023-07-23",
    "prezzo": 12.22
  },
  {
    "data": "2023-07-24",
    "prezzo": 11.85
  },
  {
    "data": "2023-07-25",
    "prezzo": 12.07
  },
  {
    "data": "2023-07-26",
    "prezzo": 11.97002
  },
  {
    "data": "2023-07-27",
    "prezzo": 11.95
  },
  {
    "data": "2023-07-28",
    "prezzo": 11.98
  },
  {
    "data": "2023-07-29",
    "prezzo": 12.0
  },
  {
    "data": "2023-07-30",
    "prezzo": 11.89
  },
  {
    "data": "2023-07-31",
    "prezzo": 11.63
  },
  {
    "data": "2023-08-01",
    "prezzo": 11.67
  },
  {
    "data": "2023-08-02",
    "prezzo": 11.41
  },
  {
    "data": "2023-08-03",
    "prezzo": 11.34
  },
  {
    "data": "2023-08-04",
    "prezzo": 11.260618
  },
  {
    "data": "2023-08-05",
    "prezzo": 11.29
  },
  {
    "data": "2023-08-06",
    "prezzo": 11.43
  },
  {
    "data": "2023-08-07",
    "prezzo": 11.31
  },
  {
    "data": "2023-08-08",
    "prezzo": 11.57
  },
  {
    "data": "2023-08-09",
    "prezzo": 11.49
  },
  {
    "data": "2023-08-10",
    "prezzo": 11.34
  },
  {
    "data": "2023-08-11",
    "prezzo": 11.36
  },
  {
    "data": "2023-08-12",
    "prezzo": 11.31
  },
  {
    "data": "2023-08-13",
    "prezzo": 11.2
  },
  {
    "data": "2023-08-14",
    "prezzo": 11.31
  },
  {
    "data": "2023-08-15",
    "prezzo": 10.82
  },
  {
    "data": "2023-08-16",
    "prezzo": 10.44
  },
  {
    "data": "2023-08-17",
    "prezzo": 9.73
  },
  {
    "data": "2023-08-18",
    "prezzo": 9.94
  },
  {
    "data": "2023-08-19",
    "prezzo": 9.97
  },
  {
    "data": "2023-08-20",
    "prezzo": 10.0
  },
  {
    "data": "2023-08-21",
    "prezzo": 9.504556
  },
  {
    "data": "2023-08-22",
    "prezzo": 9.33
  },
  {
    "data": "2023-08-23",
    "prezzo": 9.52
  },
  {
    "data": "2023-08-24",
    "prezzo": 9.37
  },
  {
    "data": "2023-08-25",
    "prezzo": 9.31
  },
  {
    "data": "2023-08-26",
    "prezzo": 9.359
  },
  {
    "data": "2023-08-27",
    "prezzo": 9.44
  },
  {
    "data": "2023-08-28",
    "prezzo": 9.57
  },
  {
    "data": "2023-08-29",
    "prezzo": 9.92642
  },
  {
    "data": "2023-08-30",
    "prezzo": 9.52
  },
  {
    "data": "2023-08-31",
    "prezzo": 9.2
  },
  {
    "data": "2023-09-01",
    "prezzo": 9.21
  },
  {
    "data": "2023-09-02",
    "prezzo": 9.21
  },
  {
    "data": "2023-09-03",
    "prezzo": 9.15
  },
  {
    "data": "2023-09-04",
    "prezzo": 9.06
  },
  {
    "data": "2023-09-05",
    "prezzo": 9.24
  },
  {
    "data": "2023-09-06",
    "prezzo": 9.27
  },
  {
    "data": "2023-09-07",
    "prezzo": 9.4
  },
  {
    "data": "2023-09-08",
    "prezzo": 9.28
  },
  {
    "data": "2023-09-09",
    "prezzo": 9.2
  },
  {
    "data": "2023-09-10",
    "prezzo": 8.85
  },
  {
    "data": "2023-09-11",
    "prezzo": 8.58
  },
  {
    "data": "2023-09-12",
    "prezzo": 8.56
  },
  {
    "data": "2023-09-13",
    "prezzo": 8.67
  },
  {
    "data": "2023-09-14",
    "prezzo": 8.84
  },
  {
    "data": "2023-09-15",
    "prezzo": 8.82
  },
  {
    "data": "2023-09-16",
    "prezzo": 8.79599
  },
  {
    "data": "2023-09-17",
    "prezzo": 8.53
  },
  {
    "data": "2023-09-18",
    "prezzo": 8.5
  },
  {
    "data": "2023-09-19",
    "prezzo": 8.64
  },
  {
    "data": "2023-09-20",
    "prezzo": 8.49125
  },
  {
    "data": "2023-09-21",
    "prezzo": 8.28
  },
  {
    "data": "2023-09-22",
    "prezzo": 8.32
  },
  {
    "data": "2023-09-23",
    "prezzo": 8.36
  },
  {
    "data": "2023-09-24",
    "prezzo": 8.251438
  },
  {
    "data": "2023-09-25",
    "prezzo": 8.44
  },
  {
    "data": "2023-09-26",
    "prezzo": 8.52
  },
  {
    "data": "2023-09-27",
    "prezzo": 8.48
  },
  {
    "data": "2023-09-28",
    "prezzo": 8.78
  },
  {
    "data": "2023-09-29",
    "prezzo": 8.68061
  },
  {
    "data": "2023-09-30",
    "prezzo": 8.76
  },
  {
    "data": "2023-10-01",
    "prezzo": 9.23
  },
  {
    "data": "2023-10-02",
    "prezzo": 8.9
  },
  {
    "data": "2023-10-03",
    "prezzo": 8.97
  },
  {
    "data": "2023-10-04",
    "prezzo": 9.6
  },
  {
    "data": "2023-10-05",
    "prezzo": 9.63
  },
  {
    "data": "2023-10-06",
    "prezzo": 10.07
  },
  {
    "data": "2023-10-07",
    "prezzo": 9.76
  },
  {
    "data": "2023-10-08",
    "prezzo": 9.55
  },
  {
    "data": "2023-10-09",
    "prezzo": 9.02
  },
  {
    "data": "2023-10-10",
    "prezzo": 8.98
  },
  {
    "data": "2023-10-11",
    "prezzo": 8.75
  },
  {
    "data": "2023-10-12",
    "prezzo": 8.67
  },
  {
    "data": "2023-10-13",
    "prezzo": 8.71
  },
  {
    "data": "2023-10-14",
    "prezzo": 8.72231
  },
  {
    "data": "2023-10-15",
    "prezzo": 8.72
  },
  {
    "data": "2023-10-16",
    "prezzo": 8.93
  },
  {
    "data": "2023-10-17",
    "prezzo": 8.62619
  },
  {
    "data": "2023-10-18",
    "prezzo": 8.45
  },
  {
    "data": "2023-10-19",
    "prezzo": 8.56
  },
  {
    "data": "2023-10-20",
    "prezzo": 8.7133
  },
  {
    "data": "2023-10-21",
    "prezzo": 9.09167
  },
  {
    "data": "2023-10-22",
    "prezzo": 9.49564
  },
  {
    "data": "2023-10-23",
    "prezzo": 9.93
  },
  {
    "data": "2023-10-24",
    "prezzo": 9.75184
  },
  {
    "data": "2023-10-25",
    "prezzo": 9.98
  },
  {
    "data": "2023-10-26",
    "prezzo": 10.48
  },
  {
    "data": "2023-10-27",
    "prezzo": 10.05
  },
  {
    "data": "2023-10-28",
    "prezzo": 10.38221
  },
  {
    "data": "2023-10-29",
    "prezzo": 10.75
  },
  {
    "data": "2023-10-30",
    "prezzo": 10.8
  },
  {
    "data": "2023-10-31",
    "prezzo": 10.72
  },
  {
    "data": "2023-11-01",
    "prezzo": 11.55
  },
  {
    "data": "2023-11-02",
    "prezzo": 11.2
  },
  {
    "data": "2023-11-03",
    "prezzo": 11.29
  },
  {
    "data": "2023-11-04",
    "prezzo": 11.41
  },
  {
    "data": "2023-11-05",
    "prezzo": 11.54
  },
  {
    "data": "2023-11-06",
    "prezzo": 12.21
  },
  {
    "data": "2023-11-07",
    "prezzo": 11.98
  },
  {
    "data": "2023-11-08",
    "prezzo": 12.14
  },
  {
    "data": "2023-11-09",
    "prezzo": 12.18
  },
  {
    "data": "2023-11-10",
    "prezzo": 13.80112
  },
  {
    "data": "2023-11-11",
    "prezzo": 15.79
  },
  {
    "data": "2023-11-12",
    "prezzo": 17.741344
  },
  {
    "data": "2023-11-13",
    "prezzo": 15.12
  },
  {
    "data": "2023-11-14",
    "prezzo": 15.68
  },
  {
    "data": "2023-11-15",
    "prezzo": 19.1
  },
  {
    "data": "2023-11-16",
    "prezzo": 20.030786
  },
  {
    "data": "2023-11-17",
    "prezzo": 20.10046
  },
  {
    "data": "2023-11-18",
    "prezzo": 20.19
  },
  {
    "data": "2023-11-19",
    "prezzo": 20.95
  },
  {
    "data": "2023-11-20",
    "prezzo": 19.07
  },
  {
    "data": "2023-11-21",
    "prezzo": 17.42
  },
  {
    "data": "2023-11-22",
    "prezzo": 19.09
  },
  {
    "data": "2023-11-23",
    "prezzo": 18.95749
  },
  {
    "data": "2023-11-24",
    "prezzo": 19.1
  },
  {
    "data": "2023-11-25",
    "prezzo": 19.51
  },
  {
    "data": "2023-11-26",
    "prezzo": 19.27
  },
  {
    "data": "2023-11-27",
    "prezzo": 18.61
  },
  {
    "data": "2023-11-28",
    "prezzo": 18.76
  },
  {
    "data": "2023-11-29",
    "prezzo": 19.26
  },
  {
    "data": "2023-11-30",
    "prezzo": 19.65
  },
  {
    "data": "2023-12-01",
    "prezzo": 20.00455
  },
  {
    "data": "2023-12-02",
    "prezzo": 20.42
  },
  {
    "data": "2023-12-03",
    "prezzo": 20.16
  },
  {
    "data": "2023-12-04",
    "prezzo": 20.94
  },
  {
    "data": "2023-12-05",
    "prezzo": 22.7
  },
  {
    "data": "2023-12-06",
    "prezzo": 24.37
  },
  {
    "data": "2023-12-07",
    "prezzo": 24.35
  },
  {
    "data": "2023-12-08",
    "prezzo": 28.352451
  },
  {
    "data": "2023-12-09",
    "prezzo": 29.628043
  },
  {
    "data": "2023-12-10",
    "prezzo": 34.539071
  },
  {
    "data": "2023-12-11",
    "prezzo": 35.381825
  },
  {
    "data": "2023-12-12",
    "prezzo": 34.62
  },
  {
    "data": "2023-12-13",
    "prezzo": 35.84
  },
  {
    "data": "2023-12-14",
    "prezzo": 35.79
  },
  {
    "data": "2023-12-15",
    "prezzo": 36.412939
  },
  {
    "data": "2023-12-16",
    "prezzo": 38.80362
  },
  {
    "data": "2023-12-17",
    "prezzo": 37.26
  },
  {
    "data": "2023-12-18",
    "prezzo": 37.62031
  },
  {
    "data": "2023-12-19",
    "prezzo": 36.242522
  },
  {
    "data": "2023-12-20",
    "prezzo": 39.69
  },
  {
    "data": "2023-12-21",
    "prezzo": 41.770428
  },
  {
    "data": "2023-12-22",
    "prezzo": 41.274577
  },
  {
    "data": "2023-12-23",
    "prezzo": 43.748599
  },
  {
    "data": "2023-12-24",
    "prezzo": 43.45
  },
  {
    "data": "2023-12-25",
    "prezzo": 43.831028
  },
  {
    "data": "2023-12-26",
    "prezzo": 40.27
  },
  {
    "data": "2023-12-27",
    "prezzo": 38.15
  },
  {
    "data": "2023-12-28",
    "prezzo": 36.0
  },
  {
    "data": "2023-12-29",
    "prezzo": 36.478417
  },
  {
    "data": "2023-12-30",
    "prezzo": 35.74
  },
  {
    "data": "2023-12-31",
    "prezzo": 35.06
  },
  {
    "data": "2024-01-01",
    "prezzo": 37.99
  },
  {
    "data": "2024-01-02",
    "prezzo": 37.13
  },
  {
    "data": "2024-01-03",
    "prezzo": 33.780522
  },
  {
    "data": "2024-01-04",
    "prezzo": 35.43
  },
  {
    "data": "2024-01-05",
    "prezzo": 33.34
  },
  {
    "data": "2024-01-06",
    "prezzo": 31.706765
  },
  {
    "data": "2024-01-07",
    "prezzo": 30.77
  },
  {
    "data": "2024-01-08",
    "prezzo": 32.980913
  },
  {
    "data": "2024-01-09",
    "prezzo": 31.77
  },
  {
    "data": "2024-01-10",
    "prezzo": 35.12
  },
  {
    "data": "2024-01-11",
    "prezzo": 35.83
  },
  {
    "data": "2024-01-12",
    "prezzo": 32.88
  },
  {
    "data": "2024-01-13",
    "prezzo": 33.36
  },
  {
    "data": "2024-01-14",
    "prezzo": 32.3
  },
  {
    "data": "2024-01-15",
    "prezzo": 32.59
  },
  {
    "data": "2024-01-16",
    "prezzo": 32.73
  },
  {
    "data": "2024-01-17",
    "prezzo": 33.06
  },
  {
    "data": "2024-01-18",
    "prezzo": 30.85
  },
  {
    "data": "2024-01-19",
    "prezzo": 29.99
  },
  {
    "data": "2024-01-20",
    "prezzo": 30.09
  },
  {
    "data": "2024-01-21",
    "prezzo": 29.87
  },
  {
    "data": "2024-01-22",
    "prezzo": 27.09
  },
  {
    "data": "2024-01-23",
    "prezzo": 28.208764
  },
  {
    "data": "2024-01-24",
    "prezzo": 28.66
  },
  {
    "data": "2024-01-25",
    "prezzo": 28.11
  },
  {
    "data": "2024-01-26",
    "prezzo": 29.75
  },
  {
    "data": "2024-01-27",
    "prezzo": 30.62513
  },
  {
    "data": "2024-01-28",
    "prezzo": 32.132951
  },
  {
    "data": "2024-01-29",
    "prezzo": 33.3
  },
  {
    "data": "2024-01-30",
    "prezzo": 32.417741
  },
  {
    "data": "2024-01-31",
    "prezzo": 30.692514
  },
  {
    "data": "2024-02-01",
    "prezzo": 31.1
  },
  {
    "data": "2024-02-02",
    "prezzo": 34.04
  },
  {
    "data": "2024-02-03",
    "prezzo": 33.29119
  },
  {
    "data": "2024-02-04",
    "prezzo": 32.29
  },
  {
    "data": "2024-02-05",
    "prezzo": 32.15
  },
  {
    "data": "2024-02-06",
    "prezzo": 31.74488
  },
  {
    "data": "2024-02-07",
    "prezzo": 32.74
  },
  {
    "data": "2024-02-08",
    "prezzo": 32.87
  },
  {
    "data": "2024-02-09",
    "prezzo": 35.19
  },
  {
    "data": "2024-02-10",
    "prezzo": 37.1773
  },
  {
    "data": "2024-02-11",
    "prezzo": 36.73916
  },
  {
    "data": "2024-02-12",
    "prezzo": 38.03
  },
  {
    "data": "2024-02-13",
    "prezzo": 37.11
  },
  {
    "data": "2024-02-14",
    "prezzo": 39.380074
  },
  {
    "data": "2024-02-15",
    "prezzo": 38.59
  },
  {
    "data": "2024-02-16",
    "prezzo": 37.36
  },
  {
    "data": "2024-02-17",
    "prezzo": 36.92
  },
  {
    "data": "2024-02-18",
    "prezzo": 37.34
  },
  {
    "data": "2024-02-19",
    "prezzo": 36.65
  },
  {
    "data": "2024-02-20",
    "prezzo": 35.66
  },
  {
    "data": "2024-02-21",
    "prezzo": 34.81
  },
  {
    "data": "2024-02-22",
    "prezzo": 33.96
  },
  {
    "data": "2024-02-23",
    "prezzo": 33.19
  },
  {
    "data": "2024-02-24",
    "prezzo": 33.91
  },
  {
    "data": "2024-02-25",
    "prezzo": 34.63
  },
  {
    "data": "2024-02-26",
    "prezzo": 36.16386
  },
  {
    "data": "2024-02-27",
    "prezzo": 36.21
  },
  {
    "data": "2024-02-28",
    "prezzo": 37.11218
  },
  {
    "data": "2024-02-29",
    "prezzo": 37.86
  },
  {
    "data": "2024-03-01",
    "prezzo": 39.460584
  },
  {
    "data": "2024-03-02",
    "prezzo": 40.968957
  },
  {
    "data": "2024-03-03",
    "prezzo": 39.29
  },
  {
    "data": "2024-03-04",
    "prezzo": 39.66
  },
  {
    "data": "2024-03-05",
    "prezzo": 36.406698
  },
  {
    "data": "2024-03-06",
    "prezzo": 38.1
  },
  {
    "data": "2024-03-07",
    "prezzo": 39.524768
  },
  {
    "data": "2024-03-08",
    "prezzo": 39.04
  },
  {
    "data": "2024-03-09",
    "prezzo": 39.3
  },
  {
    "data": "2024-03-10",
    "prezzo": 38.46
  },
  {
    "data": "2024-03-11",
    "prezzo": 44.739706
  },
  {
    "data": "2024-03-12",
    "prezzo": 50.89
  },
  {
    "data": "2024-03-13",
    "prezzo": 50.084509
  },
  {
    "data": "2024-03-14",
    "prezzo": 49.67
  },
  {
    "data": "2024-03-15",
    "prezzo": 53.597709
  },
  {
    "data": "2024-03-16",
    "prezzo": 49.1
  },
  {
    "data": "2024-03-17",
    "prezzo": 53.565281
  },
  {
    "data": "2024-03-18",
    "prezzo": 55.873465
  },
  {
    "data": "2024-03-19",
    "prezzo": 49.354481
  },
  {
    "data": "2024-03-20",
    "prezzo": 52.29333
  },
  {
    "data": "2024-03-21",
    "prezzo": 49.54
  },
  {
    "data": "2024-03-22",
    "prezzo": 49.49
  },
  {
    "data": "2024-03-23",
    "prezzo": 49.44
  },
  {
    "data": "2024-03-24",
    "prezzo": 51.53
  },
  {
    "data": "2024-03-25",
    "prezzo": 53.33772
  },
  {
    "data": "2024-03-26",
    "prezzo": 51.5
  },
  {
    "data": "2024-03-27",
    "prezzo": 50.02
  },
  {
    "data": "2024-03-28",
    "prezzo": 50.6
  },
  {
    "data": "2024-03-29",
    "prezzo": 49.49
  },
  {
    "data": "2024-03-30",
    "prezzo": 49.13
  },
  {
    "data": "2024-03-31",
    "prezzo": 50.15
  },
  {
    "data": "2024-04-01",
    "prezzo": 47.85
  },
  {
    "data": "2024-04-02",
    "prezzo": 43.60103
  },
  {
    "data": "2024-04-03",
    "prezzo": 42.39
  },
  {
    "data": "2024-04-04",
    "prezzo": 42.97004
  },
  {
    "data": "2024-04-05",
    "prezzo": 41.85
  },
  {
    "data": "2024-04-06",
    "prezzo": 44.48
  },
  {
    "data": "2024-04-07",
    "prezzo": 45.64
  },
  {
    "data": "2024-04-08",
    "prezzo": 45.98
  },
  {
    "data": "2024-04-09",
    "prezzo": 42.8
  },
  {
    "data": "2024-04-10",
    "prezzo": 44.0
  },
  {
    "data": "2024-04-11",
    "prezzo": 42.9
  },
  {
    "data": "2024-04-12",
    "prezzo": 37.178024
  },
  {
    "data": "2024-04-13",
    "prezzo": 32.342365
  },
  {
    "data": "2024-04-14",
    "prezzo": 35.053866
  },
  {
    "data": "2024-04-15",
    "prezzo": 33.1
  },
  {
    "data": "2024-04-16",
    "prezzo": 32.74674
  },
  {
    "data": "2024-04-17",
    "prezzo": 31.53
  },
  {
    "data": "2024-04-18",
    "prezzo": 32.78
  },
  {
    "data": "2024-04-19",
    "prezzo": 32.63
  },
  {
    "data": "2024-04-20",
    "prezzo": 36.0
  },
  {
    "data": "2024-04-21",
    "prezzo": 34.89
  },
  {
    "data": "2024-04-22",
    "prezzo": 36.82
  },
  {
    "data": "2024-04-23",
    "prezzo": 35.74
  },
  {
    "data": "2024-04-24",
    "prezzo": 33.87
  },
  {
    "data": "2024-04-25",
    "prezzo": 33.19
  },
  {
    "data": "2024-04-26",
    "prezzo": 32.2
  },
  {
    "data": "2024-04-27",
    "prezzo": 32.25
  },
  {
    "data": "2024-04-28",
    "prezzo": 31.7293
  },
  {
    "data": "2024-04-29",
    "prezzo": 32.89
  },
  {
    "data": "2024-04-30",
    "prezzo": 30.66
  },
  {
    "data": "2024-05-01",
    "prezzo": 31.05
  },
  {
    "data": "2024-05-02",
    "prezzo": 31.33
  },
  {
    "data": "2024-05-03",
    "prezzo": 33.04
  },
  {
    "data": "2024-05-04",
    "prezzo": 34.72794
  },
  {
    "data": "2024-05-05",
    "prezzo": 34.72
  },
  {
    "data": "2024-05-06",
    "prezzo": 34.49
  },
  {
    "data": "2024-05-07",
    "prezzo": 32.87
  },
  {
    "data": "2024-05-08",
    "prezzo": 31.75
  },
  {
    "data": "2024-05-09",
    "prezzo": 32.51742
  },
  {
    "data": "2024-05-10",
    "prezzo": 31.37
  },
  {
    "data": "2024-05-11",
    "prezzo": 31.11
  },
  {
    "data": "2024-05-12",
    "prezzo": 30.77
  },
  {
    "data": "2024-05-13",
    "prezzo": 30.06
  },
  {
    "data": "2024-05-14",
    "prezzo": 29.2
  },
  {
    "data": "2024-05-15",
    "prezzo": 31.82
  },
  {
    "data": "2024-05-16",
    "prezzo": 31.8
  },
  {
    "data": "2024-05-17",
    "prezzo": 33.502259
  },
  {
    "data": "2024-05-18",
    "prezzo": 34.29
  },
  {
    "data": "2024-05-19",
    "prezzo": 32.76
  },
  {
    "data": "2024-05-20",
    "prezzo": 36.87523
  },
  {
    "data": "2024-05-21",
    "prezzo": 37.85
  },
  {
    "data": "2024-05-22",
    "prezzo": 36.88
  },
  {
    "data": "2024-05-23",
    "prezzo": 35.59354
  },
  {
    "data": "2024-05-24",
    "prezzo": 34.96
  },
  {
    "data": "2024-05-25",
    "prezzo": 35.31
  },
  {
    "data": "2024-05-26",
    "prezzo": 33.91505
  },
  {
    "data": "2024-05-27",
    "prezzo": 35.18
  },
  {
    "data": "2024-05-28",
    "prezzo": 34.11
  },
  {
    "data": "2024-05-29",
    "prezzo": 33.49
  },
  {
    "data": "2024-05-30",
    "prezzo": 33.26
  },
  {
    "data": "2024-05-31",
    "prezzo": 33.3234
  },
  {
    "data": "2024-06-01",
    "prezzo": 32.95369
  },
  {
    "data": "2024-06-02",
    "prezzo": 32.17
  },
  {
    "data": "2024-06-03",
    "prezzo": 32.09
  },
  {
    "data": "2024-06-04",
    "prezzo": 33.11
  },
  {
    "data": "2024-06-05",
    "prezzo": 33.61
  },
  {
    "data": "2024-06-06",
    "prezzo": 33.0
  },
  {
    "data": "2024-06-07",
    "prezzo": 31.05
  },
  {
    "data": "2024-06-08",
    "prezzo": 29.95
  },
  {
    "data": "2024-06-09",
    "prezzo": 30.62
  },
  {
    "data": "2024-06-10",
    "prezzo": 29.99
  },
  {
    "data": "2024-06-11",
    "prezzo": 29.35063
  },
  {
    "data": "2024-06-12",
    "prezzo": 30.75058
  },
  {
    "data": "2024-06-13",
    "prezzo": 28.89
  },
  {
    "data": "2024-06-14",
    "prezzo": 28.3616
  },
  {
    "data": "2024-06-15",
    "prezzo": 28.0
  },
  {
    "data": "2024-06-16",
    "prezzo": 27.99185
  },
  {
    "data": "2024-06-17",
    "prezzo": 26.51607
  },
  {
    "data": "2024-06-18",
    "prezzo": 24.75
  },
  {
    "data": "2024-06-19",
    "prezzo": 24.96
  },
  {
    "data": "2024-06-20",
    "prezzo": 25.71
  },
  {
    "data": "2024-06-21",
    "prezzo": 25.67
  },
  {
    "data": "2024-06-22",
    "prezzo": 23.93
  },
  {
    "data": "2024-06-23",
    "prezzo": 23.49719
  },
  {
    "data": "2024-06-24",
    "prezzo": 23.237848
  },
  {
    "data": "2024-06-25",
    "prezzo": 23.71
  },
  {
    "data": "2024-06-26",
    "prezzo": 24.17
  },
  {
    "data": "2024-06-27",
    "prezzo": 26.07
  },
  {
    "data": "2024-06-28",
    "prezzo": 26.07
  },
  {
    "data": "2024-06-29",
    "prezzo": 25.91252
  },
  {
    "data": "2024-06-30",
    "prezzo": 27.34955
  },
  {
    "data": "2024-07-01",
    "prezzo": 26.83567
  },
  {
    "data": "2024-07-02",
    "prezzo": 26.64
  },
  {
    "data": "2024-07-03",
    "prezzo": 24.54853
  },
  {
    "data": "2024-07-04",
    "prezzo": 22.606993
  },
  {
    "data": "2024-07-05",
    "prezzo": 23.16
  },
  {
    "data": "2024-07-06",
    "prezzo": 25.24
  },
  {
    "data": "2024-07-07",
    "prezzo": 23.71
  },
  {
    "data": "2024-07-08",
    "prezzo": 23.27
  },
  {
    "data": "2024-07-09",
    "prezzo": 24.44
  },
  {
    "data": "2024-07-10",
    "prezzo": 23.72
  },
  {
    "data": "2024-07-11",
    "prezzo": 23.18726
  },
  {
    "data": "2024-07-12",
    "prezzo": 23.79753
  },
  {
    "data": "2024-07-13",
    "prezzo": 23.71
  },
  {
    "data": "2024-07-14",
    "prezzo": 24.19
  },
  {
    "data": "2024-07-15",
    "prezzo": 25.555619
  },
  {
    "data": "2024-07-16",
    "prezzo": 25.71
  },
  {
    "data": "2024-07-17",
    "prezzo": 24.91
  },
  {
    "data": "2024-07-18",
    "prezzo": 24.98
  },
  {
    "data": "2024-07-19",
    "prezzo": 25.9
  },
  {
    "data": "2024-07-20",
    "prezzo": 26.77
  },
  {
    "data": "2024-07-21",
    "prezzo": 29.86
  },
  {
    "data": "2024-07-22",
    "prezzo": 29.28
  },
  {
    "data": "2024-07-23",
    "prezzo": 27.45
  },
  {
    "data": "2024-07-24",
    "prezzo": 26.17
  },
  {
    "data": "2024-07-25",
    "prezzo": 25.1
  },
  {
    "data": "2024-07-26",
    "prezzo": 26.43
  },
  {
    "data": "2024-07-27",
    "prezzo": 25.82
  },
  {
    "data": "2024-07-28",
    "prezzo": 25.2
  },
  {
    "data": "2024-07-29",
    "prezzo": 24.941132
  },
  {
    "data": "2024-07-30",
    "prezzo": 24.334019
  },
  {
    "data": "2024-07-31",
    "prezzo": 23.751631
  },
  {
    "data": "2024-08-01",
    "prezzo": 23.816301
  },
  {
    "data": "2024-08-02",
    "prezzo": 21.632259
  },
  {
    "data": "2024-08-03",
    "prezzo": 20.808911
  },
  {
    "data": "2024-08-04",
    "prezzo": 19.478458
  },
  {
    "data": "2024-08-05",
    "prezzo": 17.864964
  },
  {
    "data": "2024-08-06",
    "prezzo": 19.155624
  },
  {
    "data": "2024-08-07",
    "prezzo": 18.184288
  },
  {
    "data": "2024-08-08",
    "prezzo": 20.848669
  },
  {
    "data": "2024-08-09",
    "prezzo": 19.935085
  },
  {
    "data": "2024-08-10",
    "prezzo": 19.791064
  },
  {
    "data": "2024-08-11",
    "prezzo": 18.706429
  },
  {
    "data": "2024-08-12",
    "prezzo": 19.460958
  },
  {
    "data": "2024-08-13",
    "prezzo": 19.45556
  },
  {
    "data": "2024-08-14",
    "prezzo": 19.034953
  },
  {
    "data": "2024-08-15",
    "prezzo": 18.365485
  },
  {
    "data": "2024-08-16",
    "prezzo": 18.49844
  },
  {
    "data": "2024-08-17",
    "prezzo": 18.7932
  },
  {
    "data": "2024-08-18",
    "prezzo": 18.894921
  },
  {
    "data": "2024-08-19",
    "prezzo": 19.147945
  },
  {
    "data": "2024-08-20",
    "prezzo": 20.014372
  },
  {
    "data": "2024-08-21",
    "prezzo": 21.097029
  },
  {
    "data": "2024-08-22",
    "prezzo": 22.701757
  },
  {
    "data": "2024-08-23",
    "prezzo": 23.715453
  },
  {
    "data": "2024-08-24",
    "prezzo": 24.210475
  },
  {
    "data": "2024-08-25",
    "prezzo": 24.07324
  },
  {
    "data": "2024-08-26",
    "prezzo": 23.238799
  },
  {
    "data": "2024-08-27",
    "prezzo": 21.58049
  },
  {
    "data": "2024-08-28",
    "prezzo": 21.082802
  },
  {
    "data": "2024-08-29",
    "prezzo": 20.676058
  },
  {
    "data": "2024-08-30",
    "prezzo": 21.094869
  },
  {
    "data": "2024-08-31",
    "prezzo": 20.643015
  },
  {
    "data": "2024-09-01",
    "prezzo": 19.406015
  },
  {
    "data": "2024-09-02",
    "prezzo": 20.21262
  },
  {
    "data": "2024-09-03",
    "prezzo": 19.358087
  },
  {
    "data": "2024-09-04",
    "prezzo": 19.771079
  },
  {
    "data": "2024-09-05",
    "prezzo": 19.227553
  },
  {
    "data": "2024-09-06",
    "prezzo": 19.116422
  },
  {
    "data": "2024-09-07",
    "prezzo": 19.678375
  },
  {
    "data": "2024-09-08",
    "prezzo": 20.979635
  },
  {
    "data": "2024-09-09",
    "prezzo": 21.61963
  },
  {
    "data": "2024-09-10",
    "prezzo": 22.09836
  },
  {
    "data": "2024-09-11",
    "prezzo": 21.145283
  },
  {
    "data": "2024-09-12",
    "prezzo": 21.688731
  },
  {
    "data": "2024-09-13",
    "prezzo": 22.499706
  },
  {
    "data": "2024-09-14",
    "prezzo": 22.860229
  },
  {
    "data": "2024-09-15",
    "prezzo": 21.464794
  },
  {
    "data": "2024-09-16",
    "prezzo": 21.124866
  },
  {
    "data": "2024-09-17",
    "prezzo": 21.379777
  },
  {
    "data": "2024-09-18",
    "prezzo": 22.227822
  },
  {
    "data": "2024-09-19",
    "prezzo": 23.902921
  },
  {
    "data": "2024-09-20",
    "prezzo": 24.788325
  },
  {
    "data": "2024-09-21",
    "prezzo": 24.894924
  },
  {
    "data": "2024-09-22",
    "prezzo": 24.45763
  },
  {
    "data": "2024-09-23",
    "prezzo": 24.643341
  },
  {
    "data": "2024-09-24",
    "prezzo": 25.42836
  },
  {
    "data": "2024-09-25",
    "prezzo": 24.508932
  },
  {
    "data": "2024-09-26",
    "prezzo": 26.095086
  },
  {
    "data": "2024-09-27",
    "prezzo": 27.271778
  },
  {
    "data": "2024-09-28",
    "prezzo": 26.235036
  },
  {
    "data": "2024-09-29",
    "prezzo": 26.004596
  },
  {
    "data": "2024-09-30",
    "prezzo": 24.882112
  },
  {
    "data": "2024-10-01",
    "prezzo": 23.324202
  },
  {
    "data": "2024-10-02",
    "prezzo": 22.934944
  },
  {
    "data": "2024-10-03",
    "prezzo": 22.349812
  },
  {
    "data": "2024-10-04",
    "prezzo": 23.924982
  },
  {
    "data": "2024-10-05",
    "prezzo": 23.364961
  },
  {
    "data": "2024-10-06",
    "prezzo": 24.54214
  },
  {
    "data": "2024-10-07",
    "prezzo": 24.209212
  },
  {
    "data": "2024-10-08",
    "prezzo": 23.995271
  },
  {
    "data": "2024-10-09",
    "prezzo": 23.541958
  },
  {
    "data": "2024-10-10",
    "prezzo": 23.640325
  },
  {
    "data": "2024-10-11",
    "prezzo": 25.081317
  },
  {
    "data": "2024-10-12",
    "prezzo": 26.145178
  },
  {
    "data": "2024-10-13",
    "prezzo": 26.574823
  },
  {
    "data": "2024-10-14",
    "prezzo": 26.584647
  },
  {
    "data": "2024-10-15",
    "prezzo": 25.894449
  },
  {
    "data": "2024-10-16",
    "prezzo": 25.796909
  },
  {
    "data": "2024-10-17",
    "prezzo": 25.184324
  },
  {
    "data": "2024-10-18",
    "prezzo": 25.856948
  },
  {
    "data": "2024-10-19",
    "prezzo": 25.824992
  },
  {
    "data": "2024-10-20",
    "prezzo": 26.629831
  },
  {
    "data": "2024-10-21",
    "prezzo": 25.628138
  },
  {
    "data": "2024-10-22",
    "prezzo": 25.579096
  },
  {
    "data": "2024-10-23",
    "prezzo": 24.803533
  },
  {
    "data": "2024-10-24",
    "prezzo": 24.774211
  },
  {
    "data": "2024-10-25",
    "prezzo": 23.106634
  },
  {
    "data": "2024-10-26",
    "prezzo": 23.528992
  },
  {
    "data": "2024-10-27",
    "prezzo": 23.832333
  },
  {
    "data": "2024-10-28",
    "prezzo": 24.249708
  },
  {
    "data": "2024-10-29",
    "prezzo": 24.801652
  },
  {
    "data": "2024-10-30",
    "prezzo": 24.097817
  },
  {
    "data": "2024-10-31",
    "prezzo": 22.969485
  },
  {
    "data": "2024-11-01",
    "prezzo": 22.885346
  },
  {
    "data": "2024-11-02",
    "prezzo": 22.299065
  },
  {
    "data": "2024-11-03",
    "prezzo": 21.677707
  },
  {
    "data": "2024-11-04",
    "prezzo": 20.889977
  },
  {
    "data": "2024-11-05",
    "prezzo": 21.955
  },
  {
    "data": "2024-11-06",
    "prezzo": 25.150495
  },
  {
    "data": "2024-11-07",
    "prezzo": 25.381711
  },
  {
    "data": "2024-11-08",
    "prezzo": 26.86409
  },
  {
    "data": "2024-11-09",
    "prezzo": 28.345
  },
  {
    "data": "2024-11-10",
    "prezzo": 29.058465
  },
  {
    "data": "2024-11-11",
    "prezzo": 32.87527
  },
  {
    "data": "2024-11-12",
    "prezzo": 31.837814
  },
  {
    "data": "2024-11-13",
    "prezzo": 31.278298
  },
  {
    "data": "2024-11-14",
    "prezzo": 29.618057
  },
  {
    "data": "2024-11-15",
    "prezzo": 31.385
  },
  {
    "data": "2024-11-16",
    "prezzo": 33.255
  },
  {
    "data": "2024-11-17",
    "prezzo": 33.663595
  },
  {
    "data": "2024-11-18",
    "prezzo": 33.358395
  },
  {
    "data": "2024-11-19",
    "prezzo": 32.299078
  },
  {
    "data": "2024-11-20",
    "prezzo": 31.830905
  },
  {
    "data": "2024-11-21",
    "prezzo": 34.021111
  },
  {
    "data": "2024-11-22",
    "prezzo": 41.423578
  },
  {
    "data": "2024-11-23",
    "prezzo": 39.56969
  },
  {
    "data": "2024-11-24",
    "prezzo": 40.049825
  },
  {
    "data": "2024-11-25",
    "prezzo": 39.51
  },
  {
    "data": "2024-11-26",
    "prezzo": 40.697956
  },
  {
    "data": "2024-11-27",
    "prezzo": 41.5
  },
  {
    "data": "2024-11-28",
    "prezzo": 40.514171
  },
  {
    "data": "2024-11-29",
    "prezzo": 42.419659
  },
  {
    "data": "2024-11-30",
    "prezzo": 42.365
  },
  {
    "data": "2024-12-01",
    "prezzo": 42.74451
  },
  {
    "data": "2024-12-02",
    "prezzo": 49.825165
  },
  {
    "data": "2024-12-03",
    "prezzo": 48.435
  },
  {
    "data": "2024-12-04",
    "prezzo": 50.19
  },
  {
    "data": "2024-12-05",
    "prezzo": 47.596055
  },
  {
    "data": "2024-12-06",
    "prezzo": 49.686093
  },
  {
    "data": "2024-12-07",
    "prezzo": 48.8
  },
  {
    "data": "2024-12-08",
    "prezzo": 51.077565
  },
  {
    "data": "2024-12-09",
    "prezzo": 42.82263
  },
  {
    "data": "2024-12-10",
    "prezzo": 42.405
  },
  {
    "data": "2024-12-11",
    "prezzo": 46.100897
  },
  {
    "data": "2024-12-12",
    "prezzo": 50.727055
  },
  {
    "data": "2024-12-13",
    "prezzo": 50.26627
  },
  {
    "data": "2024-12-14",
    "prezzo": 47.451941
  },
  {
    "data": "2024-12-15",
    "prezzo": 48.16537
  },
  {
    "data": "2024-12-16",
    "prezzo": 46.529914
  },
  {
    "data": "2024-12-17",
    "prezzo": 45.6247
  },
  {
    "data": "2024-12-18",
    "prezzo": 41.349375
  },
  {
    "data": "2024-12-19",
    "prezzo": 37.48869
  },
  {
    "data": "2024-12-20",
    "prezzo": 38.256408
  },
  {
    "data": "2024-12-21",
    "prezzo": 35.909074
  },
  {
    "data": "2024-12-22",
    "prezzo": 35.042385
  },
  {
    "data": "2024-12-23",
    "prezzo": 37.556398
  },
  {
    "data": "2024-12-24",
    "prezzo": 39.64109
  },
  {
    "data": "2024-12-25",
    "prezzo": 38.709155
  },
  {
    "data": "2024-12-26",
    "prezzo": 35.77176
  },
  {
    "data": "2024-12-27",
    "prezzo": 35.035
  },
  {
    "data": "2024-12-28",
    "prezzo": 36.147635
  },
  {
    "data": "2024-12-29",
    "prezzo": 34.31
  },
  {
    "data": "2024-12-30",
    "prezzo": 34.52577
  },
  {
    "data": "2024-12-31",
    "prezzo": 34.44726
  },
  {
    "data": "2025-01-01",
    "prezzo": 36.413105
  },
  {
    "data": "2025-01-02",
    "prezzo": 38.22635
  },
  {
    "data": "2025-01-03",
    "prezzo": 40.666018
  },
  {
    "data": "2025-01-04",
    "prezzo": 41.365995
  },
  {
    "data": "2025-01-05",
    "prezzo": 41.824817
  },
  {
    "data": "2025-01-06",
    "prezzo": 42.4532
  },
  {
    "data": "2025-01-07",
    "prezzo": 37.929775
  },
  {
    "data": "2025-01-08",
    "prezzo": 36.308833
  },
  {
    "data": "2025-01-09",
    "prezzo": 35.187132
  },
  {
    "data": "2025-01-10",
    "prezzo": 35.82208
  },
  {
    "data": "2025-01-11",
    "prezzo": 36.218729
  },
  {
    "data": "2025-01-12",
    "prezzo": 35.6706
  },
  {
    "data": "2025-01-13",
    "prezzo": 34.38818
  },
  {
    "data": "2025-01-14",
    "prezzo": 35.45657
  },
  {
    "data": "2025-01-15",
    "prezzo": 38.67753
  },
  {
    "data": "2025-01-16",
    "prezzo": 38.86
  },
  {
    "data": "2025-01-17",
    "prezzo": 40.211725
  },
  {
    "data": "2025-01-18",
    "prezzo": 38.09
  },
  {
    "data": "2025-01-19",
    "prezzo": 34.708663
  },
  {
    "data": "2025-01-20",
    "prezzo": 34.555
  },
  {
    "data": "2025-01-21",
    "prezzo": 35.514265
  },
  {
    "data": "2025-01-22",
    "prezzo": 35.362028
  },
  {
    "data": "2025-01-23",
    "prezzo": 34.153503
  },
  {
    "data": "2025-01-24",
    "prezzo": 33.7
  },
  {
    "data": "2025-01-25",
    "prezzo": 34.918563
  },
  {
    "data": "2025-01-26",
    "prezzo": 34.159801
  },
  {
    "data": "2025-01-27",
    "prezzo": 32.763175
  },
  {
    "data": "2025-01-28",
    "prezzo": 30.75
  },
  {
    "data": "2025-01-29",
    "prezzo": 31.460115
  },
  {
    "data": "2025-01-30",
    "prezzo": 32.98239
  },
  {
    "data": "2025-01-31",
    "prezzo": 33.19962
  },
  {
    "data": "2025-02-01",
    "prezzo": 31.054425
  },
  {
    "data": "2025-02-02",
    "prezzo": 26.974795
  },
  {
    "data": "2025-02-03",
    "prezzo": 27.54903
  },
  {
    "data": "2025-02-04",
    "prezzo": 25.528415
  },
  {
    "data": "2025-02-05",
    "prezzo": 24.86582
  },
  {
    "data": "2025-02-06",
    "prezzo": 23.615
  },
  {
    "data": "2025-02-07",
    "prezzo": 23.712941
  },
  {
    "data": "2025-02-08",
    "prezzo": 23.8451
  },
  {
    "data": "2025-02-09",
    "prezzo": 24.136715
  },
  {
    "data": "2025-02-10",
    "prezzo": 24.925
  },
  {
    "data": "2025-02-11",
    "prezzo": 24.523715
  },
  {
    "data": "2025-02-12",
    "prezzo": 25.50426
  },
  {
    "data": "2025-02-13",
    "prezzo": 24.275
  },
  {
    "data": "2025-02-14",
    "prezzo": 25.16801
  },
  {
    "data": "2025-02-15",
    "prezzo": 24.316831
  },
  {
    "data": "2025-02-16",
    "prezzo": 23.70854
  },
  {
    "data": "2025-02-17",
    "prezzo": 23.889235
  },
  {
    "data": "2025-02-18",
    "prezzo": 22.501532
  },
  {
    "data": "2025-02-19",
    "prezzo": 22.76803
  },
  {
    "data": "2025-02-20",
    "prezzo": 23.96665
  },
  {
    "data": "2025-02-21",
    "prezzo": 23.46214
  },
  {
    "data": "2025-02-22",
    "prezzo": 24.701615
  },
  {
    "data": "2025-02-23",
    "prezzo": 23.725998
  },
  {
    "data": "2025-02-24",
    "prezzo": 20.909895
  },
  {
    "data": "2025-02-25",
    "prezzo": 20.855
  },
  {
    "data": "2025-02-26",
    "prezzo": 20.82864
  },
  {
    "data": "2025-02-27",
    "prezzo": 21.64222
  },
  {
    "data": "2025-02-28",
    "prezzo": 21.56401
  },
  {
    "data": "2025-03-01",
    "prezzo": 21.088365
  },
  {
    "data": "2025-03-02",
    "prezzo": 23.97976
  },
  {
    "data": "2025-03-03",
    "prezzo": 19.9787
  },
  {
    "data": "2025-03-04",
    "prezzo": 18.841415
  },
  {
    "data": "2025-03-05",
    "prezzo": 20.138543
  },
  {
    "data": "2025-03-06",
    "prezzo": 19.477315
  },
  {
    "data": "2025-03-07",
    "prezzo": 18.58583
  },
  {
    "data": "2025-03-08",
    "prezzo": 18.92862
  },
  {
    "data": "2025-03-09",
    "prezzo": 16.542436
  },
  {
    "data": "2025-03-10",
    "prezzo": 14.987955
  },
  {
    "data": "2025-03-11",
    "prezzo": 16.044965
  },
  {
    "data": "2025-03-12",
    "prezzo": 17.38
  },
  {
    "data": "2025-03-13",
    "prezzo": 17.041069
  },
  {
    "data": "2025-03-14",
    "prezzo": 17.079315
  },
  {
    "data": "2025-03-15",
    "prezzo": 17.844969
  },
  {
    "data": "2025-03-16",
    "prezzo": 16.785
  },
  {
    "data": "2025-03-17",
    "prezzo": 17.238383
  },
  {
    "data": "2025-03-18",
    "prezzo": 17.349445
  },
  {
    "data": "2025-03-19",
    "prezzo": 18.091355
  },
  {
    "data": "2025-03-20",
    "prezzo": 17.26409
  },
  {
    "data": "2025-03-21",
    "prezzo": 17.725365
  },
  {
    "data": "2025-03-22",
    "prezzo": 17.953165
  },
  {
    "data": "2025-03-23",
    "prezzo": 18.28678
  },
  {
    "data": "2025-03-24",
    "prezzo": 19.886336
  },
  {
    "data": "2025-03-25",
    "prezzo": 21.234909
  },
  {
    "data": "2025-03-26",
    "prezzo": 20.52529
  },
  {
    "data": "2025-03-27",
    "prezzo": 20.380593
  },
  {
    "data": "2025-03-28",
    "prezzo": 18.804947
  },
  {
    "data": "2025-03-29",
    "prezzo": 18.10204
  },
  {
    "data": "2025-03-30",
    "prezzo": 17.42414
  },
  {
    "data": "2025-03-31",
    "prezzo": 17.351195
  },
  {
    "data": "2025-04-01",
    "prezzo": 18.36
  },
  {
    "data": "2025-04-02",
    "prezzo": 16.48722
  },
  {
    "data": "2025-04-03",
    "prezzo": 16.425655
  },
  {
    "data": "2025-04-04",
    "prezzo": 16.58885
  },
  {
    "data": "2025-04-05",
    "prezzo": 16.308253
  },
  {
    "data": "2025-04-06",
    "prezzo": 14.579167
  },
  {
    "data": "2025-04-07",
    "prezzo": 15.285
  },
  {
    "data": "2025-04-08",
    "prezzo": 14.695845
  },
  {
    "data": "2025-04-09",
    "prezzo": 16.84477
  },
  {
    "data": "2025-04-10",
    "prezzo": 16.266685
  },
  {
    "data": "2025-04-11",
    "prezzo": 16.835586
  },
  {
    "data": "2025-04-12",
    "prezzo": 18.055675
  },
  {
    "data": "2025-04-13",
    "prezzo": 17.268805
  },
  {
    "data": "2025-04-14",
    "prezzo": 17.751825
  },
  {
    "data": "2025-04-15",
    "prezzo": 16.845505
  },
  {
    "data": "2025-04-16",
    "prezzo": 16.451212
  },
  {
    "data": "2025-04-17",
    "prezzo": 16.750479
  },
  {
    "data": "2025-04-18",
    "prezzo": 16.745564
  },
  {
    "data": "2025-04-19",
    "prezzo": 17.463253
  },
  {
    "data": "2025-04-20",
    "prezzo": 17.04253
  },
  {
    "data": "2025-04-21",
    "prezzo": 17.295365
  },
  {
    "data": "2025-04-22",
    "prezzo": 19.448702
  },
  {
    "data": "2025-04-23",
    "prezzo": 19.722532
  },
  {
    "data": "2025-04-24",
    "prezzo": 19.687687
  },
  {
    "data": "2025-04-25",
    "prezzo": 19.518397
  },
  {
    "data": "2025-04-26",
    "prezzo": 19.734796
  },
  {
    "data": "2025-04-27",
    "prezzo": 19.148051
  },
  {
    "data": "2025-04-28",
    "prezzo": 19.149938
  },
  {
    "data": "2025-04-29",
    "prezzo": 18.941667
  },
  {
    "data": "2025-04-30",
    "prezzo": 18.475176
  },
  {
    "data": "2025-05-01",
    "prezzo": 19.154777
  },
  {
    "data": "2025-05-02",
    "prezzo": 18.813867
  },
  {
    "data": "2025-05-03",
    "prezzo": 18.17532
  },
  {
    "data": "2025-05-04",
    "prezzo": 17.582059
  },
  {
    "data": "2025-05-05",
    "prezzo": 17.402078
  },
  {
    "data": "2025-05-06",
    "prezzo": 17.640116
  },
  {
    "data": "2025-05-07",
    "prezzo": 17.291603
  },
  {
    "data": "2025-05-08",
    "prezzo": 19.718566
  },
  {
    "data": "2025-05-09",
    "prezzo": 20.668724
  },
  {
    "data": "2025-05-10",
    "prezzo": 22.914998
  },
  {
    "data": "2025-05-11",
    "prezzo": 22.070988
  },
  {
    "data": "2025-05-12",
    "prezzo": 22.373419
  },
  {
    "data": "2025-05-13",
    "prezzo": 22.998091
  },
  {
    "data": "2025-05-14",
    "prezzo": 22.31862
  },
  {
    "data": "2025-05-15",
    "prezzo": 21.014513
  },
  {
    "data": "2025-05-16",
    "prezzo": 20.652029
  },
  {
    "data": "2025-05-17",
    "prezzo": 19.865245
  },
  {
    "data": "2025-05-18",
    "prezzo": 20.604288
  },
  {
    "data": "2025-05-19",
    "prezzo": 19.821021
  },
  {
    "data": "2025-05-20",
    "prezzo": 20.033546
  },
  {
    "data": "2025-05-21",
    "prezzo": 20.451645
  },
  {
    "data": "2025-05-22",
    "prezzo": 22.368872
  },
  {
    "data": "2025-05-23",
    "prezzo": 20.309773
  },
  {
    "data": "2025-05-24",
    "prezzo": 20.208126
  },
  {
    "data": "2025-05-25",
    "prezzo": 20.608753
  },
  {
    "data": "2025-05-26",
    "prezzo": 20.25692
  },
  {
    "data": "2025-05-27",
    "prezzo": 20.62186
  },
  {
    "data": "2025-05-28",
    "prezzo": 21.013181
  },
  {
    "data": "2025-05-29",
    "prezzo": 19.561713
  },
  {
    "data": "2025-05-30",
    "prezzo": 18.124235
  },
  {
    "data": "2025-05-31",
    "prezzo": 18.353419
  },
  {
    "data": "2025-06-01",
    "prezzo": 18.408909
  },
  {
    "data": "2025-06-02",
    "prezzo": 18.481552
  },
  {
    "data": "2025-06-03",
    "prezzo": 18.584513
  },
  {
    "data": "2025-06-04",
    "prezzo": 17.599945
  },
  {
    "data": "2025-06-05",
    "prezzo": 16.381053
  },
  {
    "data": "2025-06-06",
    "prezzo": 17.261185
  },
  {
    "data": "2025-06-07",
    "prezzo": 18.134459
  },
  {
    "data": "2025-06-08",
    "prezzo": 18.462749
  },
  {
    "data": "2025-06-09",
    "prezzo": 19.216716
  },
  {
    "data": "2025-06-10",
    "prezzo": 19.733835
  },
  {
    "data": "2025-06-11",
    "prezzo": 18.745237
  },
  {
    "data": "2025-06-12",
    "prezzo": 17.489884
  },
  {
    "data": "2025-06-13",
    "prezzo": 16.82588
  },
  {
    "data": "2025-06-14",
    "prezzo": 16.413945
  },
  {
    "data": "2025-06-15",
    "prezzo": 16.568758
  },
  {
    "data": "2025-06-16",
    "prezzo": 16.482703
  },
  {
    "data": "2025-06-17",
    "prezzo": 16.183403
  },
  {
    "data": "2025-06-18",
    "prezzo": 15.827808
  },
  {
    "data": "2025-06-19",
    "prezzo": 15.682842
  },
  {
    "data": "2025-06-20",
    "prezzo": 15.078648
  },
  {
    "data": "2025-06-21",
    "prezzo": 14.614972
  },
  {
    "data": "2025-06-22",
    "prezzo": 14.375038
  },
  {
    "data": "2025-06-23",
    "prezzo": 15.593862
  },
  {
    "data": "2025-06-24",
    "prezzo": 15.704396
  },
  {
    "data": "2025-06-25",
    "prezzo": 15.052118
  },
  {
    "data": "2025-06-26",
    "prezzo": 14.741719
  },
  {
    "data": "2025-06-27",
    "prezzo": 15.014255
  },
  {
    "data": "2025-06-28",
    "prezzo": 15.352743
  },
  {
    "data": "2025-06-29",
    "prezzo": 15.987262
  },
  {
    "data": "2025-06-30",
    "prezzo": 15.248771
  },
  {
    "data": "2025-07-01",
    "prezzo": 14.494686
  },
  {
    "data": "2025-07-02",
    "prezzo": 15.693756
  },
  {
    "data": "2025-07-03",
    "prezzo": 15.763503
  },
  {
    "data": "2025-07-04",
    "prezzo": 15.119564
  },
  {
    "data": "2025-07-05",
    "prezzo": 15.228072
  },
  {
    "data": "2025-07-06",
    "prezzo": 15.52928
  },
  {
    "data": "2025-07-07",
    "prezzo": 15.335074
  },
  {
    "data": "2025-07-08",
    "prezzo": 15.664758
  },
  {
    "data": "2025-07-09",
    "prezzo": 16.61681
  },
  {
    "data": "2025-07-10",
    "prezzo": 17.650146
  },
  {
    "data": "2025-07-11",
    "prezzo": 17.604492
  },
  {
    "data": "2025-07-12",
    "prezzo": 17.581271
  },
  {
    "data": "2025-07-13",
    "prezzo": 18.09056
  },
  {
    "data": "2025-07-14",
    "prezzo": 18.215967
  },
  {
    "data": "2025-07-15",
    "prezzo": 19.385535
  },
  {
    "data": "2025-07-16",
    "prezzo": 19.476646
  },
  {
    "data": "2025-07-17",
    "prezzo": 20.563647
  },
  {
    "data": "2025-07-18",
    "prezzo": 20.223965
  },
  {
    "data": "2025-07-19",
    "prezzo": 21.069061
  },
  {
    "data": "2025-07-20",
    "prezzo": 21.535624
  },
  {
    "data": "2025-07-21",
    "prezzo": 21.753949
  },
  {
    "data": "2025-07-22",
    "prezzo": 22.056148
  },
  {
    "data": "2025-07-23",
    "prezzo": 20.350234
  },
  {
    "data": "2025-07-24",
    "prezzo": 20.132149
  },
  {
    "data": "2025-07-25",
    "prezzo": 20.437522
  },
  {
    "data": "2025-07-26",
    "prezzo": 21.229407
  },
  {
    "data": "2025-07-27",
    "prezzo": 22.147216
  },
  {
    "data": "2025-07-28",
    "prezzo": 21.722619
  },
  {
    "data": "2025-07-29",
    "prezzo": 21.095468
  },
  {
    "data": "2025-07-30",
    "prezzo": 20.390136
  },
  {
    "data": "2025-07-31",
    "prezzo": 19.67779
  },
  {
    "data": "2025-08-01",
    "prezzo": 18.585794
  },
  {
    "data": "2025-08-02",
    "prezzo": 18.016722
  },
  {
    "data": "2025-08-03",
    "prezzo": 18.464903
  },
  {
    "data": "2025-08-04",
    "prezzo": 19.952188
  },
  {
    "data": "2025-08-05",
    "prezzo": 18.924003
  },
  {
    "data": "2025-08-06",
    "prezzo": 19.068539
  },
  {
    "data": "2025-08-07",
    "prezzo": 20.003518
  },
  {
    "data": "2025-08-08",
    "prezzo": 20.427049
  },
  {
    "data": "2025-08-09",
    "prezzo": 20.73507
  },
  {
    "data": "2025-08-10",
    "prezzo": 20.446222
  },
  {
    "data": "2025-08-11",
    "prezzo": 19.618062
  },
  {
    "data": "2025-08-12",
    "prezzo": 21.115214
  },
  {
    "data": "2025-08-13",
    "prezzo": 21.683351
  },
  {
    "data": "2025-08-14",
    "prezzo": 20.324512
  },
  {
    "data": "2025-08-15",
    "prezzo": 20.338936
  },
  {
    "data": "2025-08-16",
    "prezzo": 20.803423
  },
  {
    "data": "2025-08-17",
    "prezzo": 21.428291
  },
  {
    "data": "2025-08-18",
    "prezzo": 20.322321
  },
  {
    "data": "2025-08-19",
    "prezzo": 19.206114
  },
  {
    "data": "2025-08-20",
    "prezzo": 20.132677
  },
  {
    "data": "2025-08-21",
    "prezzo": 19.604695
  },
  {
    "data": "2025-08-22",
    "prezzo": 21.436878
  },
  {
    "data": "2025-08-23",
    "prezzo": 22.276808
  },
  {
    "data": "2025-08-24",
    "prezzo": 22.015295
  },
  {
    "data": "2025-08-25",
    "prezzo": 20.114645
  },
  {
    "data": "2025-08-26",
    "prezzo": 20.778287
  },
  {
    "data": "2025-08-27",
    "prezzo": 20.974524
  },
  {
    "data": "2025-08-28",
    "prezzo": 21.349199
  },
  {
    "data": "2025-08-29",
    "prezzo": 20.163409
  },
  {
    "data": "2025-08-30",
    "prezzo": 20.364533
  },
  {
    "data": "2025-08-31",
    "prezzo": 20.017558
  },
  {
    "data": "2025-09-01",
    "prezzo": 19.815432
  },
  {
    "data": "2025-09-02",
    "prezzo": 21.018837
  },
  {
    "data": "2025-09-03",
    "prezzo": 21.607142
  },
  {
    "data": "2025-09-04",
    "prezzo": 20.776685
  },
  {
    "data": "2025-09-05",
    "prezzo": 20.899182
  },
  {
    "data": "2025-09-06",
    "prezzo": 20.820166
  },
  {
    "data": "2025-09-07",
    "prezzo": 21.079679
  },
  {
    "data": "2025-09-08",
    "prezzo": 21.484157
  },
  {
    "data": "2025-09-09",
    "prezzo": 22.162314
  },
  {
    "data": "2025-09-10",
    "prezzo": 25.181242
  },
  {
    "data": "2025-09-11",
    "prezzo": 24.848543
  },
  {
    "data": "2025-09-12",
    "prezzo": 24.696386
  },
  {
    "data": "2025-09-13",
    "prezzo": 25.585383
  },
  {
    "data": "2025-09-14",
    "prezzo": 25.115844
  },
  {
    "data": "2025-09-15",
    "prezzo": 25.343488
  },
  {
    "data": "2025-09-16",
    "prezzo": 25.344467
  },
  {
    "data": "2025-09-17",
    "prezzo": 26.908842
  },
  {
    "data": "2025-09-18",
    "prezzo": 29.86426
  },
  {
    "data": "2025-09-19",
    "prezzo": 28.754429
  },
  {
    "data": "2025-09-20",
    "prezzo": 28.292223
  },
  {
    "data": "2025-09-21",
    "prezzo": 28.165778
  },
  {
    "data": "2025-09-22",
    "prezzo": 28.726623
  },
  {
    "data": "2025-09-23",
    "prezzo": 28.45493
  },
  {
    "data": "2025-09-24",
    "prezzo": 27.526212
  },
  {
    "data": "2025-09-25",
    "prezzo": 24.5683
  },
  {
    "data": "2025-09-26",
    "prezzo": 24.901775
  },
  {
    "data": "2025-09-27",
    "prezzo": 24.603055
  },
  {
    "data": "2025-09-28",
    "prezzo": 25.639218
  },
  {
    "data": "2025-09-29",
    "prezzo": 25.939899
  },
  {
    "data": "2025-09-30",
    "prezzo": 25.576122
  },
  {
    "data": "2025-10-01",
    "prezzo": 26.191614
  },
  {
    "data": "2025-10-02",
    "prezzo": 26.413557
  },
  {
    "data": "2025-10-03",
    "prezzo": 26.644607
  },
  {
    "data": "2025-10-04",
    "prezzo": 25.598616
  },
  {
    "data": "2025-10-05",
    "prezzo": 25.590791
  },
  {
    "data": "2025-10-06",
    "prezzo": 26.093086
  },
  {
    "data": "2025-10-07",
    "prezzo": 23.965605
  },
  {
    "data": "2025-10-08",
    "prezzo": 24.766178
  },
  {
    "data": "2025-10-09",
    "prezzo": 24.53742
  },
  {
    "data": "2025-10-10",
    "prezzo": 18.070144
  },
  {
    "data": "2025-10-11",
    "prezzo": 18.727231
  },
  {
    "data": "2025-10-12",
    "prezzo": 19.444096
  },
  {
    "data": "2025-10-13",
    "prezzo": 20.614912
  },
  {
    "data": "2025-10-14",
    "prezzo": 19.61909
  },
  {
    "data": "2025-10-15",
    "prezzo": 18.814362
  },
  {
    "data": "2025-10-16",
    "prezzo": 17.941591
  },
  {
    "data": "2025-10-17",
    "prezzo": 17.14951
  },
  {
    "data": "2025-10-18",
    "prezzo": 17.371455
  },
  {
    "data": "2025-10-19",
    "prezzo": 17.681798
  },
  {
    "data": "2025-10-20",
    "prezzo": 17.480055
  },
  {
    "data": "2025-10-21",
    "prezzo": 16.848089
  },
  {
    "data": "2025-10-22",
    "prezzo": 16.386048
  },
  {
    "data": "2025-10-23",
    "prezzo": 16.468026
  },
  {
    "data": "2025-10-24",
    "prezzo": 16.774365
  },
  {
    "data": "2025-10-25",
    "prezzo": 16.953975
  },
  {
    "data": "2025-10-26",
    "prezzo": 17.899609
  },
  {
    "data": "2025-10-27",
    "prezzo": 17.446089
  },
  {
    "data": "2025-10-28",
    "prezzo": 16.724169
  },
  {
    "data": "2025-10-29",
    "prezzo": 16.940883
  },
  {
    "data": "2025-10-30",
    "prezzo": 15.665548
  },
  {
    "data": "2025-10-31",
    "prezzo": 15.760914
  },
  {
    "data": "2025-11-01",
    "prezzo": 16.203561
  },
  {
    "data": "2025-11-02",
    "prezzo": 16.311612
  },
  {
    "data": "2025-11-03",
    "prezzo": 14.454694
  },
  {
    "data": "2025-11-04",
    "prezzo": 13.927563
  },
  {
    "data": "2025-11-05",
    "prezzo": 14.44684
  },
  {
    "data": "2025-11-06",
    "prezzo": 13.959267
  },
  {
    "data": "2025-11-07",
    "prezzo": 15.33324
  },
  {
    "data": "2025-11-08",
    "prezzo": 15.119457
  },
  {
    "data": "2025-11-09",
    "prezzo": 15.387108
  },
  {
    "data": "2025-11-10",
    "prezzo": 15.718075
  },
  {
    "data": "2025-11-11",
    "prezzo": 14.675487
  },
  {
    "data": "2025-11-12",
    "prezzo": 14.512189
  },
  {
    "data": "2025-11-13",
    "prezzo": 13.84189
  },
  {
    "data": "2025-11-14",
    "prezzo": 13.010511
  },
  {
    "data": "2025-11-15",
    "prezzo": 13.360858
  },
  {
    "data": "2025-11-16",
    "prezzo": 13.019572
  },
  {
    "data": "2025-11-17",
    "prezzo": 12.504636
  },
  {
    "data": "2025-11-18",
    "prezzo": 12.585051
  },
  {
    "data": "2025-11-19",
    "prezzo": 12.366158
  },
  {
    "data": "2025-11-20",
    "prezzo": 11.963017
  },
  {
    "data": "2025-11-21",
    "prezzo": 11.541567
  },
  {
    "data": "2025-11-22",
    "prezzo": 11.500821
  },
  {
    "data": "2025-11-23",
    "prezzo": 11.544794
  },
  {
    "data": "2025-11-24",
    "prezzo": 12.063255
  },
  {
    "data": "2025-11-25",
    "prezzo": 12.256889
  },
  {
    "data": "2025-11-26",
    "prezzo": 12.895182
  },
  {
    "data": "2025-11-27",
    "prezzo": 12.95776
  },
  {
    "data": "2025-11-28",
    "prezzo": 12.812197
  },
  {
    "data": "2025-11-29",
    "prezzo": 12.304773
  },
  {
    "data": "2025-11-30",
    "prezzo": 11.82357
  },
  {
    "data": "2025-12-01",
    "prezzo": 10.993872
  },
  {
    "data": "2025-12-02",
    "prezzo": 11.72313
  },
  {
    "data": "2025-12-03",
    "prezzo": 12.674719
  },
  {
    "data": "2025-12-04",
    "prezzo": 12.374574
  },
  {
    "data": "2025-12-05",
    "prezzo": 11.361289
  },
  {
    "data": "2025-12-06",
    "prezzo": 11.527568
  },
  {
    "data": "2025-12-07",
    "prezzo": 11.598762
  },
  {
    "data": "2025-12-08",
    "prezzo": 11.726847
  },
  {
    "data": "2025-12-09",
    "prezzo": 12.554435
  },
  {
    "data": "2025-12-10",
    "prezzo": 12.068604
  },
  {
    "data": "2025-12-11",
    "prezzo": 11.435579
  },
  {
    "data": "2025-12-12",
    "prezzo": 11.176022
  },
  {
    "data": "2025-12-13",
    "prezzo": 11.401725
  },
  {
    "data": "2025-12-14",
    "prezzo": 10.975843
  },
  {
    "data": "2025-12-15",
    "prezzo": 10.506119
  },
  {
    "data": "2025-12-16",
    "prezzo": 10.504605
  },
  {
    "data": "2025-12-17",
    "prezzo": 10.096464
  },
  {
    "data": "2025-12-18",
    "prezzo": 9.755657
  },
  {
    "data": "2025-12-19",
    "prezzo": 10.460211
  },
  {
    "data": "2025-12-20",
    "prezzo": 10.427294
  },
  {
    "data": "2025-12-21",
    "prezzo": 10.365445
  },
  {
    "data": "2025-12-22",
    "prezzo": 10.54771
  },
  {
    "data": "2025-12-23",
    "prezzo": 10.323882
  },
  {
    "data": "2025-12-24",
    "prezzo": 10.273154
  },
  {
    "data": "2025-12-25",
    "prezzo": 10.250872
  },
  {
    "data": "2025-12-26",
    "prezzo": 10.483463
  },
  {
    "data": "2025-12-27",
    "prezzo": 10.773637
  },
  {
    "data": "2025-12-28",
    "prezzo": 10.72674
  },
  {
    "data": "2025-12-29",
    "prezzo": 10.500091
  },
  {
    "data": "2025-12-30",
    "prezzo": 10.697823
  },
  {
    "data": "2025-12-31",
    "prezzo": 10.460678
  },
  {
    "data": "2026-01-01",
    "prezzo": 11.545004
  },
  {
    "data": "2026-01-02",
    "prezzo": 11.788572
  },
  {
    "data": "2026-01-03",
    "prezzo": 11.939798
  },
  {
    "data": "2026-01-04",
    "prezzo": 12.170369
  },
  {
    "data": "2026-01-05",
    "prezzo": 12.340876
  },
  {
    "data": "2026-01-06",
    "prezzo": 12.484076
  },
  {
    "data": "2026-01-07",
    "prezzo": 12.084359
  },
  {
    "data": "2026-01-08",
    "prezzo": 11.905518
  },
  {
    "data": "2026-01-09",
    "prezzo": 11.842598
  },
  {
    "data": "2026-01-10",
    "prezzo": 11.799647
  },
  {
    "data": "2026-01-11",
    "prezzo": 11.765701
  },
  {
    "data": "2026-01-12",
    "prezzo": 11.574151
  },
  {
    "data": "2026-01-13",
    "prezzo": 12.654312
  },
  {
    "data": "2026-01-14",
    "prezzo": 12.542885
  },
  {
    "data": "2026-01-15",
    "prezzo": 11.90718
  },
  {
    "data": "2026-01-16",
    "prezzo": 11.708598
  },
  {
    "data": "2026-01-17",
    "prezzo": 11.857218
  },
  {
    "data": "2026-01-18",
    "prezzo": 11.165266
  },
  {
    "data": "2026-01-19",
    "prezzo": 10.93509
  },
  {
    "data": "2026-01-20",
    "prezzo": 10.302215
  },
  {
    "data": "2026-01-21",
    "prezzo": 10.626068
  },
  {
    "data": "2026-01-22",
    "prezzo": 10.366469
  },
  {
    "data": "2026-01-23",
    "prezzo": 10.246408
  },
  {
    "data": "2026-01-24",
    "prezzo": 10.174825
  },
  {
    "data": "2026-01-25",
    "prezzo": 9.685516
  },
  {
    "data": "2026-01-26",
    "prezzo": 9.860581
  },
  {
    "data": "2026-01-27",
    "prezzo": 10.082924
  },
  {
    "data": "2026-01-28",
    "prezzo": 10.071716
  },
  {
    "data": "2026-01-29",
    "prezzo": 9.218996
  },
  {
    "data": "2026-01-30",
    "prezzo": 9.167719
  },
  {
    "data": "2026-01-31",
    "prezzo": 8.556617
  },
  {
    "data": "2026-02-01",
    "prezzo": 8.363199
  },
  {
    "data": "2026-02-02",
    "prezzo": 8.595509
  },
  {
    "data": "2026-02-03",
    "prezzo": 8.393406
  },
  {
    "data": "2026-02-04",
    "prezzo": 8.21545
  },
  {
    "data": "2026-02-05",
    "prezzo": 7.04934
  },
  {
    "data": "2026-02-06",
    "prezzo": 7.865215
  },
  {
    "data": "2026-02-07",
    "prezzo": 7.823114
  },
  {
    "data": "2026-02-08",
    "prezzo": 7.682689
  },
  {
    "data": "2026-02-09",
    "prezzo": 7.604625
  },
  {
    "data": "2026-02-10",
    "prezzo": 7.365335
  },
  {
    "data": "2026-02-11",
    "prezzo": 7.269369
  },
  {
    "data": "2026-02-12",
    "prezzo": 7.498405
  },
  {
    "data": "2026-02-13",
    "prezzo": 7.707688
  },
  {
    "data": "2026-02-14",
    "prezzo": 8.096985
  },
  {
    "data": "2026-02-15",
    "prezzo": 7.818611
  },
  {
    "data": "2026-02-16",
    "prezzo": 7.813228
  },
  {
    "data": "2026-02-17",
    "prezzo": 7.711568
  },
  {
    "data": "2026-02-18",
    "prezzo": 7.512858
  },
  {
    "data": "2026-02-19",
    "prezzo": 7.559324
  },
  {
    "data": "2026-02-20",
    "prezzo": 7.782534
  },
  {
    "data": "2026-02-21",
    "prezzo": 7.739575
  },
  {
    "data": "2026-02-22",
    "prezzo": 7.502917
  },
  {
    "data": "2026-02-23",
    "prezzo": 7.09008
  },
  {
    "data": "2026-02-24",
    "prezzo": 7.036347
  },
  {
    "data": "2026-02-25",
    "prezzo": 8.052746
  },
  {
    "data": "2026-02-26",
    "prezzo": 7.890411
  },
  {
    "data": "2026-02-27",
    "prezzo": 7.586385
  },
  {
    "data": "2026-02-28",
    "prezzo": 7.767717
  },
  {
    "data": "2026-03-01",
    "prezzo": 7.679908
  },
  {
    "data": "2026-03-02",
    "prezzo": 7.844132
  },
  {
    "data": "2026-03-03",
    "prezzo": 7.905462
  },
  {
    "data": "2026-03-04",
    "prezzo": 8.169933
  },
  {
    "data": "2026-03-05",
    "prezzo": 8.085612
  },
  {
    "data": "2026-03-06",
    "prezzo": 7.772173
  },
  {
    "data": "2026-03-07",
    "prezzo": 7.683161
  },
  {
    "data": "2026-03-08",
    "prezzo": 7.654747
  },
  {
    "data": "2026-03-09",
    "prezzo": 7.975839
  },
  {
    "data": "2026-03-10",
    "prezzo": 8.214592
  },
  {
    "data": "2026-03-11",
    "prezzo": 8.274899
  },
  {
    "data": "2026-03-12",
    "prezzo": 8.399289
  },
  {
    "data": "2026-03-13",
    "prezzo": 8.512477
  },
  {
    "data": "2026-03-14",
    "prezzo": 8.534481
  },
  {
    "data": "2026-03-15",
    "prezzo": 8.704668
  },
  {
    "data": "2026-03-16",
    "prezzo": 9.115582
  },
  {
    "data": "2026-03-17",
    "prezzo": 8.841204
  },
  {
    "data": "2026-03-18",
    "prezzo": 8.45131
  },
  {
    "data": "2026-03-19",
    "prezzo": 8.183853
  },
  {
    "data": "2026-03-20",
    "prezzo": 8.274403
  },
  {
    "data": "2026-03-21",
    "prezzo": 7.967389
  },
  {
    "data": "2026-03-22",
    "prezzo": 7.805247
  },
  {
    "data": "2026-03-23",
    "prezzo": 8.240236
  },
  {
    "data": "2026-03-24",
    "prezzo": 8.285179
  },
  {
    "data": "2026-03-25",
    "prezzo": 8.372646
  },
  {
    "data": "2026-03-26",
    "prezzo": 7.885605
  },
  {
    "data": "2026-03-27",
    "prezzo": 7.634361
  },
  {
    "data": "2026-03-28",
    "prezzo": 7.615027
  },
  {
    "data": "2026-03-29",
    "prezzo": 7.484304
  },
  {
    "data": "2026-03-30",
    "prezzo": 7.684852
  }
]