{
    "ultimo_valore_indice": 8409.064045461782,
    "variazione_24h_pct": 0.006268053767981785,
    "variazione_7g_pct": 0.012079937311917588,
    "variazione_ytd_pct": -0.29719585579842256,
    "ultima_allocazione_pesi": {
        "LINK": 0.6142962529428609,
        "UNI": 0.1951995938486798,
        "SKY": 0.19050415320845923
    },
    "capitalizzazione_mercato": {
        "LINK": 5533617401.9571,
        "UNI": 1684445811.9611,
        "SKY": 1546264777.5145383
    },
    "rendimenti_annuali": {
        "2021": -37.8,
        "2022": -69.0,
        "2023": 89.7,
        "2024": 50.3,
        "2025": -55.5,
        "2026": -29.7
    },
    "benchmark_annuali": {
        "2021": -17.0,
        "2022": -62.1,
        "2023": 149.0,
        "2024": 134.7,
        "2025": -17.4,
        "2026": -17.5
    }
}